<railLog>
	<railEvents>
        <Track direction="null" sectionID="sec_BellsGateLoop" trackID="trk_BellsGateLoop_1"/>
        <TrainEnterTrack cycleID="77" direction="UP" sectionID="sec_BellsGateLoop" speed="0.2" time="26.122878846654775" trackID="trk_BellsGateLoop_1" trainID="train25"/>
        <TrainHeadLeaveTrack cycleID="77" direction="UP" sectionID="sec_BellsGateLoop" speed="0.2" time="26.15628659734216" trackID="trk_BellsGateLoop_1" trainID="train25"/>
        <TrainTailLeaveTrack cycleID="77" direction="UP" sectionID="sec_BellsGateLoop" speed="30632.967032967033" time="26.195460079907807" trackID="trk_BellsGateLoop_1" trainID="train25"/>
        <TrainEnterTrack cycleID="80" direction="UP" sectionID="sec_BellsGateLoop" speed="0.2" time="35.88640757820579" trackID="trk_BellsGateLoop_1" trainID="train30"/>
        <TrainHeadLeaveTrack cycleID="80" direction="UP" sectionID="sec_BellsGateLoop" speed="0.2" time="35.91981532889317" trackID="trk_BellsGateLoop_1" trainID="train30"/>
        <TrainTailLeaveTrack cycleID="80" direction="UP" sectionID="sec_BellsGateLoop" speed="30632.967032967033" time="35.95898881145882" trackID="trk_BellsGateLoop_1" trainID="train30"/>
        <TrainEnterTrack cycleID="89" direction="UP" sectionID="sec_BellsGateLoop" speed="0.2" time="47.0397230902212" trackID="trk_BellsGateLoop_1" trainID="train35"/>
        <TrainHeadLeaveTrack cycleID="89" direction="UP" sectionID="sec_BellsGateLoop" speed="0.2" time="47.07313084090858" trackID="trk_BellsGateLoop_1" trainID="train35"/>
        <TrainTailLeaveTrack cycleID="89" direction="UP" sectionID="sec_BellsGateLoop" speed="30632.967032967033" time="47.112304323474234" trackID="trk_BellsGateLoop_1" trainID="train35"/>
        <TrainEnterTrack cycleID="92" direction="UP" sectionID="sec_BellsGateLoop" speed="0.2" time="50.321268390885784" trackID="trk_BellsGateLoop_1" trainID="train38"/>
        <TrainHeadLeaveTrack cycleID="92" direction="UP" sectionID="sec_BellsGateLoop" speed="0.2" time="50.354676141573165" trackID="trk_BellsGateLoop_1" trainID="train38"/>
        <TrainTailLeaveTrack cycleID="92" direction="UP" sectionID="sec_BellsGateLoop" speed="30632.967032967033" time="50.39384962413882" trackID="trk_BellsGateLoop_1" trainID="train38"/>
        <TrainEnterTrack cycleID="102" direction="UP" sectionID="sec_BellsGateLoop" speed="0.2" time="54.91341132365349" trackID="trk_BellsGateLoop_1" trainID="train48"/>
        <TrainHeadLeaveTrack cycleID="102" direction="UP" sectionID="sec_BellsGateLoop" speed="0.2" time="54.94681907434087" trackID="trk_BellsGateLoop_1" trainID="train48"/>
        <TrainTailLeaveTrack cycleID="102" direction="UP" sectionID="sec_BellsGateLoop" speed="30632.967032967033" time="54.985992556906524" trackID="trk_BellsGateLoop_1" trainID="train48"/>
        <TrainEnterTrack cycleID="129" direction="UP" sectionID="sec_BellsGateLoop" speed="0.2" time="58.82288107801323" trackID="trk_BellsGateLoop_1" trainID="train18"/>
        <TrainHeadLeaveTrack cycleID="129" direction="UP" sectionID="sec_BellsGateLoop" speed="0.2" time="58.85628882870061" trackID="trk_BellsGateLoop_1" trainID="train18"/>
        <TrainTailLeaveTrack cycleID="129" direction="UP" sectionID="sec_BellsGateLoop" speed="30632.967032967033" time="58.895462311266265" trackID="trk_BellsGateLoop_1" trainID="train18"/>
        <TrainEnterTrack cycleID="115" direction="UP" sectionID="sec_BellsGateLoop" speed="0.2" time="61.775491102134716" trackID="trk_BellsGateLoop_1" trainID="train7"/>
        <TrainHeadLeaveTrack cycleID="115" direction="UP" sectionID="sec_BellsGateLoop" speed="0.2" time="61.8088988528221" trackID="trk_BellsGateLoop_1" trainID="train7"/>
        <TrainTailLeaveTrack cycleID="115" direction="UP" sectionID="sec_BellsGateLoop" speed="30632.967032967033" time="61.84807233538775" trackID="trk_BellsGateLoop_1" trainID="train7"/>
        <TrainEnterTrack cycleID="118" direction="UP" sectionID="sec_BellsGateLoop" speed="0.2" time="66.5988924221084" trackID="trk_BellsGateLoop_1" trainID="train6"/>
        <TrainHeadLeaveTrack cycleID="118" direction="UP" sectionID="sec_BellsGateLoop" speed="0.2" time="66.6323001727958" trackID="trk_BellsGateLoop_1" trainID="train6"/>
        <TrainTailLeaveTrack cycleID="118" direction="UP" sectionID="sec_BellsGateLoop" speed="30632.967032967033" time="66.66494474160051" trackID="trk_BellsGateLoop_1" trainID="train6"/>
        <TrainEnterTrack cycleID="124" direction="UP" sectionID="sec_BellsGateLoop" speed="0.2" time="69.91637435586672" trackID="trk_BellsGateLoop_1" trainID="train14"/>
        <TrainHeadLeaveTrack cycleID="124" direction="UP" sectionID="sec_BellsGateLoop" speed="0.2" time="69.94978210655411" trackID="trk_BellsGateLoop_1" trainID="train14"/>
        <TrainTailLeaveTrack cycleID="124" direction="UP" sectionID="sec_BellsGateLoop" speed="30632.967032967033" time="69.98895558911975" trackID="trk_BellsGateLoop_1" trainID="train14"/>
        <TrainEnterTrack cycleID="132" direction="UP" sectionID="sec_BellsGateLoop" speed="0.2" time="75.28823883336514" trackID="trk_BellsGateLoop_1" trainID="train25"/>
        <TrainHeadLeaveTrack cycleID="132" direction="UP" sectionID="sec_BellsGateLoop" speed="0.2" time="75.32164658405253" trackID="trk_BellsGateLoop_1" trainID="train25"/>
        <TrainTailLeaveTrack cycleID="132" direction="UP" sectionID="sec_BellsGateLoop" speed="30632.967032967033" time="75.36082006661817" trackID="trk_BellsGateLoop_1" trainID="train25"/>
        <TrainEnterTrack cycleID="140" direction="UP" sectionID="sec_BellsGateLoop" speed="0.2" time="76.98822365644561" trackID="trk_BellsGateLoop_1" trainID="train44"/>
        <TrainHeadLeaveTrack cycleID="140" direction="UP" sectionID="sec_BellsGateLoop" speed="0.2" time="77.021631407133" trackID="trk_BellsGateLoop_1" trainID="train44"/>
        <TrainTailLeaveTrack cycleID="140" direction="UP" sectionID="sec_BellsGateLoop" speed="30632.967032967033" time="77.06080488969864" trackID="trk_BellsGateLoop_1" trainID="train44"/>
        <TrainEnterTrack cycleID="149" direction="UP" sectionID="sec_BellsGateLoop" speed="0.2" time="81.09059039191978" trackID="trk_BellsGateLoop_1" trainID="train35"/>
        <TrainHeadLeaveTrack cycleID="149" direction="UP" sectionID="sec_BellsGateLoop" speed="0.2" time="81.12399814260716" trackID="trk_BellsGateLoop_1" trainID="train35"/>
        <TrainTailLeaveTrack cycleID="149" direction="UP" sectionID="sec_BellsGateLoop" speed="30632.967032967033" time="81.16317162517281" trackID="trk_BellsGateLoop_1" trainID="train35"/>
        <TrainEnterTrack cycleID="137" direction="UP" sectionID="sec_BellsGateLoop" speed="0.2" time="82.61338450701622" trackID="trk_BellsGateLoop_1" trainID="train30"/>
        <TrainHeadLeaveTrack cycleID="137" direction="UP" sectionID="sec_BellsGateLoop" speed="0.2" time="82.64679225770361" trackID="trk_BellsGateLoop_1" trainID="train30"/>
        <TrainTailLeaveTrack cycleID="137" direction="UP" sectionID="sec_BellsGateLoop" speed="30632.967032967033" time="82.68596574026925" trackID="trk_BellsGateLoop_1" trainID="train30"/>
        <TrainEnterTrack cycleID="142" direction="UP" sectionID="sec_BellsGateLoop" speed="0.2" time="84.1629101754703" trackID="trk_BellsGateLoop_1" trainID="train47"/>
        <TrainHeadLeaveTrack cycleID="142" direction="UP" sectionID="sec_BellsGateLoop" speed="0.2" time="84.19631792615769" trackID="trk_BellsGateLoop_1" trainID="train47"/>
        <TrainTailLeaveTrack cycleID="142" direction="UP" sectionID="sec_BellsGateLoop" speed="30632.967032967033" time="84.23549140872333" trackID="trk_BellsGateLoop_1" trainID="train47"/>
        <TrainEnterTrack cycleID="161" direction="UP" sectionID="sec_BellsGateLoop" speed="0.2" time="87.81186429755846" trackID="trk_BellsGateLoop_1" trainID="train18"/>
        <TrainHeadLeaveTrack cycleID="161" direction="UP" sectionID="sec_BellsGateLoop" speed="0.2" time="87.84527204824585" trackID="trk_BellsGateLoop_1" trainID="train18"/>
        <TrainTailLeaveTrack cycleID="161" direction="UP" sectionID="sec_BellsGateLoop" speed="30632.967032967033" time="87.88444553081149" trackID="trk_BellsGateLoop_1" trainID="train18"/>
        <TrainEnterTrack cycleID="152" direction="UP" sectionID="sec_BellsGateLoop" speed="0.2" time="90.53400318669937" trackID="trk_BellsGateLoop_1" trainID="train50"/>
        <TrainHeadLeaveTrack cycleID="152" direction="UP" sectionID="sec_BellsGateLoop" speed="0.2" time="90.56741093738675" trackID="trk_BellsGateLoop_1" trainID="train50"/>
        <TrainTailLeaveTrack cycleID="152" direction="UP" sectionID="sec_BellsGateLoop" speed="30632.967032967033" time="90.6065844199524" trackID="trk_BellsGateLoop_1" trainID="train50"/>
        <TrainEnterTrack cycleID="153" direction="UP" sectionID="sec_BellsGateLoop" speed="0.2" time="91.53303028155548" trackID="trk_BellsGateLoop_1" trainID="train3"/>
        <TrainHeadLeaveTrack cycleID="153" direction="UP" sectionID="sec_BellsGateLoop" speed="0.2" time="91.56643803224287" trackID="trk_BellsGateLoop_1" trainID="train3"/>
        <TrainTailLeaveTrack cycleID="153" direction="UP" sectionID="sec_BellsGateLoop" speed="30632.967032967033" time="91.60561151480852" trackID="trk_BellsGateLoop_1" trainID="train3"/>
        <TrainEnterTrack cycleID="146" direction="UP" sectionID="sec_BellsGateLoop" speed="0.2" time="92.17886798851009" trackID="trk_BellsGateLoop_1" trainID="train51"/>
        <TrainHeadLeaveTrack cycleID="146" direction="UP" sectionID="sec_BellsGateLoop" speed="0.2" time="92.36354402899586" trackID="trk_BellsGateLoop_1" trainID="train51"/>
        <TrainTailLeaveTrack cycleID="146" direction="UP" sectionID="sec_BellsGateLoop" speed="29396.03335090881" time="92.40436586320986" trackID="trk_BellsGateLoop_1" trainID="train51"/>
        <TrainEnterTrack cycleID="165" direction="UP" sectionID="sec_BellsGateLoop" speed="0.2" time="94.03790031382366" trackID="trk_BellsGateLoop_1" trainID="train7"/>
        <TrainHeadLeaveTrack cycleID="165" direction="UP" sectionID="sec_BellsGateLoop" speed="0.2" time="94.07130806451104" trackID="trk_BellsGateLoop_1" trainID="train7"/>
        <TrainTailLeaveTrack cycleID="165" direction="UP" sectionID="sec_BellsGateLoop" speed="30632.967032967033" time="94.11048154707669" trackID="trk_BellsGateLoop_1" trainID="train7"/>
        <TrainEnterTrack cycleID="179" direction="UP" sectionID="sec_BellsGateLoop" speed="0.2" time="96.77513677238333" trackID="trk_BellsGateLoop_1" trainID="train53"/>
        <TrainHeadLeaveTrack cycleID="179" direction="UP" sectionID="sec_BellsGateLoop" speed="0.2" time="96.80854452307072" trackID="trk_BellsGateLoop_1" trainID="train53"/>
        <TrainTailLeaveTrack cycleID="179" direction="UP" sectionID="sec_BellsGateLoop" speed="30632.967032967033" time="96.84771800563637" trackID="trk_BellsGateLoop_1" trainID="train53"/>
        <TrainEnterTrack cycleID="177" direction="UP" sectionID="sec_BellsGateLoop" speed="0.2" time="107.64098043972726" trackID="trk_BellsGateLoop_1" trainID="train38"/>
        <TrainHeadLeaveTrack cycleID="177" direction="UP" sectionID="sec_BellsGateLoop" speed="0.2" time="107.67438819041465" trackID="trk_BellsGateLoop_1" trainID="train38"/>
        <TrainTailLeaveTrack cycleID="177" direction="UP" sectionID="sec_BellsGateLoop" speed="30632.967032967033" time="107.71356167298029" trackID="trk_BellsGateLoop_1" trainID="train38"/>
        <TrainEnterTrack cycleID="187" direction="UP" sectionID="sec_BellsGateLoop" speed="0.2" time="111.2170087690848" trackID="trk_BellsGateLoop_1" trainID="train45"/>
        <TrainHeadLeaveTrack cycleID="187" direction="UP" sectionID="sec_BellsGateLoop" speed="0.2" time="111.25041651977219" trackID="trk_BellsGateLoop_1" trainID="train45"/>
        <TrainTailLeaveTrack cycleID="187" direction="UP" sectionID="sec_BellsGateLoop" speed="30632.967032967033" time="111.28959000233783" trackID="trk_BellsGateLoop_1" trainID="train45"/>
        <TrainEnterTrack cycleID="191" direction="UP" sectionID="sec_BellsGateLoop" speed="0.2" time="114.30047384831104" trackID="trk_BellsGateLoop_1" trainID="train39"/>
        <TrainHeadLeaveTrack cycleID="191" direction="UP" sectionID="sec_BellsGateLoop" speed="0.2" time="114.33388159899843" trackID="trk_BellsGateLoop_1" trainID="train39"/>
        <TrainTailLeaveTrack cycleID="191" direction="UP" sectionID="sec_BellsGateLoop" speed="30632.967032967033" time="114.37305508156408" trackID="trk_BellsGateLoop_1" trainID="train39"/>
        <TrainEnterTrack cycleID="188" direction="UP" sectionID="sec_BellsGateLoop" speed="0.2" time="116.4788511849179" trackID="trk_BellsGateLoop_1" trainID="train55"/>
        <TrainHeadLeaveTrack cycleID="188" direction="UP" sectionID="sec_BellsGateLoop" speed="0.2" time="116.51225893560529" trackID="trk_BellsGateLoop_1" trainID="train55"/>
        <TrainTailLeaveTrack cycleID="188" direction="UP" sectionID="sec_BellsGateLoop" speed="30632.967032967033" time="116.55143241817093" trackID="trk_BellsGateLoop_1" trainID="train55"/>
        <TrainEnterTrack cycleID="192" direction="UP" sectionID="sec_BellsGateLoop" speed="0.2" time="119.40000323999003" trackID="trk_BellsGateLoop_1" trainID="train17"/>
        <TrainHeadLeaveTrack cycleID="192" direction="UP" sectionID="sec_BellsGateLoop" speed="0.2" time="119.43341099067742" trackID="trk_BellsGateLoop_1" trainID="train17"/>
        <TrainTailLeaveTrack cycleID="192" direction="UP" sectionID="sec_BellsGateLoop" speed="30632.967032967033" time="119.46605555948213" trackID="trk_BellsGateLoop_1" trainID="train17"/>
        <TrainEnterTrack cycleID="209" direction="UP" sectionID="sec_BellsGateLoop" speed="0.2" time="138.46675030465414" trackID="trk_BellsGateLoop_1" trainID="train14"/>
        <TrainHeadLeaveTrack cycleID="209" direction="UP" sectionID="sec_BellsGateLoop" speed="0.2" time="138.50015805534153" trackID="trk_BellsGateLoop_1" trainID="train14"/>
        <TrainTailLeaveTrack cycleID="209" direction="UP" sectionID="sec_BellsGateLoop" speed="30632.967032967033" time="138.53933153790717" trackID="trk_BellsGateLoop_1" trainID="train14"/>
        <TrainEnterTrack cycleID="214" direction="UP" sectionID="sec_BellsGateLoop" speed="0.2" time="139.95290066570863" trackID="trk_BellsGateLoop_1" trainID="train30"/>
        <TrainHeadLeaveTrack cycleID="214" direction="UP" sectionID="sec_BellsGateLoop" speed="0.2" time="139.986308416396" trackID="trk_BellsGateLoop_1" trainID="train30"/>
        <TrainTailLeaveTrack cycleID="214" direction="UP" sectionID="sec_BellsGateLoop" speed="30632.967032967033" time="140.02548189896166" trackID="trk_BellsGateLoop_1" trainID="train30"/>
        <TrainEnterTrack cycleID="211" direction="UP" sectionID="sec_BellsGateLoop" speed="0.2" time="140.33492527114765" trackID="trk_BellsGateLoop_1" trainID="train25"/>
        <TrainHeadLeaveTrack cycleID="211" direction="UP" sectionID="sec_BellsGateLoop" speed="0.2" time="140.41264157950533" trackID="trk_BellsGateLoop_1" trainID="train25"/>
        <TrainTailLeaveTrack cycleID="211" direction="UP" sectionID="sec_BellsGateLoop" speed="29396.03335090881" time="140.45346341371933" trackID="trk_BellsGateLoop_1" trainID="train25"/>
        <TrainEnterTrack cycleID="219" direction="UP" sectionID="sec_BellsGateLoop" speed="0.2" time="142.85473222394194" trackID="trk_BellsGateLoop_1" trainID="train44"/>
        <TrainHeadLeaveTrack cycleID="219" direction="UP" sectionID="sec_BellsGateLoop" speed="0.2" time="142.88813997462933" trackID="trk_BellsGateLoop_1" trainID="train44"/>
        <TrainTailLeaveTrack cycleID="219" direction="UP" sectionID="sec_BellsGateLoop" speed="30632.967032967033" time="142.92731345719497" trackID="trk_BellsGateLoop_1" trainID="train44"/>
        <TrainEnterTrack cycleID="227" direction="UP" sectionID="sec_BellsGateLoop" speed="0.2" time="156.1132397908814" trackID="trk_BellsGateLoop_1" trainID="train48"/>
        <TrainHeadLeaveTrack cycleID="227" direction="UP" sectionID="sec_BellsGateLoop" speed="0.2" time="156.1466475415688" trackID="trk_BellsGateLoop_1" trainID="train48"/>
        <TrainTailLeaveTrack cycleID="227" direction="UP" sectionID="sec_BellsGateLoop" speed="30632.967032967033" time="156.18582102413444" trackID="trk_BellsGateLoop_1" trainID="train48"/>
        <TrainEnterTrack cycleID="229" direction="UP" sectionID="sec_BellsGateLoop" speed="0.2" time="159.26036001150354" trackID="trk_BellsGateLoop_1" trainID="train47"/>
        <TrainHeadLeaveTrack cycleID="229" direction="UP" sectionID="sec_BellsGateLoop" speed="0.2" time="159.29376776219092" trackID="trk_BellsGateLoop_1" trainID="train47"/>
        <TrainTailLeaveTrack cycleID="229" direction="UP" sectionID="sec_BellsGateLoop" speed="30632.967032967033" time="159.33294124475657" trackID="trk_BellsGateLoop_1" trainID="train47"/>
        <TrainEnterTrack cycleID="254" direction="UP" sectionID="sec_BellsGateLoop" speed="0.2" time="175.47756654197954" trackID="trk_BellsGateLoop_1" trainID="train7"/>
        <TrainHeadLeaveTrack cycleID="254" direction="UP" sectionID="sec_BellsGateLoop" speed="0.2" time="175.51097429266693" trackID="trk_BellsGateLoop_1" trainID="train7"/>
        <TrainTailLeaveTrack cycleID="254" direction="UP" sectionID="sec_BellsGateLoop" speed="30632.967032967033" time="175.55014777523257" trackID="trk_BellsGateLoop_1" trainID="train7"/>
        <TrainEnterTrack cycleID="242" direction="UP" sectionID="sec_BellsGateLoop" speed="0.2" time="177.22661375544797" trackID="trk_BellsGateLoop_1" trainID="train35"/>
        <TrainHeadLeaveTrack cycleID="242" direction="UP" sectionID="sec_BellsGateLoop" speed="0.2" time="177.26002150613536" trackID="trk_BellsGateLoop_1" trainID="train35"/>
        <TrainTailLeaveTrack cycleID="242" direction="UP" sectionID="sec_BellsGateLoop" speed="30632.967032967033" time="177.299194988701" trackID="trk_BellsGateLoop_1" trainID="train35"/>
        <TrainEnterTrack cycleID="262" direction="UP" sectionID="sec_BellsGateLoop" speed="0.2" time="178.507820605417" trackID="trk_BellsGateLoop_1" trainID="train45"/>
        <TrainHeadLeaveTrack cycleID="262" direction="UP" sectionID="sec_BellsGateLoop" speed="0.2" time="178.7134628496402" trackID="trk_BellsGateLoop_1" trainID="train45"/>
        <TrainTailLeaveTrack cycleID="262" direction="UP" sectionID="sec_BellsGateLoop" speed="29396.03335090881" time="178.7542846838542" trackID="trk_BellsGateLoop_1" trainID="train45"/>
        <TrainEnterTrack cycleID="248" direction="UP" sectionID="sec_BellsGateLoop" speed="0.2" time="184.7755279080849" trackID="trk_BellsGateLoop_1" trainID="train18"/>
        <TrainHeadLeaveTrack cycleID="248" direction="UP" sectionID="sec_BellsGateLoop" speed="0.2" time="184.8089356587723" trackID="trk_BellsGateLoop_1" trainID="train18"/>
        <TrainTailLeaveTrack cycleID="248" direction="UP" sectionID="sec_BellsGateLoop" speed="30632.967032967033" time="184.84810914133794" trackID="trk_BellsGateLoop_1" trainID="train18"/>
        <TrainEnterTrack cycleID="265" direction="UP" sectionID="sec_BellsGateLoop" speed="0.2" time="188.58650889053646" trackID="trk_BellsGateLoop_1" trainID="train55"/>
        <TrainHeadLeaveTrack cycleID="265" direction="UP" sectionID="sec_BellsGateLoop" speed="0.2" time="188.61991664122385" trackID="trk_BellsGateLoop_1" trainID="train55"/>
        <TrainTailLeaveTrack cycleID="265" direction="UP" sectionID="sec_BellsGateLoop" speed="30632.967032967033" time="188.6590901237895" trackID="trk_BellsGateLoop_1" trainID="train55"/>
        <TrainEnterTrack cycleID="252" direction="UP" sectionID="sec_BellsGateLoop" speed="0.2" time="189.92357142595" trackID="trk_BellsGateLoop_1" trainID="train3"/>
        <TrainHeadLeaveTrack cycleID="252" direction="UP" sectionID="sec_BellsGateLoop" speed="0.2" time="190.10214657586712" trackID="trk_BellsGateLoop_1" trainID="train3"/>
        <TrainTailLeaveTrack cycleID="252" direction="UP" sectionID="sec_BellsGateLoop" speed="29396.03335090881" time="190.14296841008112" trackID="trk_BellsGateLoop_1" trainID="train3"/>
        <TrainEnterTrack cycleID="256" direction="UP" sectionID="sec_BellsGateLoop" speed="0.2" time="190.61675117895052" trackID="trk_BellsGateLoop_1" trainID="train53"/>
        <TrainHeadLeaveTrack cycleID="256" direction="UP" sectionID="sec_BellsGateLoop" speed="0.2" time="190.6501589296379" trackID="trk_BellsGateLoop_1" trainID="train53"/>
        <TrainTailLeaveTrack cycleID="256" direction="UP" sectionID="sec_BellsGateLoop" speed="30632.967032967033" time="190.68933241220356" trackID="trk_BellsGateLoop_1" trainID="train53"/>
        <TrainEnterTrack cycleID="255" direction="UP" sectionID="sec_BellsGateLoop" speed="0.2" time="193.05861764746965" trackID="trk_BellsGateLoop_1" trainID="train51"/>
        <TrainHeadLeaveTrack cycleID="255" direction="UP" sectionID="sec_BellsGateLoop" speed="0.2" time="193.09202539815703" trackID="trk_BellsGateLoop_1" trainID="train51"/>
        <TrainTailLeaveTrack cycleID="255" direction="UP" sectionID="sec_BellsGateLoop" speed="30632.967032967033" time="193.13119888072268" trackID="trk_BellsGateLoop_1" trainID="train51"/>
        <TrainEnterTrack cycleID="270" direction="UP" sectionID="sec_BellsGateLoop" speed="0.2" time="195.65263253043656" trackID="trk_BellsGateLoop_1" trainID="train14"/>
        <TrainHeadLeaveTrack cycleID="270" direction="UP" sectionID="sec_BellsGateLoop" speed="0.2" time="195.68604028112395" trackID="trk_BellsGateLoop_1" trainID="train14"/>
        <TrainTailLeaveTrack cycleID="270" direction="UP" sectionID="sec_BellsGateLoop" speed="30632.967032967033" time="195.7252137636896" trackID="trk_BellsGateLoop_1" trainID="train14"/>
        <TrainEnterTrack cycleID="301" direction="UP" sectionID="sec_BellsGateLoop" speed="0.2" time="199.10621560979195" trackID="trk_BellsGateLoop_1" trainID="train48"/>
        <TrainHeadLeaveTrack cycleID="301" direction="UP" sectionID="sec_BellsGateLoop" speed="0.2" time="199.13962336047933" trackID="trk_BellsGateLoop_1" trainID="train48"/>
        <TrainTailLeaveTrack cycleID="301" direction="UP" sectionID="sec_BellsGateLoop" speed="30632.967032967033" time="199.17879684304498" trackID="trk_BellsGateLoop_1" trainID="train48"/>
        <TrainEnterTrack cycleID="276" direction="UP" sectionID="sec_BellsGateLoop" speed="0.2" time="200.12034955602405" trackID="trk_BellsGateLoop_1" trainID="train44"/>
        <TrainHeadLeaveTrack cycleID="276" direction="UP" sectionID="sec_BellsGateLoop" speed="0.2" time="200.15375730671144" trackID="trk_BellsGateLoop_1" trainID="train44"/>
        <TrainTailLeaveTrack cycleID="276" direction="UP" sectionID="sec_BellsGateLoop" speed="30632.967032967033" time="200.19293078927709" trackID="trk_BellsGateLoop_1" trainID="train44"/>
        <TrainEnterTrack cycleID="282" direction="UP" sectionID="sec_BellsGateLoop" speed="0.2" time="200.77606023700156" trackID="trk_BellsGateLoop_1" trainID="train50"/>
        <TrainHeadLeaveTrack cycleID="282" direction="UP" sectionID="sec_BellsGateLoop" speed="0.2" time="200.80946798768895" trackID="trk_BellsGateLoop_1" trainID="train50"/>
        <TrainTailLeaveTrack cycleID="282" direction="UP" sectionID="sec_BellsGateLoop" speed="30632.967032967033" time="200.8486414702546" trackID="trk_BellsGateLoop_1" trainID="train50"/>
        <TrainEnterTrack cycleID="283" direction="UP" sectionID="sec_BellsGateLoop" speed="0.2" time="201.88382882160244" trackID="trk_BellsGateLoop_1" trainID="train38"/>
        <TrainHeadLeaveTrack cycleID="283" direction="UP" sectionID="sec_BellsGateLoop" speed="0.2" time="201.91723657228982" trackID="trk_BellsGateLoop_1" trainID="train38"/>
        <TrainTailLeaveTrack cycleID="283" direction="UP" sectionID="sec_BellsGateLoop" speed="30632.967032967033" time="201.95641005485547" trackID="trk_BellsGateLoop_1" trainID="train38"/>
        <TrainEnterTrack cycleID="285" direction="UP" sectionID="sec_BellsGateLoop" speed="0.2" time="203.17227559743966" trackID="trk_BellsGateLoop_1" trainID="train6"/>
        <TrainHeadLeaveTrack cycleID="285" direction="UP" sectionID="sec_BellsGateLoop" speed="0.2" time="203.20568334812705" trackID="trk_BellsGateLoop_1" trainID="train6"/>
        <TrainTailLeaveTrack cycleID="285" direction="UP" sectionID="sec_BellsGateLoop" speed="30632.967032967033" time="203.23832791693175" trackID="trk_BellsGateLoop_1" trainID="train6"/>
        <TrainEnterTrack cycleID="308" direction="UP" sectionID="sec_BellsGateLoop" speed="0.2" time="208.0016246673761" trackID="trk_BellsGateLoop_1" trainID="train39"/>
        <TrainHeadLeaveTrack cycleID="308" direction="UP" sectionID="sec_BellsGateLoop" speed="0.2" time="208.03503241806348" trackID="trk_BellsGateLoop_1" trainID="train39"/>
        <TrainTailLeaveTrack cycleID="308" direction="UP" sectionID="sec_BellsGateLoop" speed="30632.967032967033" time="208.07420590062912" trackID="trk_BellsGateLoop_1" trainID="train39"/>
        <TrainEnterTrack cycleID="317" direction="UP" sectionID="sec_BellsGateLoop" speed="0.2" time="216.597183487344" trackID="trk_BellsGateLoop_1" trainID="train17"/>
        <TrainHeadLeaveTrack cycleID="317" direction="UP" sectionID="sec_BellsGateLoop" speed="0.2" time="216.6305912380314" trackID="trk_BellsGateLoop_1" trainID="train17"/>
        <TrainTailLeaveTrack cycleID="317" direction="UP" sectionID="sec_BellsGateLoop" speed="30632.967032967033" time="216.6632358068361" trackID="trk_BellsGateLoop_1" trainID="train17"/>
        <TrainEnterTrack cycleID="326" direction="UP" sectionID="sec_BellsGateLoop" speed="0.2" time="223.38186403402062" trackID="trk_BellsGateLoop_1" trainID="train3"/>
        <TrainHeadLeaveTrack cycleID="326" direction="UP" sectionID="sec_BellsGateLoop" speed="0.2" time="223.415271784708" trackID="trk_BellsGateLoop_1" trainID="train3"/>
        <TrainTailLeaveTrack cycleID="326" direction="UP" sectionID="sec_BellsGateLoop" speed="30632.967032967033" time="223.45444526727366" trackID="trk_BellsGateLoop_1" trainID="train3"/>
        <TrainEnterTrack cycleID="328" direction="UP" sectionID="sec_BellsGateLoop" speed="0.2" time="223.95855406843162" trackID="trk_BellsGateLoop_1" trainID="train53"/>
        <TrainHeadLeaveTrack cycleID="328" direction="UP" sectionID="sec_BellsGateLoop" speed="0.2" time="223.991961819119" trackID="trk_BellsGateLoop_1" trainID="train53"/>
        <TrainTailLeaveTrack cycleID="328" direction="UP" sectionID="sec_BellsGateLoop" speed="30632.967032967033" time="224.03113530168466" trackID="trk_BellsGateLoop_1" trainID="train53"/>
        <TrainEnterTrack cycleID="333" direction="UP" sectionID="sec_BellsGateLoop" speed="0.2" time="226.64467796585484" trackID="trk_BellsGateLoop_1" trainID="train51"/>
        <TrainHeadLeaveTrack cycleID="333" direction="UP" sectionID="sec_BellsGateLoop" speed="0.2" time="226.67808571654223" trackID="trk_BellsGateLoop_1" trainID="train51"/>
        <TrainTailLeaveTrack cycleID="333" direction="UP" sectionID="sec_BellsGateLoop" speed="30632.967032967033" time="226.71725919910787" trackID="trk_BellsGateLoop_1" trainID="train51"/>
        <TrainEnterTrack cycleID="336" direction="UP" sectionID="sec_BellsGateLoop" speed="0.2" time="228.5144131191236" trackID="trk_BellsGateLoop_1" trainID="train14"/>
        <TrainHeadLeaveTrack cycleID="336" direction="UP" sectionID="sec_BellsGateLoop" speed="0.2" time="228.54782086981098" trackID="trk_BellsGateLoop_1" trainID="train14"/>
        <TrainTailLeaveTrack cycleID="336" direction="UP" sectionID="sec_BellsGateLoop" speed="30632.967032967033" time="228.58699435237662" trackID="trk_BellsGateLoop_1" trainID="train14"/>
        <TrainEnterTrack cycleID="343" direction="UP" sectionID="sec_BellsGateLoop" speed="0.2" time="231.92043122409217" trackID="trk_BellsGateLoop_1" trainID="train50"/>
        <TrainHeadLeaveTrack cycleID="343" direction="UP" sectionID="sec_BellsGateLoop" speed="0.2" time="231.95383897477956" trackID="trk_BellsGateLoop_1" trainID="train50"/>
        <TrainTailLeaveTrack cycleID="343" direction="UP" sectionID="sec_BellsGateLoop" speed="30632.967032967033" time="231.9930124573452" trackID="trk_BellsGateLoop_1" trainID="train50"/>
        <TrainEnterTrack cycleID="352" direction="UP" sectionID="sec_BellsGateLoop" speed="0.2" time="254.65260086689977" trackID="trk_BellsGateLoop_1" trainID="train25"/>
        <TrainHeadLeaveTrack cycleID="352" direction="UP" sectionID="sec_BellsGateLoop" speed="0.2" time="254.68600861758716" trackID="trk_BellsGateLoop_1" trainID="train25"/>
        <TrainTailLeaveTrack cycleID="352" direction="UP" sectionID="sec_BellsGateLoop" speed="30632.967032967033" time="254.7251821001528" trackID="trk_BellsGateLoop_1" trainID="train25"/>
        <TrainEnterTrack cycleID="351" direction="UP" sectionID="sec_BellsGateLoop" speed="0.2" time="255.60923627481966" trackID="trk_BellsGateLoop_1" trainID="train30"/>
        <TrainHeadLeaveTrack cycleID="351" direction="UP" sectionID="sec_BellsGateLoop" speed="0.2" time="255.64264402550705" trackID="trk_BellsGateLoop_1" trainID="train30"/>
        <TrainTailLeaveTrack cycleID="351" direction="UP" sectionID="sec_BellsGateLoop" speed="30632.967032967033" time="255.6818175080727" trackID="trk_BellsGateLoop_1" trainID="train30"/>
        <TrainEnterTrack cycleID="353" direction="UP" sectionID="sec_BellsGateLoop" speed="0.2" time="257.75104187765845" trackID="trk_BellsGateLoop_1" trainID="train50"/>
        <TrainHeadLeaveTrack cycleID="353" direction="UP" sectionID="sec_BellsGateLoop" speed="0.2" time="257.78444962834584" trackID="trk_BellsGateLoop_1" trainID="train50"/>
        <TrainTailLeaveTrack cycleID="353" direction="UP" sectionID="sec_BellsGateLoop" speed="30632.967032967033" time="257.8236231109115" trackID="trk_BellsGateLoop_1" trainID="train50"/>
        <TrainEnterTrack cycleID="361" direction="UP" sectionID="sec_BellsGateLoop" speed="0.2" time="261.87158115511227" trackID="trk_BellsGateLoop_1" trainID="train48"/>
        <TrainHeadLeaveTrack cycleID="361" direction="UP" sectionID="sec_BellsGateLoop" speed="0.2" time="261.90498890579966" trackID="trk_BellsGateLoop_1" trainID="train48"/>
        <TrainTailLeaveTrack cycleID="361" direction="UP" sectionID="sec_BellsGateLoop" speed="30632.967032967033" time="261.9441623883653" trackID="trk_BellsGateLoop_1" trainID="train48"/>
        <TrainEnterTrack cycleID="366" direction="UP" sectionID="sec_BellsGateLoop" speed="0.2" time="264.45049660424854" trackID="trk_BellsGateLoop_1" trainID="train6"/>
        <TrainHeadLeaveTrack cycleID="366" direction="UP" sectionID="sec_BellsGateLoop" speed="0.2" time="264.72164759706914" trackID="trk_BellsGateLoop_1" trainID="train6"/>
        <TrainTailLeaveTrack cycleID="366" direction="UP" sectionID="sec_BellsGateLoop" speed="29396.03335090881" time="264.75566579224744" trackID="trk_BellsGateLoop_1" trainID="train6"/>
        <TrainEnterTrack cycleID="369" direction="UP" sectionID="sec_BellsGateLoop" speed="0.2" time="268.1119477773439" trackID="trk_BellsGateLoop_1" trainID="train39"/>
        <TrainHeadLeaveTrack cycleID="369" direction="UP" sectionID="sec_BellsGateLoop" speed="0.2" time="268.1453555280313" trackID="trk_BellsGateLoop_1" trainID="train39"/>
        <TrainTailLeaveTrack cycleID="369" direction="UP" sectionID="sec_BellsGateLoop" speed="30632.967032967033" time="268.184529010597" trackID="trk_BellsGateLoop_1" trainID="train39"/>
        <TrainEnterTrack cycleID="364" direction="UP" sectionID="sec_BellsGateLoop" speed="0.2" time="270.26852253632217" trackID="trk_BellsGateLoop_1" trainID="train38"/>
        <TrainHeadLeaveTrack cycleID="364" direction="UP" sectionID="sec_BellsGateLoop" speed="0.2" time="270.6165429866071" trackID="trk_BellsGateLoop_1" trainID="train38"/>
        <TrainTailLeaveTrack cycleID="364" direction="UP" sectionID="sec_BellsGateLoop" speed="29396.03335090881" time="270.6573648208211" trackID="trk_BellsGateLoop_1" trainID="train38"/>
        <TrainEnterTrack cycleID="377" direction="UP" sectionID="sec_BellsGateLoop" speed="0.2" time="276.44378544818477" trackID="trk_BellsGateLoop_1" trainID="train51"/>
        <TrainHeadLeaveTrack cycleID="377" direction="UP" sectionID="sec_BellsGateLoop" speed="0.2" time="276.47719319887216" trackID="trk_BellsGateLoop_1" trainID="train51"/>
        <TrainTailLeaveTrack cycleID="377" direction="UP" sectionID="sec_BellsGateLoop" speed="30632.967032967033" time="276.51636668143783" trackID="trk_BellsGateLoop_1" trainID="train51"/>
        <TrainEnterTrack cycleID="391" direction="UP" sectionID="sec_BellsGateLoop" speed="0.2" time="280.7035307134015" trackID="trk_BellsGateLoop_1" trainID="train45"/>
        <TrainHeadLeaveTrack cycleID="391" direction="UP" sectionID="sec_BellsGateLoop" speed="0.2" time="280.7369384640889" trackID="trk_BellsGateLoop_1" trainID="train45"/>
        <TrainTailLeaveTrack cycleID="391" direction="UP" sectionID="sec_BellsGateLoop" speed="30632.967032967033" time="280.77611194665457" trackID="trk_BellsGateLoop_1" trainID="train45"/>
        <TrainEnterTrack cycleID="393" direction="UP" sectionID="sec_BellsGateLoop" speed="0.2" time="281.34936842035614" trackID="trk_BellsGateLoop_1" trainID="train18"/>
        <TrainHeadLeaveTrack cycleID="393" direction="UP" sectionID="sec_BellsGateLoop" speed="0.2" time="281.38277617104353" trackID="trk_BellsGateLoop_1" trainID="train18"/>
        <TrainTailLeaveTrack cycleID="393" direction="UP" sectionID="sec_BellsGateLoop" speed="30632.967032967033" time="281.4219496536092" trackID="trk_BellsGateLoop_1" trainID="train18"/>
        <TrainEnterTrack cycleID="381" direction="UP" sectionID="sec_BellsGateLoop" speed="0.2" time="282.3473617415882" trackID="trk_BellsGateLoop_1" trainID="train47"/>
        <TrainHeadLeaveTrack cycleID="381" direction="UP" sectionID="sec_BellsGateLoop" speed="0.2" time="282.3807694922756" trackID="trk_BellsGateLoop_1" trainID="train47"/>
        <TrainTailLeaveTrack cycleID="381" direction="UP" sectionID="sec_BellsGateLoop" speed="30632.967032967033" time="282.41994297484126" trackID="trk_BellsGateLoop_1" trainID="train47"/>
        <TrainEnterTrack cycleID="390" direction="UP" sectionID="sec_BellsGateLoop" speed="0.2" time="284.39638288338705" trackID="trk_BellsGateLoop_1" trainID="train35"/>
        <TrainHeadLeaveTrack cycleID="390" direction="UP" sectionID="sec_BellsGateLoop" speed="0.2" time="284.42979063407444" trackID="trk_BellsGateLoop_1" trainID="train35"/>
        <TrainTailLeaveTrack cycleID="390" direction="UP" sectionID="sec_BellsGateLoop" speed="30632.967032967033" time="284.4689641166401" trackID="trk_BellsGateLoop_1" trainID="train35"/>
        <TrainEnterTrack cycleID="394" direction="UP" sectionID="sec_BellsGateLoop" speed="0.2" time="285.6336854993163" trackID="trk_BellsGateLoop_1" trainID="train55"/>
        <TrainHeadLeaveTrack cycleID="394" direction="UP" sectionID="sec_BellsGateLoop" speed="0.2" time="285.6670932500037" trackID="trk_BellsGateLoop_1" trainID="train55"/>
        <TrainTailLeaveTrack cycleID="394" direction="UP" sectionID="sec_BellsGateLoop" speed="30632.967032967033" time="285.70626673256936" trackID="trk_BellsGateLoop_1" trainID="train55"/>
        <TrainEnterTrack cycleID="407" direction="UP" sectionID="sec_BellsGateLoop" speed="0.2" time="293.595562654977" trackID="trk_BellsGateLoop_1" trainID="train44"/>
        <TrainHeadLeaveTrack cycleID="407" direction="UP" sectionID="sec_BellsGateLoop" speed="0.2" time="293.6289704056644" trackID="trk_BellsGateLoop_1" trainID="train44"/>
        <TrainTailLeaveTrack cycleID="407" direction="UP" sectionID="sec_BellsGateLoop" speed="30632.967032967033" time="293.6681438882301" trackID="trk_BellsGateLoop_1" trainID="train44"/>
        <TrainEnterTrack cycleID="417" direction="UP" sectionID="sec_BellsGateLoop" speed="0.2" time="307.354337457671" trackID="trk_BellsGateLoop_1" trainID="train25"/>
        <TrainHeadLeaveTrack cycleID="417" direction="UP" sectionID="sec_BellsGateLoop" speed="0.2" time="307.3877452083584" trackID="trk_BellsGateLoop_1" trainID="train25"/>
        <TrainTailLeaveTrack cycleID="417" direction="UP" sectionID="sec_BellsGateLoop" speed="30632.967032967033" time="307.4269186909241" trackID="trk_BellsGateLoop_1" trainID="train25"/>
        <TrainEnterTrack cycleID="443" direction="UP" sectionID="sec_BellsGateLoop" speed="0.2" time="313.249232847209" trackID="trk_BellsGateLoop_1" trainID="train39"/>
        <TrainHeadLeaveTrack cycleID="443" direction="UP" sectionID="sec_BellsGateLoop" speed="0.2" time="313.2826405978964" trackID="trk_BellsGateLoop_1" trainID="train39"/>
        <TrainTailLeaveTrack cycleID="443" direction="UP" sectionID="sec_BellsGateLoop" speed="30632.967032967033" time="313.32181408046205" trackID="trk_BellsGateLoop_1" trainID="train39"/>
        <TrainEnterTrack cycleID="447" direction="UP" sectionID="sec_BellsGateLoop" speed="0.2" time="315.26223205991107" trackID="trk_BellsGateLoop_1" trainID="train45"/>
        <TrainHeadLeaveTrack cycleID="447" direction="UP" sectionID="sec_BellsGateLoop" speed="0.2" time="315.29563981059846" trackID="trk_BellsGateLoop_1" trainID="train45"/>
        <TrainTailLeaveTrack cycleID="447" direction="UP" sectionID="sec_BellsGateLoop" speed="30632.967032967033" time="315.33481329316413" trackID="trk_BellsGateLoop_1" trainID="train45"/>
        <TrainEnterTrack cycleID="438" direction="UP" sectionID="sec_BellsGateLoop" speed="0.2" time="316.9292752445106" trackID="trk_BellsGateLoop_1" trainID="train48"/>
        <TrainHeadLeaveTrack cycleID="438" direction="UP" sectionID="sec_BellsGateLoop" speed="0.2" time="316.962682995198" trackID="trk_BellsGateLoop_1" trainID="train48"/>
        <TrainTailLeaveTrack cycleID="438" direction="UP" sectionID="sec_BellsGateLoop" speed="30632.967032967033" time="317.0018564777637" trackID="trk_BellsGateLoop_1" trainID="train48"/>
        <TrainEnterTrack cycleID="426" direction="UP" sectionID="sec_BellsGateLoop" speed="0.2" time="317.9272685657427" trackID="trk_BellsGateLoop_1" trainID="train3"/>
        <TrainHeadLeaveTrack cycleID="426" direction="UP" sectionID="sec_BellsGateLoop" speed="0.2" time="318.09023917479584" trackID="trk_BellsGateLoop_1" trainID="train3"/>
        <TrainTailLeaveTrack cycleID="426" direction="UP" sectionID="sec_BellsGateLoop" speed="29396.03335090881" time="318.13106100900984" trackID="trk_BellsGateLoop_1" trainID="train3"/>
        <TrainEnterTrack cycleID="427" direction="UP" sectionID="sec_BellsGateLoop" speed="0.2" time="319.0696728509266" trackID="trk_BellsGateLoop_1" trainID="train53"/>
        <TrainHeadLeaveTrack cycleID="427" direction="UP" sectionID="sec_BellsGateLoop" speed="0.2" time="319.4338704537738" trackID="trk_BellsGateLoop_1" trainID="train53"/>
        <TrainTailLeaveTrack cycleID="427" direction="UP" sectionID="sec_BellsGateLoop" speed="29396.03335090881" time="319.4746922879878" trackID="trk_BellsGateLoop_1" trainID="train53"/>
        <TrainEnterTrack cycleID="441" direction="UP" sectionID="sec_BellsGateLoop" speed="0.2" time="319.94041924174707" trackID="trk_BellsGateLoop_1" trainID="train6"/>
        <TrainHeadLeaveTrack cycleID="441" direction="UP" sectionID="sec_BellsGateLoop" speed="0.2" time="319.97382699243445" trackID="trk_BellsGateLoop_1" trainID="train6"/>
        <TrainTailLeaveTrack cycleID="441" direction="UP" sectionID="sec_BellsGateLoop" speed="30632.967032967033" time="320.00647156123915" trackID="trk_BellsGateLoop_1" trainID="train6"/>
        <TrainEnterTrack cycleID="433" direction="UP" sectionID="sec_BellsGateLoop" speed="0.2" time="321.4805393550706" trackID="trk_BellsGateLoop_1" trainID="train14"/>
        <TrainHeadLeaveTrack cycleID="433" direction="UP" sectionID="sec_BellsGateLoop" speed="0.2" time="321.513947105758" trackID="trk_BellsGateLoop_1" trainID="train14"/>
        <TrainTailLeaveTrack cycleID="433" direction="UP" sectionID="sec_BellsGateLoop" speed="30632.967032967033" time="321.5531205883237" trackID="trk_BellsGateLoop_1" trainID="train14"/>
        <TrainEnterTrack cycleID="452" direction="UP" sectionID="sec_BellsGateLoop" speed="0.2" time="328.67701748377345" trackID="trk_BellsGateLoop_1" trainID="train47"/>
        <TrainHeadLeaveTrack cycleID="452" direction="UP" sectionID="sec_BellsGateLoop" speed="0.2" time="328.71042523446084" trackID="trk_BellsGateLoop_1" trainID="train47"/>
        <TrainTailLeaveTrack cycleID="452" direction="UP" sectionID="sec_BellsGateLoop" speed="30632.967032967033" time="328.7495987170265" trackID="trk_BellsGateLoop_1" trainID="train47"/>
        <TrainEnterTrack cycleID="456" direction="UP" sectionID="sec_BellsGateLoop" speed="0.2" time="329.4708298337782" trackID="trk_BellsGateLoop_1" trainID="train30"/>
        <TrainHeadLeaveTrack cycleID="456" direction="UP" sectionID="sec_BellsGateLoop" speed="0.2" time="329.5042375844656" trackID="trk_BellsGateLoop_1" trainID="train30"/>
        <TrainTailLeaveTrack cycleID="456" direction="UP" sectionID="sec_BellsGateLoop" speed="30632.967032967033" time="329.5434110670313" trackID="trk_BellsGateLoop_1" trainID="train30"/>
        <TrainEnterTrack cycleID="458" direction="UP" sectionID="sec_BellsGateLoop" speed="0.2" time="331.12102219108465" trackID="trk_BellsGateLoop_1" trainID="train50"/>
        <TrainHeadLeaveTrack cycleID="458" direction="UP" sectionID="sec_BellsGateLoop" speed="0.2" time="331.15442994177204" trackID="trk_BellsGateLoop_1" trainID="train50"/>
        <TrainTailLeaveTrack cycleID="458" direction="UP" sectionID="sec_BellsGateLoop" speed="30632.967032967033" time="331.1936034243377" trackID="trk_BellsGateLoop_1" trainID="train50"/>
        <TrainEnterTrack cycleID="462" direction="UP" sectionID="sec_BellsGateLoop" speed="0.2" time="333.9609046103859" trackID="trk_BellsGateLoop_1" trainID="train55"/>
        <TrainHeadLeaveTrack cycleID="462" direction="UP" sectionID="sec_BellsGateLoop" speed="0.2" time="333.9943123610733" trackID="trk_BellsGateLoop_1" trainID="train55"/>
        <TrainTailLeaveTrack cycleID="462" direction="UP" sectionID="sec_BellsGateLoop" speed="30632.967032967033" time="334.03348584363897" trackID="trk_BellsGateLoop_1" trainID="train55"/>
        <TrainEnterTrack cycleID="484" direction="UP" sectionID="sec_BellsGateLoop" speed="0.2" time="355.20130552054036" trackID="trk_BellsGateLoop_1" trainID="train39"/>
        <TrainHeadLeaveTrack cycleID="484" direction="UP" sectionID="sec_BellsGateLoop" speed="0.2" time="355.23471327122775" trackID="trk_BellsGateLoop_1" trainID="train39"/>
        <TrainTailLeaveTrack cycleID="484" direction="UP" sectionID="sec_BellsGateLoop" speed="30632.967032967033" time="355.2738867537934" trackID="trk_BellsGateLoop_1" trainID="train39"/>
        <TrainEnterTrack cycleID="468" direction="UP" sectionID="sec_BellsGateLoop" speed="0.2" time="361.35167011515375" trackID="trk_BellsGateLoop_1" trainID="train44"/>
        <TrainHeadLeaveTrack cycleID="468" direction="UP" sectionID="sec_BellsGateLoop" speed="0.2" time="361.38507786584114" trackID="trk_BellsGateLoop_1" trainID="train44"/>
        <TrainTailLeaveTrack cycleID="468" direction="UP" sectionID="sec_BellsGateLoop" speed="30632.967032967033" time="361.4242513484068" trackID="trk_BellsGateLoop_1" trainID="train44"/>
        <TrainEnterTrack cycleID="476" direction="UP" sectionID="sec_BellsGateLoop" speed="0.2" time="363.6699238288591" trackID="trk_BellsGateLoop_1" trainID="train25"/>
        <TrainHeadLeaveTrack cycleID="476" direction="UP" sectionID="sec_BellsGateLoop" speed="0.2" time="363.7033315795465" trackID="trk_BellsGateLoop_1" trainID="train25"/>
        <TrainTailLeaveTrack cycleID="476" direction="UP" sectionID="sec_BellsGateLoop" speed="30632.967032967033" time="363.7425050621122" trackID="trk_BellsGateLoop_1" trainID="train25"/>
        <TrainEnterTrack cycleID="501" direction="DOWN" sectionID="sec_BellsGateLoop" speed="0.2" time="368.9680439809876" trackID="trk_BellsGateLoop_1" trainID="train38"/>
        <TrainHeadLeaveTrack cycleID="501" direction="UP" sectionID="sec_BellsGateLoop" speed="0.2" time="369.00212345595713" trackID="trk_BellsGateLoop_1" trainID="train38"/>
        <TrainTailLeaveTrack cycleID="501" direction="DOWN" sectionID="sec_BellsGateLoop" speed="39128.57142857143" time="369.0327915830108" trackID="trk_BellsGateLoop_1" trainID="train38"/>
        <TrainEnterTrack cycleID="504" direction="DOWN" sectionID="sec_BellsGateLoop" speed="0.2" time="369.7550138559873" trackID="trk_BellsGateLoop_1" trainID="train51"/>
        <TrainHeadLeaveTrack cycleID="504" direction="UP" sectionID="sec_BellsGateLoop" speed="0.2" time="369.7890933309568" trackID="trk_BellsGateLoop_1" trainID="train51"/>
        <TrainTailLeaveTrack cycleID="504" direction="DOWN" sectionID="sec_BellsGateLoop" speed="39128.57142857143" time="369.8197614580105" trackID="trk_BellsGateLoop_1" trainID="train51"/>
        <TrainEnterTrack cycleID="489" direction="UP" sectionID="sec_BellsGateLoop" speed="0.2" time="370.6836273807296" trackID="trk_BellsGateLoop_1" trainID="train53"/>
        <TrainHeadLeaveTrack cycleID="489" direction="UP" sectionID="sec_BellsGateLoop" speed="0.2" time="370.717035131417" trackID="trk_BellsGateLoop_1" trainID="train53"/>
        <TrainTailLeaveTrack cycleID="489" direction="UP" sectionID="sec_BellsGateLoop" speed="30632.967032967033" time="370.75620861398266" trackID="trk_BellsGateLoop_1" trainID="train53"/>
        <TrainEnterTrack cycleID="498" direction="UP" sectionID="sec_BellsGateLoop" speed="0.2" time="374.05735913464935" trackID="trk_BellsGateLoop_1" trainID="train55"/>
        <TrainHeadLeaveTrack cycleID="498" direction="UP" sectionID="sec_BellsGateLoop" speed="0.2" time="374.09076688533673" trackID="trk_BellsGateLoop_1" trainID="train55"/>
        <TrainTailLeaveTrack cycleID="498" direction="UP" sectionID="sec_BellsGateLoop" speed="30632.967032967033" time="374.1299403679024" trackID="trk_BellsGateLoop_1" trainID="train55"/>
        <TrainEnterTrack cycleID="488" direction="UP" sectionID="sec_BellsGateLoop" speed="0.2" time="374.37193662240094" trackID="trk_BellsGateLoop_1" trainID="train3"/>
        <TrainHeadLeaveTrack cycleID="488" direction="UP" sectionID="sec_BellsGateLoop" speed="0.2" time="374.517100048446" trackID="trk_BellsGateLoop_1" trainID="train3"/>
        <TrainTailLeaveTrack cycleID="488" direction="UP" sectionID="sec_BellsGateLoop" speed="29396.03335090881" time="374.55792188266" trackID="trk_BellsGateLoop_1" trainID="train3"/>
        <TrainEnterTrack cycleID="494" direction="UP" sectionID="sec_BellsGateLoop" speed="0.2" time="375.42272904664844" trackID="trk_BellsGateLoop_1" trainID="train47"/>
        <TrainHeadLeaveTrack cycleID="494" direction="UP" sectionID="sec_BellsGateLoop" speed="0.2" time="375.45613679733583" trackID="trk_BellsGateLoop_1" trainID="train47"/>
        <TrainTailLeaveTrack cycleID="494" direction="UP" sectionID="sec_BellsGateLoop" speed="30632.967032967033" time="375.4953102799015" trackID="trk_BellsGateLoop_1" trainID="train47"/>
        <TrainEnterTrack cycleID="495" direction="UP" sectionID="sec_BellsGateLoop" speed="0.2" time="378.27649374998396" trackID="trk_BellsGateLoop_1" trainID="train50"/>
        <TrainHeadLeaveTrack cycleID="495" direction="UP" sectionID="sec_BellsGateLoop" speed="0.2" time="378.30990150067134" trackID="trk_BellsGateLoop_1" trainID="train50"/>
        <TrainTailLeaveTrack cycleID="495" direction="UP" sectionID="sec_BellsGateLoop" speed="30632.967032967033" time="378.349074983237" trackID="trk_BellsGateLoop_1" trainID="train50"/>
        <TrainEnterTrack cycleID="501" direction="UP" sectionID="sec_BellsGateLoop" speed="0.2" time="378.9223314569386" trackID="trk_BellsGateLoop_1" trainID="train38"/>
        <TrainHeadLeaveTrack cycleID="501" direction="UP" sectionID="sec_BellsGateLoop" speed="0.2" time="378.955739207626" trackID="trk_BellsGateLoop_1" trainID="train38"/>
        <TrainTailLeaveTrack cycleID="501" direction="UP" sectionID="sec_BellsGateLoop" speed="30632.967032967033" time="378.99491269019165" trackID="trk_BellsGateLoop_1" trainID="train38"/>
        <TrainEnterTrack cycleID="506" direction="UP" sectionID="sec_BellsGateLoop" speed="0.2" time="379.3043560623777" trackID="trk_BellsGateLoop_1" trainID="train35"/>
        <TrainHeadLeaveTrack cycleID="506" direction="UP" sectionID="sec_BellsGateLoop" speed="0.2" time="379.3820723707353" trackID="trk_BellsGateLoop_1" trainID="train35"/>
        <TrainTailLeaveTrack cycleID="506" direction="UP" sectionID="sec_BellsGateLoop" speed="29396.03335090881" time="379.4228942049493" trackID="trk_BellsGateLoop_1" trainID="train35"/>
        <TrainEnterTrack cycleID="504" direction="UP" sectionID="sec_BellsGateLoop" speed="0.2" time="381.5939754401521" trackID="trk_BellsGateLoop_1" trainID="train51"/>
        <TrainHeadLeaveTrack cycleID="504" direction="UP" sectionID="sec_BellsGateLoop" speed="0.2" time="381.6273831908395" trackID="trk_BellsGateLoop_1" trainID="train51"/>
        <TrainTailLeaveTrack cycleID="504" direction="UP" sectionID="sec_BellsGateLoop" speed="30632.967032967033" time="381.6665566734052" trackID="trk_BellsGateLoop_1" trainID="train51"/>
        <TrainEnterTrack cycleID="529" direction="UP" sectionID="sec_BellsGateLoop" speed="0.2" time="411.5594643707762" trackID="trk_BellsGateLoop_1" trainID="train17"/>
        <TrainHeadLeaveTrack cycleID="529" direction="UP" sectionID="sec_BellsGateLoop" speed="0.2" time="411.5928721214636" trackID="trk_BellsGateLoop_1" trainID="train17"/>
        <TrainTailLeaveTrack cycleID="529" direction="UP" sectionID="sec_BellsGateLoop" speed="30632.967032967033" time="411.6255166902683" trackID="trk_BellsGateLoop_1" trainID="train17"/>
        <TrainEnterTrack cycleID="532" direction="UP" sectionID="sec_BellsGateLoop" speed="0.2" time="415.7686430158936" trackID="trk_BellsGateLoop_1" trainID="train14"/>
        <TrainHeadLeaveTrack cycleID="532" direction="UP" sectionID="sec_BellsGateLoop" speed="0.2" time="415.802050766581" trackID="trk_BellsGateLoop_1" trainID="train14"/>
        <TrainTailLeaveTrack cycleID="532" direction="UP" sectionID="sec_BellsGateLoop" speed="30632.967032967033" time="415.84122424914665" trackID="trk_BellsGateLoop_1" trainID="train14"/>
        <TrainEnterTrack cycleID="541" direction="UP" sectionID="sec_BellsGateLoop" speed="0.2" time="417.8348528936534" trackID="trk_BellsGateLoop_1" trainID="train44"/>
        <TrainHeadLeaveTrack cycleID="541" direction="UP" sectionID="sec_BellsGateLoop" speed="0.2" time="417.8682606443408" trackID="trk_BellsGateLoop_1" trainID="train44"/>
        <TrainTailLeaveTrack cycleID="541" direction="UP" sectionID="sec_BellsGateLoop" speed="30632.967032967033" time="417.9074341269065" trackID="trk_BellsGateLoop_1" trainID="train44"/>
        <TrainEnterTrack cycleID="552" direction="UP" sectionID="sec_BellsGateLoop" speed="0.2" time="419.1003106248399" trackID="trk_BellsGateLoop_1" trainID="train18"/>
        <TrainHeadLeaveTrack cycleID="552" direction="UP" sectionID="sec_BellsGateLoop" speed="0.2" time="419.1337183755273" trackID="trk_BellsGateLoop_1" trainID="train18"/>
        <TrainTailLeaveTrack cycleID="552" direction="UP" sectionID="sec_BellsGateLoop" speed="30632.967032967033" time="419.17289185809295" trackID="trk_BellsGateLoop_1" trainID="train18"/>
        <TrainEnterTrack cycleID="547" direction="UP" sectionID="sec_BellsGateLoop" speed="0.2" time="424.81268371393986" trackID="trk_BellsGateLoop_1" trainID="train3"/>
        <TrainHeadLeaveTrack cycleID="547" direction="UP" sectionID="sec_BellsGateLoop" speed="0.2" time="424.84609146462725" trackID="trk_BellsGateLoop_1" trainID="train3"/>
        <TrainTailLeaveTrack cycleID="547" direction="UP" sectionID="sec_BellsGateLoop" speed="30632.967032967033" time="424.8852649471929" trackID="trk_BellsGateLoop_1" trainID="train3"/>
        <TrainEnterTrack cycleID="557" direction="UP" sectionID="sec_BellsGateLoop" speed="0.2" time="433.3559855499217" trackID="trk_BellsGateLoop_1" trainID="train51"/>
        <TrainHeadLeaveTrack cycleID="557" direction="UP" sectionID="sec_BellsGateLoop" speed="0.2" time="433.3893933006091" trackID="trk_BellsGateLoop_1" trainID="train51"/>
        <TrainTailLeaveTrack cycleID="557" direction="UP" sectionID="sec_BellsGateLoop" speed="30632.967032967033" time="433.42856678317474" trackID="trk_BellsGateLoop_1" trainID="train51"/>
        <TrainEnterTrack cycleID="564" direction="UP" sectionID="sec_BellsGateLoop" speed="0.2" time="434.7110783217341" trackID="trk_BellsGateLoop_1" trainID="train30"/>
        <TrainHeadLeaveTrack cycleID="564" direction="UP" sectionID="sec_BellsGateLoop" speed="0.2" time="434.74448607242147" trackID="trk_BellsGateLoop_1" trainID="train30"/>
        <TrainTailLeaveTrack cycleID="564" direction="UP" sectionID="sec_BellsGateLoop" speed="30632.967032967033" time="434.78365955498714" trackID="trk_BellsGateLoop_1" trainID="train30"/>
        <TrainEnterTrack cycleID="563" direction="UP" sectionID="sec_BellsGateLoop" speed="0.2" time="436.3062499066886" trackID="trk_BellsGateLoop_1" trainID="train6"/>
        <TrainHeadLeaveTrack cycleID="563" direction="UP" sectionID="sec_BellsGateLoop" speed="0.2" time="436.339657657376" trackID="trk_BellsGateLoop_1" trainID="train6"/>
        <TrainTailLeaveTrack cycleID="563" direction="UP" sectionID="sec_BellsGateLoop" speed="30632.967032967033" time="436.3723022261807" trackID="trk_BellsGateLoop_1" trainID="train6"/>
        <TrainEnterTrack cycleID="576" direction="UP" sectionID="sec_BellsGateLoop" speed="0.2" time="437.7945434009604" trackID="trk_BellsGateLoop_1" trainID="train39"/>
        <TrainHeadLeaveTrack cycleID="576" direction="UP" sectionID="sec_BellsGateLoop" speed="0.2" time="437.82795115164777" trackID="trk_BellsGateLoop_1" trainID="train39"/>
        <TrainTailLeaveTrack cycleID="576" direction="UP" sectionID="sec_BellsGateLoop" speed="30632.967032967033" time="437.86712463421344" trackID="trk_BellsGateLoop_1" trainID="train39"/>
        <TrainEnterTrack cycleID="579" direction="UP" sectionID="sec_BellsGateLoop" speed="0.2" time="443.0183140456249" trackID="trk_BellsGateLoop_1" trainID="train50"/>
        <TrainHeadLeaveTrack cycleID="579" direction="UP" sectionID="sec_BellsGateLoop" speed="0.2" time="443.120189615249" trackID="trk_BellsGateLoop_1" trainID="train50"/>
        <TrainTailLeaveTrack cycleID="579" direction="UP" sectionID="sec_BellsGateLoop" speed="29396.03335090881" time="443.161011449463" trackID="trk_BellsGateLoop_1" trainID="train50"/>
        <TrainEnterTrack cycleID="586" direction="UP" sectionID="sec_BellsGateLoop" speed="0.2" time="447.70415084118684" trackID="trk_BellsGateLoop_1" trainID="train55"/>
        <TrainHeadLeaveTrack cycleID="586" direction="UP" sectionID="sec_BellsGateLoop" speed="0.2" time="447.73755859187423" trackID="trk_BellsGateLoop_1" trainID="train55"/>
        <TrainTailLeaveTrack cycleID="586" direction="UP" sectionID="sec_BellsGateLoop" speed="30632.967032967033" time="447.7767320744399" trackID="trk_BellsGateLoop_1" trainID="train55"/>
        <TrainEnterTrack cycleID="585" direction="UP" sectionID="sec_BellsGateLoop" speed="0.2" time="453.1330750646495" trackID="trk_BellsGateLoop_1" trainID="train53"/>
        <TrainHeadLeaveTrack cycleID="585" direction="UP" sectionID="sec_BellsGateLoop" speed="0.2" time="453.1664828153369" trackID="trk_BellsGateLoop_1" trainID="train53"/>
        <TrainTailLeaveTrack cycleID="585" direction="UP" sectionID="sec_BellsGateLoop" speed="30632.967032967033" time="453.2056562979026" trackID="trk_BellsGateLoop_1" trainID="train53"/>
        <TrainEnterTrack cycleID="599" direction="UP" sectionID="sec_BellsGateLoop" speed="0.2" time="455.66074939392166" trackID="trk_BellsGateLoop_1" trainID="train14"/>
        <TrainHeadLeaveTrack cycleID="599" direction="UP" sectionID="sec_BellsGateLoop" speed="0.2" time="455.69415714460905" trackID="trk_BellsGateLoop_1" trainID="train14"/>
        <TrainTailLeaveTrack cycleID="599" direction="UP" sectionID="sec_BellsGateLoop" speed="30632.967032967033" time="455.7333306271747" trackID="trk_BellsGateLoop_1" trainID="train14"/>
        <TrainEnterTrack cycleID="591" direction="UP" sectionID="sec_BellsGateLoop" speed="0.2" time="458.4903548148407" trackID="trk_BellsGateLoop_1" trainID="train25"/>
        <TrainHeadLeaveTrack cycleID="591" direction="UP" sectionID="sec_BellsGateLoop" speed="0.2" time="458.5237625655281" trackID="trk_BellsGateLoop_1" trainID="train25"/>
        <TrainTailLeaveTrack cycleID="591" direction="UP" sectionID="sec_BellsGateLoop" speed="30632.967032967033" time="458.5629360480938" trackID="trk_BellsGateLoop_1" trainID="train25"/>
        <TrainEnterTrack cycleID="607" direction="UP" sectionID="sec_BellsGateLoop" speed="0.2" time="468.53374788563985" trackID="trk_BellsGateLoop_1" trainID="train3"/>
        <TrainHeadLeaveTrack cycleID="607" direction="UP" sectionID="sec_BellsGateLoop" speed="0.2" time="468.56715563632724" trackID="trk_BellsGateLoop_1" trainID="train3"/>
        <TrainTailLeaveTrack cycleID="607" direction="UP" sectionID="sec_BellsGateLoop" speed="30632.967032967033" time="468.6063291188929" trackID="trk_BellsGateLoop_1" trainID="train3"/>
        <TrainEnterTrack cycleID="617" direction="UP" sectionID="sec_BellsGateLoop" speed="0.2" time="477.877415566016" trackID="trk_BellsGateLoop_1" trainID="train6"/>
        <TrainHeadLeaveTrack cycleID="617" direction="UP" sectionID="sec_BellsGateLoop" speed="0.2" time="477.9108233167034" trackID="trk_BellsGateLoop_1" trainID="train6"/>
        <TrainTailLeaveTrack cycleID="617" direction="UP" sectionID="sec_BellsGateLoop" speed="30632.967032967033" time="477.9434678855081" trackID="trk_BellsGateLoop_1" trainID="train6"/>
        <TrainEnterTrack cycleID="619" direction="UP" sectionID="sec_BellsGateLoop" speed="0.2" time="482.24025995224054" trackID="trk_BellsGateLoop_1" trainID="train47"/>
        <TrainHeadLeaveTrack cycleID="619" direction="UP" sectionID="sec_BellsGateLoop" speed="0.2" time="482.2736677029279" trackID="trk_BellsGateLoop_1" trainID="train47"/>
        <TrainTailLeaveTrack cycleID="619" direction="UP" sectionID="sec_BellsGateLoop" speed="30632.967032967033" time="482.3128411854936" trackID="trk_BellsGateLoop_1" trainID="train47"/>
        <TrainEnterTrack cycleID="622" direction="UP" sectionID="sec_BellsGateLoop" speed="0.2" time="485.28727441527144" trackID="trk_BellsGateLoop_1" trainID="train50"/>
        <TrainHeadLeaveTrack cycleID="622" direction="UP" sectionID="sec_BellsGateLoop" speed="0.2" time="485.32068216595883" trackID="trk_BellsGateLoop_1" trainID="train50"/>
        <TrainTailLeaveTrack cycleID="622" direction="UP" sectionID="sec_BellsGateLoop" speed="30632.967032967033" time="485.3598556485245" trackID="trk_BellsGateLoop_1" trainID="train50"/>
        <TrainEnterTrack cycleID="630" direction="UP" sectionID="sec_BellsGateLoop" speed="0.2" time="490.79760047318973" trackID="trk_BellsGateLoop_1" trainID="train53"/>
        <TrainHeadLeaveTrack cycleID="630" direction="UP" sectionID="sec_BellsGateLoop" speed="0.2" time="490.8310082238771" trackID="trk_BellsGateLoop_1" trainID="train53"/>
        <TrainTailLeaveTrack cycleID="630" direction="UP" sectionID="sec_BellsGateLoop" speed="30632.967032967033" time="490.8701817064428" trackID="trk_BellsGateLoop_1" trainID="train53"/>
        <TrainEnterTrack cycleID="638" direction="UP" sectionID="sec_BellsGateLoop" speed="0.2" time="496.4405899272872" trackID="trk_BellsGateLoop_1" trainID="train38"/>
        <TrainHeadLeaveTrack cycleID="638" direction="UP" sectionID="sec_BellsGateLoop" speed="0.2" time="496.4739976779746" trackID="trk_BellsGateLoop_1" trainID="train38"/>
        <TrainTailLeaveTrack cycleID="638" direction="UP" sectionID="sec_BellsGateLoop" speed="30632.967032967033" time="496.51317116054025" trackID="trk_BellsGateLoop_1" trainID="train38"/>
        <TrainEnterTrack cycleID="669" direction="UP" sectionID="sec_BellsGateLoop" speed="0.2" time="524.7400231179835" trackID="trk_BellsGateLoop_1" trainID="train45"/>
        <TrainHeadLeaveTrack cycleID="669" direction="UP" sectionID="sec_BellsGateLoop" speed="0.2" time="524.7734308686709" trackID="trk_BellsGateLoop_1" trainID="train45"/>
        <TrainTailLeaveTrack cycleID="669" direction="UP" sectionID="sec_BellsGateLoop" speed="30632.967032967033" time="524.8126043512365" trackID="trk_BellsGateLoop_1" trainID="train45"/>
        <TrainEnterTrack cycleID="670" direction="UP" sectionID="sec_BellsGateLoop" speed="0.2" time="529.7974093696549" trackID="trk_BellsGateLoop_1" trainID="train18"/>
        <TrainHeadLeaveTrack cycleID="670" direction="UP" sectionID="sec_BellsGateLoop" speed="0.2" time="530.0558257997376" trackID="trk_BellsGateLoop_1" trainID="train18"/>
        <TrainTailLeaveTrack cycleID="670" direction="UP" sectionID="sec_BellsGateLoop" speed="29396.03335090881" time="530.0966476339515" trackID="trk_BellsGateLoop_1" trainID="train18"/>
        <TrainEnterTrack cycleID="671" direction="UP" sectionID="sec_BellsGateLoop" speed="0.2" time="532.9109693502256" trackID="trk_BellsGateLoop_1" trainID="train44"/>
        <TrainHeadLeaveTrack cycleID="671" direction="UP" sectionID="sec_BellsGateLoop" speed="0.2" time="532.944377100913" trackID="trk_BellsGateLoop_1" trainID="train44"/>
        <TrainTailLeaveTrack cycleID="671" direction="UP" sectionID="sec_BellsGateLoop" speed="30632.967032967033" time="532.9835505834786" trackID="trk_BellsGateLoop_1" trainID="train44"/>
        <TrainEnterTrack cycleID="681" direction="UP" sectionID="sec_BellsGateLoop" speed="0.2" time="537.3869543240072" trackID="trk_BellsGateLoop_1" trainID="train30"/>
        <TrainHeadLeaveTrack cycleID="681" direction="UP" sectionID="sec_BellsGateLoop" speed="0.2" time="537.4203620746946" trackID="trk_BellsGateLoop_1" trainID="train30"/>
        <TrainTailLeaveTrack cycleID="681" direction="UP" sectionID="sec_BellsGateLoop" speed="30632.967032967033" time="537.4595355572602" trackID="trk_BellsGateLoop_1" trainID="train30"/>
        <TrainEnterTrack cycleID="685" direction="UP" sectionID="sec_BellsGateLoop" speed="0.2" time="540.6583077951508" trackID="trk_BellsGateLoop_1" trainID="train7"/>
        <TrainHeadLeaveTrack cycleID="685" direction="UP" sectionID="sec_BellsGateLoop" speed="0.2" time="540.6917155458382" trackID="trk_BellsGateLoop_1" trainID="train7"/>
        <TrainTailLeaveTrack cycleID="685" direction="UP" sectionID="sec_BellsGateLoop" speed="30632.967032967033" time="540.7308890284038" trackID="trk_BellsGateLoop_1" trainID="train7"/>
        <TrainEnterTrack cycleID="679" direction="UP" sectionID="sec_BellsGateLoop" speed="0.2" time="542.7742961415235" trackID="trk_BellsGateLoop_1" trainID="train25"/>
        <TrainHeadLeaveTrack cycleID="679" direction="UP" sectionID="sec_BellsGateLoop" speed="0.2" time="542.8077038922108" trackID="trk_BellsGateLoop_1" trainID="train25"/>
        <TrainTailLeaveTrack cycleID="679" direction="UP" sectionID="sec_BellsGateLoop" speed="30632.967032967033" time="542.8468773747765" trackID="trk_BellsGateLoop_1" trainID="train25"/>
        <TrainEnterTrack cycleID="714" direction="UP" sectionID="sec_BellsGateLoop" speed="0.2" time="556.119793731585" trackID="trk_BellsGateLoop_1" trainID="train55"/>
        <TrainHeadLeaveTrack cycleID="714" direction="UP" sectionID="sec_BellsGateLoop" speed="0.2" time="556.1532014822724" trackID="trk_BellsGateLoop_1" trainID="train55"/>
        <TrainTailLeaveTrack cycleID="714" direction="UP" sectionID="sec_BellsGateLoop" speed="30632.967032967033" time="556.192374964838" trackID="trk_BellsGateLoop_1" trainID="train55"/>
        <TrainEnterTrack cycleID="716" direction="UP" sectionID="sec_BellsGateLoop" speed="0.2" time="556.5018183370239" trackID="trk_BellsGateLoop_1" trainID="train14"/>
        <TrainHeadLeaveTrack cycleID="716" direction="UP" sectionID="sec_BellsGateLoop" speed="0.2" time="556.5795346453816" trackID="trk_BellsGateLoop_1" trainID="train14"/>
        <TrainTailLeaveTrack cycleID="716" direction="UP" sectionID="sec_BellsGateLoop" speed="29396.03335090881" time="556.6203564795956" trackID="trk_BellsGateLoop_1" trainID="train14"/>
        <TrainEnterTrack cycleID="734" direction="UP" sectionID="sec_BellsGateLoop" speed="0.2" time="576.193043042332" trackID="trk_BellsGateLoop_1" trainID="train6"/>
        <TrainHeadLeaveTrack cycleID="734" direction="UP" sectionID="sec_BellsGateLoop" speed="0.2" time="576.2264507930194" trackID="trk_BellsGateLoop_1" trainID="train6"/>
        <TrainTailLeaveTrack cycleID="734" direction="UP" sectionID="sec_BellsGateLoop" speed="30632.967032967033" time="576.259095361824" trackID="trk_BellsGateLoop_1" trainID="train6"/>
        <TrainEnterTrack cycleID="737" direction="UP" sectionID="sec_BellsGateLoop" speed="0.2" time="577.2652650518046" trackID="trk_BellsGateLoop_1" trainID="train39"/>
        <TrainHeadLeaveTrack cycleID="737" direction="UP" sectionID="sec_BellsGateLoop" speed="0.2" time="577.298672802492" trackID="trk_BellsGateLoop_1" trainID="train39"/>
        <TrainTailLeaveTrack cycleID="737" direction="UP" sectionID="sec_BellsGateLoop" speed="30632.967032967033" time="577.3378462850576" trackID="trk_BellsGateLoop_1" trainID="train39"/>
        <TrainEnterTrack cycleID="741" direction="UP" sectionID="sec_BellsGateLoop" speed="0.2" time="579.9993678922838" trackID="trk_BellsGateLoop_1" trainID="train3"/>
        <TrainHeadLeaveTrack cycleID="741" direction="UP" sectionID="sec_BellsGateLoop" speed="0.2" time="580.0327756429712" trackID="trk_BellsGateLoop_1" trainID="train3"/>
        <TrainTailLeaveTrack cycleID="741" direction="UP" sectionID="sec_BellsGateLoop" speed="30632.967032967033" time="580.0719491255368" trackID="trk_BellsGateLoop_1" trainID="train3"/>
        <TrainEnterTrack cycleID="740" direction="UP" sectionID="sec_BellsGateLoop" speed="0.2" time="582.6713655327316" trackID="trk_BellsGateLoop_1" trainID="train35"/>
        <TrainHeadLeaveTrack cycleID="740" direction="UP" sectionID="sec_BellsGateLoop" speed="0.2" time="582.704773283419" trackID="trk_BellsGateLoop_1" trainID="train35"/>
        <TrainTailLeaveTrack cycleID="740" direction="UP" sectionID="sec_BellsGateLoop" speed="30632.967032967033" time="582.7439467659846" trackID="trk_BellsGateLoop_1" trainID="train35"/>
        <TrainEnterTrack cycleID="745" direction="UP" sectionID="sec_BellsGateLoop" speed="0.2" time="586.5732672772423" trackID="trk_BellsGateLoop_1" trainID="train30"/>
        <TrainHeadLeaveTrack cycleID="745" direction="UP" sectionID="sec_BellsGateLoop" speed="0.2" time="586.6066750279297" trackID="trk_BellsGateLoop_1" trainID="train30"/>
        <TrainTailLeaveTrack cycleID="745" direction="UP" sectionID="sec_BellsGateLoop" speed="30632.967032967033" time="586.6458485104953" trackID="trk_BellsGateLoop_1" trainID="train30"/>
        <TrainEnterTrack cycleID="748" direction="UP" sectionID="sec_BellsGateLoop" speed="0.2" time="591.0555961445231" trackID="trk_BellsGateLoop_1" trainID="train7"/>
        <TrainHeadLeaveTrack cycleID="748" direction="UP" sectionID="sec_BellsGateLoop" speed="0.2" time="591.0890038952105" trackID="trk_BellsGateLoop_1" trainID="train7"/>
        <TrainTailLeaveTrack cycleID="748" direction="UP" sectionID="sec_BellsGateLoop" speed="30632.967032967033" time="591.1281773777761" trackID="trk_BellsGateLoop_1" trainID="train7"/>
        <TrainEnterTrack cycleID="758" direction="UP" sectionID="sec_BellsGateLoop" speed="0.2" time="596.4965789620188" trackID="trk_BellsGateLoop_1" trainID="train55"/>
        <TrainHeadLeaveTrack cycleID="758" direction="UP" sectionID="sec_BellsGateLoop" speed="0.2" time="596.8455933483466" trackID="trk_BellsGateLoop_1" trainID="train55"/>
        <TrainTailLeaveTrack cycleID="758" direction="UP" sectionID="sec_BellsGateLoop" speed="29396.03335090881" time="596.8864151825605" trackID="trk_BellsGateLoop_1" trainID="train55"/>
        <TrainEnterTrack cycleID="771" direction="UP" sectionID="sec_BellsGateLoop" speed="0.2" time="598.9144153201016" trackID="trk_BellsGateLoop_1" trainID="train53"/>
        <TrainHeadLeaveTrack cycleID="771" direction="UP" sectionID="sec_BellsGateLoop" speed="0.2" time="599.3184129224451" trackID="trk_BellsGateLoop_1" trainID="train53"/>
        <TrainTailLeaveTrack cycleID="771" direction="UP" sectionID="sec_BellsGateLoop" speed="29396.03335090881" time="599.359234756659" trackID="trk_BellsGateLoop_1" trainID="train53"/>
        <TrainEnterTrack cycleID="762" direction="UP" sectionID="sec_BellsGateLoop" speed="0.2" time="599.8255224837026" trackID="trk_BellsGateLoop_1" trainID="train14"/>
        <TrainHeadLeaveTrack cycleID="762" direction="UP" sectionID="sec_BellsGateLoop" speed="0.2" time="599.85893023439" trackID="trk_BellsGateLoop_1" trainID="train14"/>
        <TrainTailLeaveTrack cycleID="762" direction="UP" sectionID="sec_BellsGateLoop" speed="30632.967032967033" time="599.8981037169556" trackID="trk_BellsGateLoop_1" trainID="train14"/>
        <TrainEnterTrack cycleID="768" direction="UP" sectionID="sec_BellsGateLoop" speed="0.2" time="601.0391094533401" trackID="trk_BellsGateLoop_1" trainID="train47"/>
        <TrainHeadLeaveTrack cycleID="768" direction="UP" sectionID="sec_BellsGateLoop" speed="0.2" time="601.0725172040275" trackID="trk_BellsGateLoop_1" trainID="train47"/>
        <TrainTailLeaveTrack cycleID="768" direction="UP" sectionID="sec_BellsGateLoop" speed="30632.967032967033" time="601.1116906865931" trackID="trk_BellsGateLoop_1" trainID="train47"/>
        <TrainEnterTrack cycleID="769" direction="UP" sectionID="sec_BellsGateLoop" speed="0.2" time="603.5811246297555" trackID="trk_BellsGateLoop_1" trainID="train50"/>
        <TrainHeadLeaveTrack cycleID="769" direction="UP" sectionID="sec_BellsGateLoop" speed="0.2" time="603.6145323804429" trackID="trk_BellsGateLoop_1" trainID="train50"/>
        <TrainTailLeaveTrack cycleID="769" direction="UP" sectionID="sec_BellsGateLoop" speed="30632.967032967033" time="603.6537058630086" trackID="trk_BellsGateLoop_1" trainID="train50"/>
        <TrainEnterTrack cycleID="772" direction="UP" sectionID="sec_BellsGateLoop" speed="0.2" time="605.7698388743379" trackID="trk_BellsGateLoop_1" trainID="train38"/>
        <TrainHeadLeaveTrack cycleID="772" direction="UP" sectionID="sec_BellsGateLoop" speed="0.2" time="605.8032466250253" trackID="trk_BellsGateLoop_1" trainID="train38"/>
        <TrainTailLeaveTrack cycleID="772" direction="UP" sectionID="sec_BellsGateLoop" speed="30632.967032967033" time="605.8424201075909" trackID="trk_BellsGateLoop_1" trainID="train38"/>
        <TrainEnterTrack cycleID="781" direction="UP" sectionID="sec_BellsGateLoop" speed="0.2" time="606.2299471838493" trackID="trk_BellsGateLoop_1" trainID="train6"/>
        <TrainHeadLeaveTrack cycleID="781" direction="UP" sectionID="sec_BellsGateLoop" speed="0.2" time="606.2633549345367" trackID="trk_BellsGateLoop_1" trainID="train6"/>
        <TrainTailLeaveTrack cycleID="781" direction="UP" sectionID="sec_BellsGateLoop" speed="30632.967032967033" time="606.2959995033414" trackID="trk_BellsGateLoop_1" trainID="train6"/>
        <TrainEnterTrack cycleID="774" direction="UP" sectionID="sec_BellsGateLoop" speed="0.2" time="607.8858270877498" trackID="trk_BellsGateLoop_1" trainID="train51"/>
        <TrainHeadLeaveTrack cycleID="774" direction="UP" sectionID="sec_BellsGateLoop" speed="0.2" time="607.9192348384372" trackID="trk_BellsGateLoop_1" trainID="train51"/>
        <TrainTailLeaveTrack cycleID="774" direction="UP" sectionID="sec_BellsGateLoop" speed="30632.967032967033" time="607.9584083210028" trackID="trk_BellsGateLoop_1" trainID="train51"/>
        <TrainEnterTrack cycleID="790" direction="UP" sectionID="sec_BellsGateLoop" speed="0.2" time="625.4916025385212" trackID="trk_BellsGateLoop_1" trainID="train35"/>
        <TrainHeadLeaveTrack cycleID="790" direction="UP" sectionID="sec_BellsGateLoop" speed="0.2" time="625.5250102892086" trackID="trk_BellsGateLoop_1" trainID="train35"/>
        <TrainTailLeaveTrack cycleID="790" direction="UP" sectionID="sec_BellsGateLoop" speed="30632.967032967033" time="625.5641837717742" trackID="trk_BellsGateLoop_1" trainID="train35"/>
        <TrainEnterTrack cycleID="799" direction="UP" sectionID="sec_BellsGateLoop" speed="0.2" time="633.7152550338392" trackID="trk_BellsGateLoop_1" trainID="train48"/>
        <TrainHeadLeaveTrack cycleID="799" direction="UP" sectionID="sec_BellsGateLoop" speed="0.2" time="633.7486627845266" trackID="trk_BellsGateLoop_1" trainID="train48"/>
        <TrainTailLeaveTrack cycleID="799" direction="UP" sectionID="sec_BellsGateLoop" speed="30632.967032967033" time="633.7878362670922" trackID="trk_BellsGateLoop_1" trainID="train48"/>
        <TrainEnterTrack cycleID="801" direction="UP" sectionID="sec_BellsGateLoop" speed="0.2" time="638.4828948464004" trackID="trk_BellsGateLoop_1" trainID="train18"/>
        <TrainHeadLeaveTrack cycleID="801" direction="UP" sectionID="sec_BellsGateLoop" speed="0.2" time="638.5163025970878" trackID="trk_BellsGateLoop_1" trainID="train18"/>
        <TrainTailLeaveTrack cycleID="801" direction="UP" sectionID="sec_BellsGateLoop" speed="30632.967032967033" time="638.5554760796534" trackID="trk_BellsGateLoop_1" trainID="train18"/>
        <TrainEnterTrack cycleID="814" direction="UP" sectionID="sec_BellsGateLoop" speed="0.2" time="642.5351072058734" trackID="trk_BellsGateLoop_1" trainID="train7"/>
        <TrainHeadLeaveTrack cycleID="814" direction="UP" sectionID="sec_BellsGateLoop" speed="0.2" time="642.5685149565608" trackID="trk_BellsGateLoop_1" trainID="train7"/>
        <TrainTailLeaveTrack cycleID="814" direction="UP" sectionID="sec_BellsGateLoop" speed="30632.967032967033" time="642.6076884391264" trackID="trk_BellsGateLoop_1" trainID="train7"/>
        <TrainEnterTrack cycleID="808" direction="UP" sectionID="sec_BellsGateLoop" speed="0.2" time="644.6510955516887" trackID="trk_BellsGateLoop_1" trainID="train30"/>
        <TrainHeadLeaveTrack cycleID="808" direction="UP" sectionID="sec_BellsGateLoop" speed="0.2" time="645.0397024151363" trackID="trk_BellsGateLoop_1" trainID="train30"/>
        <TrainTailLeaveTrack cycleID="808" direction="UP" sectionID="sec_BellsGateLoop" speed="29396.03335090881" time="645.0805242493502" trackID="trk_BellsGateLoop_1" trainID="train30"/>
        <TrainEnterTrack cycleID="821" direction="UP" sectionID="sec_BellsGateLoop" speed="0.2" time="654.1566826572114" trackID="trk_BellsGateLoop_1" trainID="train14"/>
        <TrainHeadLeaveTrack cycleID="821" direction="UP" sectionID="sec_BellsGateLoop" speed="0.2" time="654.1900904078988" trackID="trk_BellsGateLoop_1" trainID="train14"/>
        <TrainTailLeaveTrack cycleID="821" direction="UP" sectionID="sec_BellsGateLoop" speed="30632.967032967033" time="654.2292638904644" trackID="trk_BellsGateLoop_1" trainID="train14"/>
        <TrainEnterTrack cycleID="822" direction="UP" sectionID="sec_BellsGateLoop" speed="0.2" time="655.1557097520674" trackID="trk_BellsGateLoop_1" trainID="train47"/>
        <TrainHeadLeaveTrack cycleID="822" direction="UP" sectionID="sec_BellsGateLoop" speed="0.2" time="655.1891175027548" trackID="trk_BellsGateLoop_1" trainID="train47"/>
        <TrainTailLeaveTrack cycleID="822" direction="UP" sectionID="sec_BellsGateLoop" speed="30632.967032967033" time="655.2282909853204" trackID="trk_BellsGateLoop_1" trainID="train47"/>
        <TrainEnterTrack cycleID="830" direction="UP" sectionID="sec_BellsGateLoop" speed="0.2" time="662.9299442720962" trackID="trk_BellsGateLoop_1" trainID="train35"/>
        <TrainHeadLeaveTrack cycleID="830" direction="UP" sectionID="sec_BellsGateLoop" speed="0.2" time="662.9633520227836" trackID="trk_BellsGateLoop_1" trainID="train35"/>
        <TrainTailLeaveTrack cycleID="830" direction="UP" sectionID="sec_BellsGateLoop" speed="30632.967032967033" time="663.0025255053492" trackID="trk_BellsGateLoop_1" trainID="train35"/>
        <TrainEnterTrack cycleID="832" direction="UP" sectionID="sec_BellsGateLoop" speed="0.2" time="670.5667652335984" trackID="trk_BellsGateLoop_1" trainID="train44"/>
        <TrainHeadLeaveTrack cycleID="832" direction="UP" sectionID="sec_BellsGateLoop" speed="0.2" time="670.6001729842858" trackID="trk_BellsGateLoop_1" trainID="train44"/>
        <TrainTailLeaveTrack cycleID="832" direction="UP" sectionID="sec_BellsGateLoop" speed="30632.967032967033" time="670.6393464668514" trackID="trk_BellsGateLoop_1" trainID="train44"/>
        <TrainEnterTrack cycleID="835" direction="UP" sectionID="sec_BellsGateLoop" speed="0.2" time="674.6713403334047" trackID="trk_BellsGateLoop_1" trainID="train48"/>
        <TrainHeadLeaveTrack cycleID="835" direction="UP" sectionID="sec_BellsGateLoop" speed="0.2" time="674.7047480840921" trackID="trk_BellsGateLoop_1" trainID="train48"/>
        <TrainTailLeaveTrack cycleID="835" direction="UP" sectionID="sec_BellsGateLoop" speed="30632.967032967033" time="674.7439215666577" trackID="trk_BellsGateLoop_1" trainID="train48"/>
        <TrainEnterTrack cycleID="907" direction="UP" sectionID="sec_BellsGateLoop" speed="0.2" time="750.0123637550543" trackID="trk_BellsGateLoop_1" trainID="train50"/>
        <TrainHeadLeaveTrack cycleID="907" direction="UP" sectionID="sec_BellsGateLoop" speed="0.2" time="750.0457715057416" trackID="trk_BellsGateLoop_1" trainID="train50"/>
        <TrainTailLeaveTrack cycleID="907" direction="UP" sectionID="sec_BellsGateLoop" speed="30632.967032967033" time="750.0849449883073" trackID="trk_BellsGateLoop_1" trainID="train50"/>
        <TrainEnterTrack cycleID="904" direction="UP" sectionID="sec_BellsGateLoop" speed="0.2" time="751.3514337503522" trackID="trk_BellsGateLoop_1" trainID="train51"/>
        <TrainHeadLeaveTrack cycleID="904" direction="UP" sectionID="sec_BellsGateLoop" speed="0.2" time="751.3848415010395" trackID="trk_BellsGateLoop_1" trainID="train51"/>
        <TrainTailLeaveTrack cycleID="904" direction="UP" sectionID="sec_BellsGateLoop" speed="30632.967032967033" time="751.4240149836052" trackID="trk_BellsGateLoop_1" trainID="train51"/>
        <TrainEnterTrack cycleID="912" direction="UP" sectionID="sec_BellsGateLoop" speed="0.2" time="754.5198642467132" trackID="trk_BellsGateLoop_1" trainID="train35"/>
        <TrainHeadLeaveTrack cycleID="912" direction="UP" sectionID="sec_BellsGateLoop" speed="0.2" time="754.5532719974005" trackID="trk_BellsGateLoop_1" trainID="train35"/>
        <TrainTailLeaveTrack cycleID="912" direction="UP" sectionID="sec_BellsGateLoop" speed="30632.967032967033" time="754.5924454799662" trackID="trk_BellsGateLoop_1" trainID="train35"/>
        <TrainEnterTrack cycleID="921" direction="UP" sectionID="sec_BellsGateLoop" speed="0.2" time="757.1445412021031" trackID="trk_BellsGateLoop_1" trainID="train18"/>
        <TrainHeadLeaveTrack cycleID="921" direction="UP" sectionID="sec_BellsGateLoop" speed="0.2" time="757.1779489527905" trackID="trk_BellsGateLoop_1" trainID="train18"/>
        <TrainTailLeaveTrack cycleID="921" direction="UP" sectionID="sec_BellsGateLoop" speed="30632.967032967033" time="757.2171224353561" trackID="trk_BellsGateLoop_1" trainID="train18"/>
        <TrainEnterTrack cycleID="918" direction="UP" sectionID="sec_BellsGateLoop" speed="0.2" time="760.5391971606027" trackID="trk_BellsGateLoop_1" trainID="train30"/>
        <TrainHeadLeaveTrack cycleID="918" direction="UP" sectionID="sec_BellsGateLoop" speed="0.2" time="760.5726049112901" trackID="trk_BellsGateLoop_1" trainID="train30"/>
        <TrainTailLeaveTrack cycleID="918" direction="UP" sectionID="sec_BellsGateLoop" speed="30632.967032967033" time="760.6117783938557" trackID="trk_BellsGateLoop_1" trainID="train30"/>
        <TrainEnterTrack cycleID="916" direction="UP" sectionID="sec_BellsGateLoop" speed="0.2" time="761.3193573328651" trackID="trk_BellsGateLoop_1" trainID="train44"/>
        <TrainHeadLeaveTrack cycleID="916" direction="UP" sectionID="sec_BellsGateLoop" speed="0.2" time="761.3527650835525" trackID="trk_BellsGateLoop_1" trainID="train44"/>
        <TrainTailLeaveTrack cycleID="916" direction="UP" sectionID="sec_BellsGateLoop" speed="30632.967032967033" time="761.3919385661181" trackID="trk_BellsGateLoop_1" trainID="train44"/>
        <TrainEnterTrack cycleID="926" direction="UP" sectionID="sec_BellsGateLoop" speed="0.2" time="765.4153390129279" trackID="trk_BellsGateLoop_1" trainID="train17"/>
        <TrainHeadLeaveTrack cycleID="926" direction="UP" sectionID="sec_BellsGateLoop" speed="0.2" time="765.4487467636153" trackID="trk_BellsGateLoop_1" trainID="train17"/>
        <TrainTailLeaveTrack cycleID="926" direction="UP" sectionID="sec_BellsGateLoop" speed="30632.967032967033" time="765.48139133242" trackID="trk_BellsGateLoop_1" trainID="train17"/>
        <TrainEnterTrack cycleID="937" direction="UP" sectionID="sec_BellsGateLoop" speed="0.2" time="776.7144947118009" trackID="trk_BellsGateLoop_1" trainID="train6"/>
        <TrainHeadLeaveTrack cycleID="937" direction="UP" sectionID="sec_BellsGateLoop" speed="0.2" time="776.7479024624882" trackID="trk_BellsGateLoop_1" trainID="train6"/>
        <TrainTailLeaveTrack cycleID="937" direction="UP" sectionID="sec_BellsGateLoop" speed="30632.967032967033" time="776.7805470312929" trackID="trk_BellsGateLoop_1" trainID="train6"/>
        <TrainEnterTrack cycleID="951" direction="UP" sectionID="sec_BellsGateLoop" speed="0.2" time="799.7264948156009" trackID="trk_BellsGateLoop_1" trainID="train25"/>
        <TrainHeadLeaveTrack cycleID="951" direction="UP" sectionID="sec_BellsGateLoop" speed="0.2" time="799.7599025662882" trackID="trk_BellsGateLoop_1" trainID="train25"/>
        <TrainTailLeaveTrack cycleID="951" direction="UP" sectionID="sec_BellsGateLoop" speed="30632.967032967033" time="799.7990760488539" trackID="trk_BellsGateLoop_1" trainID="train25"/>
        <TrainEnterTrack cycleID="958" direction="UP" sectionID="sec_BellsGateLoop" speed="0.2" time="808.1313712727812" trackID="trk_BellsGateLoop_1" trainID="train55"/>
        <TrainHeadLeaveTrack cycleID="958" direction="UP" sectionID="sec_BellsGateLoop" speed="0.2" time="808.1647790234686" trackID="trk_BellsGateLoop_1" trainID="train55"/>
        <TrainTailLeaveTrack cycleID="958" direction="UP" sectionID="sec_BellsGateLoop" speed="30632.967032967033" time="808.2039525060342" trackID="trk_BellsGateLoop_1" trainID="train55"/>
        <TrainEnterTrack cycleID="971" direction="UP" sectionID="sec_BellsGateLoop" speed="0.2" time="817.1651147631292" trackID="trk_BellsGateLoop_1" trainID="train38"/>
        <TrainHeadLeaveTrack cycleID="971" direction="UP" sectionID="sec_BellsGateLoop" speed="0.2" time="817.1985225138166" trackID="trk_BellsGateLoop_1" trainID="train38"/>
        <TrainTailLeaveTrack cycleID="971" direction="UP" sectionID="sec_BellsGateLoop" speed="30632.967032967033" time="817.2376959963822" trackID="trk_BellsGateLoop_1" trainID="train38"/>
        <TrainEnterTrack cycleID="980" direction="UP" sectionID="sec_BellsGateLoop" speed="0.2" time="828.6936364924695" trackID="trk_BellsGateLoop_1" trainID="train51"/>
        <TrainHeadLeaveTrack cycleID="980" direction="UP" sectionID="sec_BellsGateLoop" speed="0.2" time="828.7270442431569" trackID="trk_BellsGateLoop_1" trainID="train51"/>
        <TrainTailLeaveTrack cycleID="980" direction="UP" sectionID="sec_BellsGateLoop" speed="30632.967032967033" time="828.7662177257225" trackID="trk_BellsGateLoop_1" trainID="train51"/>
        <TrainEnterTrack cycleID="984" direction="UP" sectionID="sec_BellsGateLoop" speed="0.2" time="834.5885318820068" trackID="trk_BellsGateLoop_1" trainID="train53"/>
        <TrainHeadLeaveTrack cycleID="984" direction="UP" sectionID="sec_BellsGateLoop" speed="0.2" time="834.6219396326942" trackID="trk_BellsGateLoop_1" trainID="train53"/>
        <TrainTailLeaveTrack cycleID="984" direction="UP" sectionID="sec_BellsGateLoop" speed="30632.967032967033" time="834.6611131152598" trackID="trk_BellsGateLoop_1" trainID="train53"/>
        <TrainEnterTrack cycleID="992" direction="UP" sectionID="sec_BellsGateLoop" speed="0.2" time="838.7707574566609" trackID="trk_BellsGateLoop_1" trainID="train30"/>
        <TrainHeadLeaveTrack cycleID="992" direction="UP" sectionID="sec_BellsGateLoop" speed="0.2" time="838.8041652073483" trackID="trk_BellsGateLoop_1" trainID="train30"/>
        <TrainTailLeaveTrack cycleID="992" direction="UP" sectionID="sec_BellsGateLoop" speed="30632.967032967033" time="838.8433386899139" trackID="trk_BellsGateLoop_1" trainID="train30"/>
        <TrainEnterTrack cycleID="994" direction="UP" sectionID="sec_BellsGateLoop" speed="0.2" time="842.0882391465824" trackID="trk_BellsGateLoop_1" trainID="train44"/>
        <TrainHeadLeaveTrack cycleID="994" direction="UP" sectionID="sec_BellsGateLoop" speed="0.2" time="842.1216468972698" trackID="trk_BellsGateLoop_1" trainID="train44"/>
        <TrainTailLeaveTrack cycleID="994" direction="UP" sectionID="sec_BellsGateLoop" speed="30632.967032967033" time="842.1608203798354" trackID="trk_BellsGateLoop_1" trainID="train44"/>
	</railEvents>
</railLog>