<railLog>
	<railEvents>
        <Track direction="DOWN" sectionID="sec_GretaTSF" trackID="trk_GretaReliefRd2"/>
        <TrainEnterTrack cycleID="120" direction="DOWN" sectionID="sec_GretaTSF" speed="0.2" time="46.452320216960075" trackID="trk_GretaReliefRd2" trainID="train12"/>
        <TrainHeadLeaveTrack cycleID="120" direction="UP" sectionID="sec_GretaTSF" speed="0.2" time="50.48820457070157" trackID="trk_GretaReliefRd2" trainID="train12"/>
        <TrainTailLeaveTrack cycleID="120" direction="UP" sectionID="sec_GretaTSF" speed="44100.67675560665" time="50.55468354566447" trackID="trk_GretaReliefRd2" trainID="train12"/>
        <TrainEnterTrack cycleID="128" direction="DOWN" sectionID="sec_GretaTSF" speed="0.2" time="51.21269519594515" trackID="trk_GretaReliefRd2" trainID="train28"/>
        <TrainHeadLeaveTrack cycleID="128" direction="UP" sectionID="sec_GretaTSF" speed="0.2" time="55.248579549686646" trackID="trk_GretaReliefRd2" trainID="train28"/>
        <TrainTailLeaveTrack cycleID="128" direction="UP" sectionID="sec_GretaTSF" speed="44100.67675560665" time="55.315058524649544" trackID="trk_GretaReliefRd2" trainID="train28"/>
        <TrainEnterTrack cycleID="141" direction="DOWN" sectionID="sec_GretaTSF" speed="0.2" time="62.879361862611816" trackID="trk_GretaReliefRd2" trainID="train43"/>
        <TrainHeadLeaveTrack cycleID="141" direction="UP" sectionID="sec_GretaTSF" speed="0.2" time="66.91524621635331" trackID="trk_GretaReliefRd2" trainID="train43"/>
        <TrainTailLeaveTrack cycleID="141" direction="UP" sectionID="sec_GretaTSF" speed="44100.67675560665" time="67.24019001519125" trackID="trk_GretaReliefRd2" trainID="train43"/>
        <TrainEnterTrack cycleID="151" direction="DOWN" sectionID="sec_GretaTSF" speed="0.2" time="68.04602852927843" trackID="trk_GretaReliefRd2" trainID="train38"/>
        <TrainHeadLeaveTrack cycleID="151" direction="UP" sectionID="sec_GretaTSF" speed="0.2" time="72.08191288301992" trackID="trk_GretaReliefRd2" trainID="train38"/>
        <TrainTailLeaveTrack cycleID="151" direction="DOWN" sectionID="sec_GretaTSF" speed="28217.785129203065" time="72.18568792216956" trackID="trk_GretaReliefRd2" trainID="train38"/>
        <TrainEnterTrack cycleID="160" direction="DOWN" sectionID="sec_GretaTSF" speed="0.2" time="73.71269519594509" trackID="trk_GretaReliefRd2" trainID="train23"/>
        <TrainHeadLeaveTrack cycleID="160" direction="UP" sectionID="sec_GretaTSF" speed="0.2" time="77.74857954968658" trackID="trk_GretaReliefRd2" trainID="train23"/>
        <TrainTailLeaveTrack cycleID="160" direction="UP" sectionID="sec_GretaTSF" speed="44100.67675560665" time="77.81505852464947" trackID="trk_GretaReliefRd2" trainID="train23"/>
        <TrainEnterTrack cycleID="197" direction="DOWN" sectionID="sec_GretaTSF" speed="0.2" time="102.4759550444249" trackID="trk_GretaReliefRd2" trainID="train28"/>
        <TrainHeadLeaveTrack cycleID="197" direction="UP" sectionID="sec_GretaTSF" speed="0.2" time="106.51183939816639" trackID="trk_GretaReliefRd2" trainID="train28"/>
        <TrainTailLeaveTrack cycleID="197" direction="UP" sectionID="sec_GretaTSF" speed="44100.67675560665" time="106.57831837312928" trackID="trk_GretaReliefRd2" trainID="train28"/>
        <TrainEnterTrack cycleID="211" direction="DOWN" sectionID="sec_GretaTSF" speed="0.2" time="119.76979969911662" trackID="trk_GretaReliefRd2" trainID="train25"/>
        <TrainHeadLeaveTrack cycleID="211" direction="UP" sectionID="sec_GretaTSF" speed="0.2" time="123.80568405285811" trackID="trk_GretaReliefRd2" trainID="train25"/>
        <TrainTailLeaveTrack cycleID="211" direction="DOWN" sectionID="sec_GretaTSF" speed="28286.374308469352" time="123.86706727208808" trackID="trk_GretaReliefRd2" trainID="train25"/>
        <TrainEnterTrack cycleID="220" direction="DOWN" sectionID="sec_GretaTSF" speed="0.2" time="123.90325620886969" trackID="trk_GretaReliefRd2" trainID="train29"/>
        <TrainHeadLeaveTrack cycleID="220" direction="UP" sectionID="sec_GretaTSF" speed="0.2" time="127.93914056261119" trackID="trk_GretaReliefRd2" trainID="train29"/>
        <TrainTailLeaveTrack cycleID="220" direction="UP" sectionID="sec_GretaTSF" speed="44100.67675560665" time="128.00380550645517" trackID="trk_GretaReliefRd2" trainID="train29"/>
        <TrainEnterTrack cycleID="243" direction="DOWN" sectionID="sec_GretaTSF" speed="0.2" time="163.5023130362163" trackID="trk_GretaReliefRd2" trainID="train32"/>
        <TrainHeadLeaveTrack cycleID="243" direction="UP" sectionID="sec_GretaTSF" speed="0.2" time="167.5381973899578" trackID="trk_GretaReliefRd2" trainID="train32"/>
        <TrainTailLeaveTrack cycleID="243" direction="UP" sectionID="sec_GretaTSF" speed="44100.67675560665" time="169.2256024271848" trackID="trk_GretaReliefRd2" trainID="train32"/>
        <TrainEnterTrack cycleID="255" direction="DOWN" sectionID="sec_GretaTSF" speed="0.2" time="169.2617913639664" trackID="trk_GretaReliefRd2" trainID="train51"/>
        <TrainHeadLeaveTrack cycleID="255" direction="UP" sectionID="sec_GretaTSF" speed="0.2" time="173.2976757177079" trackID="trk_GretaReliefRd2" trainID="train51"/>
        <TrainTailLeaveTrack cycleID="255" direction="DOWN" sectionID="sec_GretaTSF" speed="28286.374308469352" time="173.35905893693788" trackID="trk_GretaReliefRd2" trainID="train51"/>
        <TrainEnterTrack cycleID="269" direction="DOWN" sectionID="sec_GretaTSF" speed="0.2" time="175.09572978967776" trackID="trk_GretaReliefRd2" trainID="train37"/>
        <TrainHeadLeaveTrack cycleID="269" direction="UP" sectionID="sec_GretaTSF" speed="0.2" time="179.13161414341926" trackID="trk_GretaReliefRd2" trainID="train37"/>
        <TrainTailLeaveTrack cycleID="269" direction="UP" sectionID="sec_GretaTSF" speed="44100.67675560665" time="179.1980931183822" trackID="trk_GretaReliefRd2" trainID="train37"/>
        <TrainEnterTrack cycleID="278" direction="DOWN" sectionID="sec_GretaTSF" speed="0.2" time="179.2342820551638" trackID="trk_GretaReliefRd2" trainID="train9"/>
        <TrainHeadLeaveTrack cycleID="278" direction="UP" sectionID="sec_GretaTSF" speed="0.2" time="183.27016640890528" trackID="trk_GretaReliefRd2" trainID="train9"/>
        <TrainTailLeaveTrack cycleID="278" direction="UP" sectionID="sec_GretaTSF" speed="44100.67675560665" time="183.40234952085157" trackID="trk_GretaReliefRd2" trainID="train9"/>
        <TrainEnterTrack cycleID="296" direction="DOWN" sectionID="sec_GretaTSF" speed="0.2" time="185.39076285179465" trackID="trk_GretaReliefRd2" trainID="train23"/>
        <TrainHeadLeaveTrack cycleID="296" direction="UP" sectionID="sec_GretaTSF" speed="0.2" time="189.42664720553614" trackID="trk_GretaReliefRd2" trainID="train23"/>
        <TrainTailLeaveTrack cycleID="296" direction="UP" sectionID="sec_GretaTSF" speed="44100.67675560665" time="189.52832995092544" trackID="trk_GretaReliefRd2" trainID="train23"/>
        <TrainEnterTrack cycleID="317" direction="DOWN" sectionID="sec_GretaTSF" speed="0.2" time="199.86830114416236" trackID="trk_GretaReliefRd2" trainID="train17"/>
        <TrainHeadLeaveTrack cycleID="317" direction="UP" sectionID="sec_GretaTSF" speed="0.2" time="203.90418549790385" trackID="trk_GretaReliefRd2" trainID="train17"/>
        <TrainTailLeaveTrack cycleID="317" direction="DOWN" sectionID="sec_GretaTSF" speed="28217.785129203065" time="204.04649330872655" trackID="trk_GretaReliefRd2" trainID="train17"/>
        <TrainEnterTrack cycleID="332" direction="DOWN" sectionID="sec_GretaTSF" speed="0.2" time="205.58889864146315" trackID="trk_GretaReliefRd2" trainID="train32"/>
        <TrainHeadLeaveTrack cycleID="332" direction="UP" sectionID="sec_GretaTSF" speed="0.2" time="209.62478299520464" trackID="trk_GretaReliefRd2" trainID="train32"/>
        <TrainTailLeaveTrack cycleID="332" direction="UP" sectionID="sec_GretaTSF" speed="44100.67675560665" time="209.69126197016757" trackID="trk_GretaReliefRd2" trainID="train32"/>
        <TrainEnterTrack cycleID="338" direction="DOWN" sectionID="sec_GretaTSF" speed="0.2" time="209.72745090694917" trackID="trk_GretaReliefRd2" trainID="train28"/>
        <TrainHeadLeaveTrack cycleID="338" direction="UP" sectionID="sec_GretaTSF" speed="0.2" time="213.76333526069067" trackID="trk_GretaReliefRd2" trainID="train28"/>
        <TrainTailLeaveTrack cycleID="338" direction="UP" sectionID="sec_GretaTSF" speed="44100.67675560665" time="213.8298142356536" trackID="trk_GretaReliefRd2" trainID="train28"/>
        <TrainEnterTrack cycleID="367" direction="DOWN" sectionID="sec_GretaTSF" speed="0.2" time="250.21269519594506" trackID="trk_GretaReliefRd2" trainID="train34"/>
        <TrainHeadLeaveTrack cycleID="367" direction="UP" sectionID="sec_GretaTSF" speed="0.2" time="254.24857954968655" trackID="trk_GretaReliefRd2" trainID="train34"/>
        <TrainTailLeaveTrack cycleID="367" direction="UP" sectionID="sec_GretaTSF" speed="44100.67675560665" time="254.3150585246495" trackID="trk_GretaReliefRd2" trainID="train34"/>
        <TrainEnterTrack cycleID="378" direction="DOWN" sectionID="sec_GretaTSF" speed="0.2" time="255.60686982637716" trackID="trk_GretaReliefRd2" trainID="train14"/>
        <TrainHeadLeaveTrack cycleID="378" direction="UP" sectionID="sec_GretaTSF" speed="0.2" time="259.6427541801187" trackID="trk_GretaReliefRd2" trainID="train14"/>
        <TrainTailLeaveTrack cycleID="378" direction="DOWN" sectionID="sec_GretaTSF" speed="28286.374308469352" time="259.7041373993486" trackID="trk_GretaReliefRd2" trainID="train14"/>
        <TrainEnterTrack cycleID="395" direction="DOWN" sectionID="sec_GretaTSF" speed="0.2" time="262.68005648642503" trackID="trk_GretaReliefRd2" trainID="train24"/>
        <TrainHeadLeaveTrack cycleID="395" direction="UP" sectionID="sec_GretaTSF" speed="0.2" time="266.80158250440434" trackID="trk_GretaReliefRd2" trainID="train24"/>
        <TrainTailLeaveTrack cycleID="395" direction="UP" sectionID="sec_GretaTSF" speed="44100.67675560665" time="267.31583452408626" trackID="trk_GretaReliefRd2" trainID="train24"/>
        <TrainEnterTrack cycleID="423" direction="DOWN" sectionID="sec_GretaTSF" speed="0.2" time="293.483340177583" trackID="trk_GretaReliefRd2" trainID="train32"/>
        <TrainHeadLeaveTrack cycleID="423" direction="UP" sectionID="sec_GretaTSF" speed="0.2" time="297.5192245313245" trackID="trk_GretaReliefRd2" trainID="train32"/>
        <TrainTailLeaveTrack cycleID="423" direction="UP" sectionID="sec_GretaTSF" speed="44100.67675560665" time="297.8782424664157" trackID="trk_GretaReliefRd2" trainID="train32"/>
        <TrainEnterTrack cycleID="430" direction="DOWN" sectionID="sec_GretaTSF" speed="0.2" time="297.91443140319734" trackID="trk_GretaReliefRd2" trainID="train29"/>
        <TrainHeadLeaveTrack cycleID="430" direction="UP" sectionID="sec_GretaTSF" speed="0.2" time="301.95031575693883" trackID="trk_GretaReliefRd2" trainID="train29"/>
        <TrainTailLeaveTrack cycleID="430" direction="UP" sectionID="sec_GretaTSF" speed="44100.67675560665" time="302.04188934396655" trackID="trk_GretaReliefRd2" trainID="train29"/>
        <TrainEnterTrack cycleID="444" direction="DOWN" sectionID="sec_GretaTSF" speed="0.2" time="303.54602852927854" trackID="trk_GretaReliefRd2" trainID="train43"/>
        <TrainHeadLeaveTrack cycleID="444" direction="UP" sectionID="sec_GretaTSF" speed="0.2" time="307.58191288302004" trackID="trk_GretaReliefRd2" trainID="train43"/>
        <TrainTailLeaveTrack cycleID="444" direction="UP" sectionID="sec_GretaTSF" speed="44100.67675560665" time="307.6483918579829" trackID="trk_GretaReliefRd2" trainID="train43"/>
        <TrainEnterTrack cycleID="452" direction="DOWN" sectionID="sec_GretaTSF" speed="0.2" time="308.2659902037292" trackID="trk_GretaReliefRd2" trainID="train47"/>
        <TrainHeadLeaveTrack cycleID="452" direction="UP" sectionID="sec_GretaTSF" speed="0.2" time="312.3018745574707" trackID="trk_GretaReliefRd2" trainID="train47"/>
        <TrainTailLeaveTrack cycleID="452" direction="DOWN" sectionID="sec_GretaTSF" speed="28286.374308469352" time="312.3632577767006" trackID="trk_GretaReliefRd2" trainID="train47"/>
        <TrainEnterTrack cycleID="462" direction="DOWN" sectionID="sec_GretaTSF" speed="0.2" time="313.6455493619547" trackID="trk_GretaReliefRd2" trainID="train55"/>
        <TrainHeadLeaveTrack cycleID="462" direction="UP" sectionID="sec_GretaTSF" speed="0.2" time="317.6814337156962" trackID="trk_GretaReliefRd2" trainID="train55"/>
        <TrainTailLeaveTrack cycleID="462" direction="DOWN" sectionID="sec_GretaTSF" speed="28286.374308469352" time="317.7428169349261" trackID="trk_GretaReliefRd2" trainID="train55"/>
        <TrainEnterTrack cycleID="475" direction="DOWN" sectionID="sec_GretaTSF" speed="0.2" time="343.21269519594523" trackID="trk_GretaReliefRd2" trainID="train2"/>
        <TrainHeadLeaveTrack cycleID="475" direction="UP" sectionID="sec_GretaTSF" speed="0.2" time="347.2486893679431" trackID="trk_GretaReliefRd2" trainID="train2"/>
        <TrainTailLeaveTrack cycleID="475" direction="UP" sectionID="sec_GretaTSF" speed="35217.35526031388" time="347.3056181678787" trackID="trk_GretaReliefRd2" trainID="train2"/>
        <TrainEnterTrack cycleID="487" direction="DOWN" sectionID="sec_GretaTSF" speed="0.2" time="349.99000979077977" trackID="trk_GretaReliefRd2" trainID="train37"/>
        <TrainHeadLeaveTrack cycleID="487" direction="UP" sectionID="sec_GretaTSF" speed="0.2" time="354.0350520294235" trackID="trk_GretaReliefRd2" trainID="train37"/>
        <TrainTailLeaveTrack cycleID="487" direction="UP" sectionID="sec_GretaTSF" speed="44100.67675560665" time="354.35121548834036" trackID="trk_GretaReliefRd2" trainID="train37"/>
        <TrainEnterTrack cycleID="493" direction="DOWN" sectionID="sec_GretaTSF" speed="0.2" time="354.387404425122" trackID="trk_GretaReliefRd2" trainID="train13"/>
        <TrainHeadLeaveTrack cycleID="493" direction="UP" sectionID="sec_GretaTSF" speed="0.2" time="358.4232887788635" trackID="trk_GretaReliefRd2" trainID="train13"/>
        <TrainTailLeaveTrack cycleID="493" direction="UP" sectionID="sec_GretaTSF" speed="44100.67675560665" time="358.48795372270746" trackID="trk_GretaReliefRd2" trainID="train13"/>
        <TrainEnterTrack cycleID="501" direction="DOWN" sectionID="sec_GretaTSF" speed="0.2" time="358.5241426594891" trackID="trk_GretaReliefRd2" trainID="train38"/>
        <TrainHeadLeaveTrack cycleID="501" direction="UP" sectionID="sec_GretaTSF" speed="0.2" time="362.5600270132306" trackID="trk_GretaReliefRd2" trainID="train38"/>
        <TrainTailLeaveTrack cycleID="501" direction="DOWN" sectionID="sec_GretaTSF" speed="28217.785129203065" time="362.6997161786525" trackID="trk_GretaReliefRd2" trainID="train38"/>
        <TrainEnterTrack cycleID="532" direction="DOWN" sectionID="sec_GretaTSF" speed="0.2" time="395.54602852927854" trackID="trk_GretaReliefRd2" trainID="train14"/>
        <TrainHeadLeaveTrack cycleID="532" direction="UP" sectionID="sec_GretaTSF" speed="0.2" time="399.58191288302004" trackID="trk_GretaReliefRd2" trainID="train14"/>
        <TrainTailLeaveTrack cycleID="532" direction="DOWN" sectionID="sec_GretaTSF" speed="28217.785129203065" time="400.17506572438157" trackID="trk_GretaReliefRd2" trainID="train14"/>
        <TrainEnterTrack cycleID="542" direction="DOWN" sectionID="sec_GretaTSF" speed="0.2" time="402.21269519594523" trackID="trk_GretaReliefRd2" trainID="train25"/>
        <TrainHeadLeaveTrack cycleID="542" direction="UP" sectionID="sec_GretaTSF" speed="0.2" time="406.2485795496867" trackID="trk_GretaReliefRd2" trainID="train25"/>
        <TrainTailLeaveTrack cycleID="542" direction="DOWN" sectionID="sec_GretaTSF" speed="28286.374308469352" time="406.30996276891665" trackID="trk_GretaReliefRd2" trainID="train25"/>
        <TrainEnterTrack cycleID="563" direction="DOWN" sectionID="sec_GretaTSF" speed="0.2" time="412.84672315309166" trackID="trk_GretaReliefRd2" trainID="train6"/>
        <TrainHeadLeaveTrack cycleID="563" direction="UP" sectionID="sec_GretaTSF" speed="0.2" time="416.88260750683315" trackID="trk_GretaReliefRd2" trainID="train6"/>
        <TrainTailLeaveTrack cycleID="563" direction="DOWN" sectionID="sec_GretaTSF" speed="28286.374308469352" time="416.9369201839774" trackID="trk_GretaReliefRd2" trainID="train6"/>
        <TrainEnterTrack cycleID="574" direction="DOWN" sectionID="sec_GretaTSF" speed="0.2" time="417.4360351456128" trackID="trk_GretaReliefRd2" trainID="train29"/>
        <TrainHeadLeaveTrack cycleID="574" direction="UP" sectionID="sec_GretaTSF" speed="0.2" time="421.513188088842" trackID="trk_GretaReliefRd2" trainID="train29"/>
        <TrainTailLeaveTrack cycleID="574" direction="UP" sectionID="sec_GretaTSF" speed="44100.67675560665" time="421.78884471767105" trackID="trk_GretaReliefRd2" trainID="train29"/>
        <TrainEnterTrack cycleID="587" direction="DOWN" sectionID="sec_GretaTSF" speed="0.2" time="434.84672315309166" trackID="trk_GretaReliefRd2" trainID="train47"/>
        <TrainHeadLeaveTrack cycleID="587" direction="UP" sectionID="sec_GretaTSF" speed="0.2" time="438.88260750683315" trackID="trk_GretaReliefRd2" trainID="train47"/>
        <TrainTailLeaveTrack cycleID="587" direction="DOWN" sectionID="sec_GretaTSF" speed="28286.374308469352" time="438.9439907260631" trackID="trk_GretaReliefRd2" trainID="train47"/>
        <TrainEnterTrack cycleID="603" direction="DOWN" sectionID="sec_GretaTSF" speed="0.2" time="445.21269519594523" trackID="trk_GretaReliefRd2" trainID="train13"/>
        <TrainHeadLeaveTrack cycleID="603" direction="UP" sectionID="sec_GretaTSF" speed="0.2" time="449.2485795496867" trackID="trk_GretaReliefRd2" trainID="train13"/>
        <TrainTailLeaveTrack cycleID="603" direction="UP" sectionID="sec_GretaTSF" speed="44100.67675560665" time="449.3132444935307" trackID="trk_GretaReliefRd2" trainID="train13"/>
        <TrainEnterTrack cycleID="609" direction="DOWN" sectionID="sec_GretaTSF" speed="0.2" time="449.34943343031233" trackID="trk_GretaReliefRd2" trainID="train43"/>
        <TrainHeadLeaveTrack cycleID="609" direction="UP" sectionID="sec_GretaTSF" speed="0.2" time="453.3853177840538" trackID="trk_GretaReliefRd2" trainID="train43"/>
        <TrainTailLeaveTrack cycleID="609" direction="UP" sectionID="sec_GretaTSF" speed="44100.67675560665" time="453.4517967590167" trackID="trk_GretaReliefRd2" trainID="train43"/>
        <TrainEnterTrack cycleID="623" direction="DOWN" sectionID="sec_GretaTSF" speed="0.2" time="464.3624605752298" trackID="trk_GretaReliefRd2" trainID="train2"/>
        <TrainHeadLeaveTrack cycleID="623" direction="UP" sectionID="sec_GretaTSF" speed="0.2" time="468.3983449289713" trackID="trk_GretaReliefRd2" trainID="train2"/>
        <TrainTailLeaveTrack cycleID="623" direction="UP" sectionID="sec_GretaTSF" speed="44100.67675560665" time="469.00140992358985" trackID="trk_GretaReliefRd2" trainID="train2"/>
        <TrainEnterTrack cycleID="630" direction="DOWN" sectionID="sec_GretaTSF" speed="0.2" time="471.50188664602575" trackID="trk_GretaReliefRd2" trainID="train53"/>
        <TrainHeadLeaveTrack cycleID="630" direction="UP" sectionID="sec_GretaTSF" speed="0.2" time="475.7304000290921" trackID="trk_GretaReliefRd2" trainID="train53"/>
        <TrainTailLeaveTrack cycleID="630" direction="DOWN" sectionID="sec_GretaTSF" speed="28217.785129203065" time="475.80241890650166" trackID="trk_GretaReliefRd2" trainID="train53"/>
        <TrainEnterTrack cycleID="637" direction="DOWN" sectionID="sec_GretaTSF" speed="0.2" time="475.8332063375809" trackID="trk_GretaReliefRd2" trainID="train21"/>
        <TrainHeadLeaveTrack cycleID="637" direction="UP" sectionID="sec_GretaTSF" speed="0.2" time="479.9136227300888" trackID="trk_GretaReliefRd2" trainID="train21"/>
        <TrainTailLeaveTrack cycleID="637" direction="UP" sectionID="sec_GretaTSF" speed="35217.35526031388" time="479.9478354573924" trackID="trk_GretaReliefRd2" trainID="train21"/>
        <TrainEnterTrack cycleID="679" direction="DOWN" sectionID="sec_GretaTSF" speed="0.2" time="520.694624243463" trackID="trk_GretaReliefRd2" trainID="train25"/>
        <TrainHeadLeaveTrack cycleID="679" direction="UP" sectionID="sec_GretaTSF" speed="0.2" time="524.732807683361" trackID="trk_GretaReliefRd2" trainID="train25"/>
        <TrainTailLeaveTrack cycleID="679" direction="DOWN" sectionID="sec_GretaTSF" speed="28217.785129203065" time="524.9806759414275" trackID="trk_GretaReliefRd2" trainID="train25"/>
        <TrainEnterTrack cycleID="699" direction="DOWN" sectionID="sec_GretaTSF" speed="0.2" time="526.8605148166313" trackID="trk_GretaReliefRd2" trainID="train34"/>
        <TrainHeadLeaveTrack cycleID="699" direction="UP" sectionID="sec_GretaTSF" speed="0.2" time="530.8963991703728" trackID="trk_GretaReliefRd2" trainID="train34"/>
        <TrainTailLeaveTrack cycleID="699" direction="UP" sectionID="sec_GretaTSF" speed="44100.67675560665" time="530.9628781453357" trackID="trk_GretaReliefRd2" trainID="train34"/>
        <TrainEnterTrack cycleID="707" direction="DOWN" sectionID="sec_GretaTSF" speed="0.2" time="531.3092883777584" trackID="trk_GretaReliefRd2" trainID="train28"/>
        <TrainHeadLeaveTrack cycleID="707" direction="UP" sectionID="sec_GretaTSF" speed="0.2" time="535.3451727314999" trackID="trk_GretaReliefRd2" trainID="train28"/>
        <TrainTailLeaveTrack cycleID="707" direction="UP" sectionID="sec_GretaTSF" speed="44100.67675560665" time="535.4116517064629" trackID="trk_GretaReliefRd2" trainID="train28"/>
        <TrainEnterTrack cycleID="716" direction="DOWN" sectionID="sec_GretaTSF" speed="0.2" time="539.5133898197582" trackID="trk_GretaReliefRd2" trainID="train14"/>
        <TrainHeadLeaveTrack cycleID="716" direction="UP" sectionID="sec_GretaTSF" speed="0.2" time="543.5492741734997" trackID="trk_GretaReliefRd2" trainID="train14"/>
        <TrainTailLeaveTrack cycleID="716" direction="DOWN" sectionID="sec_GretaTSF" speed="28286.374308469352" time="543.6106573927298" trackID="trk_GretaReliefRd2" trainID="train14"/>
        <TrainEnterTrack cycleID="742" direction="DOWN" sectionID="sec_GretaTSF" speed="0.2" time="566.8793618626119" trackID="trk_GretaReliefRd2" trainID="train34"/>
        <TrainHeadLeaveTrack cycleID="742" direction="UP" sectionID="sec_GretaTSF" speed="0.2" time="570.9152462163534" trackID="trk_GretaReliefRd2" trainID="train34"/>
        <TrainTailLeaveTrack cycleID="742" direction="UP" sectionID="sec_GretaTSF" speed="44100.67675560665" time="570.9817251913163" trackID="trk_GretaReliefRd2" trainID="train34"/>
        <TrainEnterTrack cycleID="752" direction="DOWN" sectionID="sec_GretaTSF" speed="0.2" time="575.9450661228681" trackID="trk_GretaReliefRd2" trainID="train32"/>
        <TrainHeadLeaveTrack cycleID="752" direction="UP" sectionID="sec_GretaTSF" speed="0.2" time="579.9809504766096" trackID="trk_GretaReliefRd2" trainID="train32"/>
        <TrainTailLeaveTrack cycleID="752" direction="UP" sectionID="sec_GretaTSF" speed="44100.67675560665" time="580.2924024771442" trackID="trk_GretaReliefRd2" trainID="train32"/>
        <TrainEnterTrack cycleID="762" direction="DOWN" sectionID="sec_GretaTSF" speed="0.2" time="580.3285914139258" trackID="trk_GretaReliefRd2" trainID="train14"/>
        <TrainHeadLeaveTrack cycleID="762" direction="UP" sectionID="sec_GretaTSF" speed="0.2" time="584.3644757676673" trackID="trk_GretaReliefRd2" trainID="train14"/>
        <TrainTailLeaveTrack cycleID="762" direction="DOWN" sectionID="sec_GretaTSF" speed="28217.785129203065" time="584.5058423298734" trackID="trk_GretaReliefRd2" trainID="train14"/>
        <TrainEnterTrack cycleID="771" direction="DOWN" sectionID="sec_GretaTSF" speed="0.2" time="584.5445841645072" trackID="trk_GretaReliefRd2" trainID="train53"/>
        <TrainHeadLeaveTrack cycleID="771" direction="UP" sectionID="sec_GretaTSF" speed="0.2" time="588.5804685182487" trackID="trk_GretaReliefRd2" trainID="train53"/>
        <TrainTailLeaveTrack cycleID="771" direction="DOWN" sectionID="sec_GretaTSF" speed="28286.374308469352" time="588.6418517374788" trackID="trk_GretaReliefRd2" trainID="train53"/>
        <TrainEnterTrack cycleID="809" direction="DOWN" sectionID="sec_GretaTSF" speed="0.2" time="625.6593834637409" trackID="trk_GretaReliefRd2" trainID="train21"/>
        <TrainHeadLeaveTrack cycleID="809" direction="UP" sectionID="sec_GretaTSF" speed="0.2" time="629.6952678174824" trackID="trk_GretaReliefRd2" trainID="train21"/>
        <TrainTailLeaveTrack cycleID="809" direction="UP" sectionID="sec_GretaTSF" speed="35217.35526031388" time="629.7289123629679" trackID="trk_GretaReliefRd2" trainID="train21"/>
        <TrainEnterTrack cycleID="821" direction="DOWN" sectionID="sec_GretaTSF" speed="0.2" time="635.2126951959452" trackID="trk_GretaReliefRd2" trainID="train14"/>
        <TrainHeadLeaveTrack cycleID="821" direction="UP" sectionID="sec_GretaTSF" speed="0.2" time="639.2485795496867" trackID="trk_GretaReliefRd2" trainID="train14"/>
        <TrainTailLeaveTrack cycleID="821" direction="DOWN" sectionID="sec_GretaTSF" speed="28286.374308469352" time="639.3099627689168" trackID="trk_GretaReliefRd2" trainID="train14"/>
        <TrainEnterTrack cycleID="848" direction="DOWN" sectionID="sec_GretaTSF" speed="0.2" time="664.680056486425" trackID="trk_GretaReliefRd2" trainID="train12"/>
        <TrainHeadLeaveTrack cycleID="848" direction="UP" sectionID="sec_GretaTSF" speed="0.2" time="668.7159408401665" trackID="trk_GretaReliefRd2" trainID="train12"/>
        <TrainTailLeaveTrack cycleID="848" direction="UP" sectionID="sec_GretaTSF" speed="44100.67675560665" time="668.8455939763189" trackID="trk_GretaReliefRd2" trainID="train12"/>
        <TrainEnterTrack cycleID="882" direction="DOWN" sectionID="sec_GretaTSF" speed="0.2" time="696.5460285292785" trackID="trk_GretaReliefRd2" trainID="train47"/>
        <TrainHeadLeaveTrack cycleID="882" direction="UP" sectionID="sec_GretaTSF" speed="0.2" time="700.58191288302" trackID="trk_GretaReliefRd2" trainID="train47"/>
        <TrainTailLeaveTrack cycleID="882" direction="DOWN" sectionID="sec_GretaTSF" speed="28217.785129203065" time="700.6963499566136" trackID="trk_GretaReliefRd2" trainID="train47"/>
        <TrainEnterTrack cycleID="896" direction="DOWN" sectionID="sec_GretaTSF" speed="0.2" time="725.6004327571615" trackID="trk_GretaReliefRd2" trainID="train12"/>
        <TrainHeadLeaveTrack cycleID="896" direction="UP" sectionID="sec_GretaTSF" speed="0.2" time="729.636317110903" trackID="trk_GretaReliefRd2" trainID="train12"/>
        <TrainTailLeaveTrack cycleID="896" direction="UP" sectionID="sec_GretaTSF" speed="44100.67675560665" time="729.7027960858659" trackID="trk_GretaReliefRd2" trainID="train12"/>
        <TrainEnterTrack cycleID="904" direction="DOWN" sectionID="sec_GretaTSF" speed="0.2" time="729.7389850226475" trackID="trk_GretaReliefRd2" trainID="train51"/>
        <TrainHeadLeaveTrack cycleID="904" direction="UP" sectionID="sec_GretaTSF" speed="0.2" time="733.774869376389" trackID="trk_GretaReliefRd2" trainID="train51"/>
        <TrainTailLeaveTrack cycleID="904" direction="DOWN" sectionID="sec_GretaTSF" speed="28286.374308469352" time="733.836252595619" trackID="trk_GretaReliefRd2" trainID="train51"/>
        <TrainEnterTrack cycleID="918" direction="DOWN" sectionID="sec_GretaTSF" speed="0.2" time="738.3793618626119" trackID="trk_GretaReliefRd2" trainID="train30"/>
        <TrainHeadLeaveTrack cycleID="918" direction="UP" sectionID="sec_GretaTSF" speed="0.2" time="742.4152462163534" trackID="trk_GretaReliefRd2" trainID="train30"/>
        <TrainTailLeaveTrack cycleID="918" direction="DOWN" sectionID="sec_GretaTSF" speed="28286.374308469352" time="742.4766294355834" trackID="trk_GretaReliefRd2" trainID="train30"/>
        <TrainEnterTrack cycleID="930" direction="DOWN" sectionID="sec_GretaTSF" speed="0.2" time="747.782502532668" trackID="trk_GretaReliefRd2" trainID="train29"/>
        <TrainHeadLeaveTrack cycleID="930" direction="UP" sectionID="sec_GretaTSF" speed="0.2" time="751.8183868864095" trackID="trk_GretaReliefRd2" trainID="train29"/>
        <TrainTailLeaveTrack cycleID="930" direction="UP" sectionID="sec_GretaTSF" speed="44100.67675560665" time="751.8830518302535" trackID="trk_GretaReliefRd2" trainID="train29"/>
        <TrainEnterTrack cycleID="941" direction="DOWN" sectionID="sec_GretaTSF" speed="0.2" time="759.8793618626119" trackID="trk_GretaReliefRd2" trainID="train3"/>
        <TrainHeadLeaveTrack cycleID="941" direction="UP" sectionID="sec_GretaTSF" speed="0.2" time="763.9152462163534" trackID="trk_GretaReliefRd2" trainID="train3"/>
        <TrainTailLeaveTrack cycleID="941" direction="DOWN" sectionID="sec_GretaTSF" speed="28286.374308469352" time="763.9766294355834" trackID="trk_GretaReliefRd2" trainID="train3"/>
        <TrainEnterTrack cycleID="961" direction="DOWN" sectionID="sec_GretaTSF" speed="0.2" time="788.6122150385519" trackID="trk_GretaReliefRd2" trainID="train34"/>
        <TrainHeadLeaveTrack cycleID="961" direction="UP" sectionID="sec_GretaTSF" speed="0.2" time="792.7581139465713" trackID="trk_GretaReliefRd2" trainID="train34"/>
        <TrainTailLeaveTrack cycleID="961" direction="UP" sectionID="sec_GretaTSF" speed="44100.67675560665" time="793.0746705987846" trackID="trk_GretaReliefRd2" trainID="train34"/>
        <TrainEnterTrack cycleID="983" direction="DOWN" sectionID="sec_GretaTSF" speed="0.2" time="810.7126951959452" trackID="trk_GretaReliefRd2" trainID="train50"/>
        <TrainHeadLeaveTrack cycleID="983" direction="UP" sectionID="sec_GretaTSF" speed="0.2" time="814.7485795496867" trackID="trk_GretaReliefRd2" trainID="train50"/>
        <TrainTailLeaveTrack cycleID="983" direction="DOWN" sectionID="sec_GretaTSF" speed="28286.374308469352" time="814.8099627689168" trackID="trk_GretaReliefRd2" trainID="train50"/>
        <TrainEnterTrack cycleID="988" direction="DOWN" sectionID="sec_GretaTSF" speed="0.2" time="815.3793618626119" trackID="trk_GretaReliefRd2" trainID="train29"/>
        <TrainHeadLeaveTrack cycleID="988" direction="UP" sectionID="sec_GretaTSF" speed="0.2" time="819.4152462163534" trackID="trk_GretaReliefRd2" trainID="train29"/>
        <TrainTailLeaveTrack cycleID="988" direction="UP" sectionID="sec_GretaTSF" speed="35217.35526031388" time="819.4716068344708" trackID="trk_GretaReliefRd2" trainID="train29"/>
        <TrainEnterTrack cycleID="999" direction="DOWN" sectionID="sec_GretaTSF" speed="0.2" time="823.180056486425" trackID="trk_GretaReliefRd2" trainID="train1"/>
        <TrainHeadLeaveTrack cycleID="999" direction="UP" sectionID="sec_GretaTSF" speed="0.2" time="827.2159408401665" trackID="trk_GretaReliefRd2" trainID="train1"/>
        <TrainTailLeaveTrack cycleID="999" direction="UP" sectionID="sec_GretaTSF" speed="44100.67675560665" time="827.2824198151294" trackID="trk_GretaReliefRd2" trainID="train1"/>
        <TrainEnterTrack cycleID="1042" direction="DOWN" sectionID="sec_GretaTSF" speed="0.2" time="882.39946697529" trackID="trk_GretaReliefRd2" trainID="train14"/>
        <TrainHeadLeaveTrack cycleID="1042" direction="UP" sectionID="sec_GretaTSF" speed="0.2" time="886.4353513290315" trackID="trk_GretaReliefRd2" trainID="train14"/>
        <TrainTailLeaveTrack cycleID="1042" direction="DOWN" sectionID="sec_GretaTSF" speed="28286.374308469352" time="886.4967345482615" trackID="trk_GretaReliefRd2" trainID="train14"/>
	</railEvents>
</railLog>