<railLog>
	<railEvents>
        <Track direction="null" sectionID="sec_SconeLoop" trackID="trk_SconeLoop_2"/>
        <TrainEnterTrack cycleID="77" direction="DOWN" sectionID="sec_SconeLoop" speed="0.2" time="16.106277648870492" trackID="trk_SconeLoop_2" trainID="train25"/>
        <TrainHeadLeaveTrack cycleID="77" direction="UP" sectionID="sec_SconeLoop" speed="0.2" time="16.139610982203827" trackID="trk_SconeLoop_2" trainID="train25"/>
        <TrainTailLeaveTrack cycleID="77" direction="DOWN" sectionID="sec_SconeLoop" speed="54251.464192405634" time="16.161730200880474" trackID="trk_SconeLoop_2" trainID="train25"/>
        <TrainEnterTrack cycleID="80" direction="DOWN" sectionID="sec_SconeLoop" speed="0.2" time="25.44423137011384" trackID="trk_SconeLoop_2" trainID="train30"/>
        <TrainHeadLeaveTrack cycleID="80" direction="UP" sectionID="sec_SconeLoop" speed="0.2" time="25.477564703447175" trackID="trk_SconeLoop_2" trainID="train30"/>
        <TrainTailLeaveTrack cycleID="80" direction="DOWN" sectionID="sec_SconeLoop" speed="54251.464192405634" time="25.499683922123822" trackID="trk_SconeLoop_2" trainID="train30"/>
        <TrainEnterTrack cycleID="89" direction="DOWN" sectionID="sec_SconeLoop" speed="0.2" time="36.77569693362199" trackID="trk_SconeLoop_2" trainID="train35"/>
        <TrainHeadLeaveTrack cycleID="89" direction="UP" sectionID="sec_SconeLoop" speed="0.2" time="36.80903026695532" trackID="trk_SconeLoop_2" trainID="train35"/>
        <TrainTailLeaveTrack cycleID="89" direction="DOWN" sectionID="sec_SconeLoop" speed="54251.464192405634" time="36.83114948563196" trackID="trk_SconeLoop_2" trainID="train35"/>
        <TrainEnterTrack cycleID="92" direction="DOWN" sectionID="sec_SconeLoop" speed="0.2" time="37.91918125117499" trackID="trk_SconeLoop_2" trainID="train38"/>
        <TrainHeadLeaveTrack cycleID="92" direction="UP" sectionID="sec_SconeLoop" speed="0.2" time="37.95251458450832" trackID="trk_SconeLoop_2" trainID="train38"/>
        <TrainTailLeaveTrack cycleID="92" direction="DOWN" sectionID="sec_SconeLoop" speed="54251.464192405634" time="37.974633803184965" trackID="trk_SconeLoop_2" trainID="train38"/>
        <TrainEnterTrack cycleID="102" direction="DOWN" sectionID="sec_SconeLoop" speed="0.2" time="42.170907030716855" trackID="trk_SconeLoop_2" trainID="train48"/>
        <TrainHeadLeaveTrack cycleID="102" direction="UP" sectionID="sec_SconeLoop" speed="0.2" time="42.204240364050186" trackID="trk_SconeLoop_2" trainID="train48"/>
        <TrainTailLeaveTrack cycleID="102" direction="DOWN" sectionID="sec_SconeLoop" speed="54251.464192405634" time="42.22635958272683" trackID="trk_SconeLoop_2" trainID="train48"/>
        <TrainEnterTrack cycleID="129" direction="DOWN" sectionID="sec_SconeLoop" speed="0.2" time="45.732119060134536" trackID="trk_SconeLoop_2" trainID="train18"/>
        <TrainHeadLeaveTrack cycleID="129" direction="UP" sectionID="sec_SconeLoop" speed="0.2" time="45.76545239346787" trackID="trk_SconeLoop_2" trainID="train18"/>
        <TrainTailLeaveTrack cycleID="129" direction="DOWN" sectionID="sec_SconeLoop" speed="54251.464192405634" time="45.78757161214451" trackID="trk_SconeLoop_2" trainID="train18"/>
        <TrainEnterTrack cycleID="115" direction="DOWN" sectionID="sec_SconeLoop" speed="0.2" time="46.073856915368786" trackID="trk_SconeLoop_2" trainID="train7"/>
        <TrainHeadLeaveTrack cycleID="115" direction="UP" sectionID="sec_SconeLoop" speed="0.2" time="46.10719024870212" trackID="trk_SconeLoop_2" trainID="train7"/>
        <TrainTailLeaveTrack cycleID="115" direction="DOWN" sectionID="sec_SconeLoop" speed="54251.464192405634" time="46.12930946737876" trackID="trk_SconeLoop_2" trainID="train7"/>
        <TrainEnterTrack cycleID="118" direction="DOWN" sectionID="sec_SconeLoop" speed="0.2" time="53.353597919213605" trackID="trk_SconeLoop_2" trainID="train6"/>
        <TrainHeadLeaveTrack cycleID="118" direction="UP" sectionID="sec_SconeLoop" speed="0.2" time="53.38693125254694" trackID="trk_SconeLoop_2" trainID="train6"/>
        <TrainTailLeaveTrack cycleID="118" direction="DOWN" sectionID="sec_SconeLoop" speed="54251.464192405634" time="53.405363934777476" trackID="trk_SconeLoop_2" trainID="train6"/>
        <TrainEnterTrack cycleID="124" direction="DOWN" sectionID="sec_SconeLoop" speed="0.2" time="56.92507474159139" trackID="trk_SconeLoop_2" trainID="train14"/>
        <TrainHeadLeaveTrack cycleID="124" direction="UP" sectionID="sec_SconeLoop" speed="0.2" time="56.95840807492472" trackID="trk_SconeLoop_2" trainID="train14"/>
        <TrainTailLeaveTrack cycleID="124" direction="DOWN" sectionID="sec_SconeLoop" speed="54251.464192405634" time="56.98052729360136" trackID="trk_SconeLoop_2" trainID="train14"/>
        <TrainEnterTrack cycleID="132" direction="DOWN" sectionID="sec_SconeLoop" speed="0.2" time="61.15851844071138" trackID="trk_SconeLoop_2" trainID="train25"/>
        <TrainHeadLeaveTrack cycleID="132" direction="UP" sectionID="sec_SconeLoop" speed="0.2" time="61.191851774044714" trackID="trk_SconeLoop_2" trainID="train25"/>
        <TrainTailLeaveTrack cycleID="132" direction="DOWN" sectionID="sec_SconeLoop" speed="54251.464192405634" time="61.21397099272136" trackID="trk_SconeLoop_2" trainID="train25"/>
        <TrainEnterTrack cycleID="137" direction="DOWN" sectionID="sec_SconeLoop" speed="0.2" time="69.62649046238326" trackID="trk_SconeLoop_2" trainID="train30"/>
        <TrainHeadLeaveTrack cycleID="137" direction="UP" sectionID="sec_SconeLoop" speed="0.2" time="69.65982379571659" trackID="trk_SconeLoop_2" trainID="train30"/>
        <TrainTailLeaveTrack cycleID="137" direction="DOWN" sectionID="sec_SconeLoop" speed="54251.464192405634" time="69.68194301439324" trackID="trk_SconeLoop_2" trainID="train30"/>
        <TrainEnterTrack cycleID="140" direction="DOWN" sectionID="sec_SconeLoop" speed="0.2" time="70.13080762308583" trackID="trk_SconeLoop_2" trainID="train44"/>
        <TrainHeadLeaveTrack cycleID="140" direction="UP" sectionID="sec_SconeLoop" speed="0.2" time="70.16414095641916" trackID="trk_SconeLoop_2" trainID="train44"/>
        <TrainTailLeaveTrack cycleID="140" direction="DOWN" sectionID="sec_SconeLoop" speed="54251.464192405634" time="70.18626017509581" trackID="trk_SconeLoop_2" trainID="train44"/>
        <TrainEnterTrack cycleID="142" direction="DOWN" sectionID="sec_SconeLoop" speed="0.2" time="70.83267640401195" trackID="trk_SconeLoop_2" trainID="train47"/>
        <TrainHeadLeaveTrack cycleID="142" direction="UP" sectionID="sec_SconeLoop" speed="0.2" time="70.86600973734528" trackID="trk_SconeLoop_2" trainID="train47"/>
        <TrainTailLeaveTrack cycleID="142" direction="DOWN" sectionID="sec_SconeLoop" speed="54251.464192405634" time="70.88812895602193" trackID="trk_SconeLoop_2" trainID="train47"/>
        <TrainEnterTrack cycleID="161" direction="DOWN" sectionID="sec_SconeLoop" speed="0.2" time="71.26084099634251" trackID="trk_SconeLoop_2" trainID="train18"/>
        <TrainHeadLeaveTrack cycleID="161" direction="UP" sectionID="sec_SconeLoop" speed="0.2" time="71.29417432967584" trackID="trk_SconeLoop_2" trainID="train18"/>
        <TrainTailLeaveTrack cycleID="161" direction="DOWN" sectionID="sec_SconeLoop" speed="54251.464192405634" time="71.31629354835249" trackID="trk_SconeLoop_2" trainID="train18"/>
        <TrainEnterTrack cycleID="146" direction="DOWN" sectionID="sec_SconeLoop" speed="0.2" time="73.0905505134984" trackID="trk_SconeLoop_2" trainID="train51"/>
        <TrainHeadLeaveTrack cycleID="146" direction="UP" sectionID="sec_SconeLoop" speed="0.2" time="73.12388384683173" trackID="trk_SconeLoop_2" trainID="train51"/>
        <TrainTailLeaveTrack cycleID="146" direction="DOWN" sectionID="sec_SconeLoop" speed="54251.464192405634" time="73.14600306550838" trackID="trk_SconeLoop_2" trainID="train51"/>
        <TrainEnterTrack cycleID="149" direction="DOWN" sectionID="sec_SconeLoop" speed="0.2" time="74.23484514412695" trackID="trk_SconeLoop_2" trainID="train35"/>
        <TrainHeadLeaveTrack cycleID="149" direction="UP" sectionID="sec_SconeLoop" speed="0.2" time="74.26817847746028" trackID="trk_SconeLoop_2" trainID="train35"/>
        <TrainTailLeaveTrack cycleID="149" direction="DOWN" sectionID="sec_SconeLoop" speed="54251.464192405634" time="74.29029769613693" trackID="trk_SconeLoop_2" trainID="train35"/>
        <TrainEnterTrack cycleID="152" direction="DOWN" sectionID="sec_SconeLoop" speed="0.2" time="75.41730299546879" trackID="trk_SconeLoop_2" trainID="train50"/>
        <TrainHeadLeaveTrack cycleID="152" direction="UP" sectionID="sec_SconeLoop" speed="0.2" time="75.45063632880212" trackID="trk_SconeLoop_2" trainID="train50"/>
        <TrainTailLeaveTrack cycleID="152" direction="DOWN" sectionID="sec_SconeLoop" speed="54251.464192405634" time="75.47275554747877" trackID="trk_SconeLoop_2" trainID="train50"/>
        <TrainEnterTrack cycleID="153" direction="DOWN" sectionID="sec_SconeLoop" speed="0.2" time="77.1399392546996" trackID="trk_SconeLoop_2" trainID="train3"/>
        <TrainHeadLeaveTrack cycleID="153" direction="UP" sectionID="sec_SconeLoop" speed="0.2" time="77.17327258803293" trackID="trk_SconeLoop_2" trainID="train3"/>
        <TrainTailLeaveTrack cycleID="153" direction="DOWN" sectionID="sec_SconeLoop" speed="54251.464192405634" time="77.19539180670958" trackID="trk_SconeLoop_2" trainID="train3"/>
        <TrainEnterTrack cycleID="165" direction="DOWN" sectionID="sec_SconeLoop" speed="0.2" time="79.03493458388517" trackID="trk_SconeLoop_2" trainID="train7"/>
        <TrainHeadLeaveTrack cycleID="165" direction="UP" sectionID="sec_SconeLoop" speed="0.2" time="79.0682679172185" trackID="trk_SconeLoop_2" trainID="train7"/>
        <TrainTailLeaveTrack cycleID="165" direction="DOWN" sectionID="sec_SconeLoop" speed="54251.464192405634" time="79.09038713589516" trackID="trk_SconeLoop_2" trainID="train7"/>
        <TrainEnterTrack cycleID="179" direction="DOWN" sectionID="sec_SconeLoop" speed="0.2" time="89.25500137983487" trackID="trk_SconeLoop_2" trainID="train53"/>
        <TrainHeadLeaveTrack cycleID="179" direction="UP" sectionID="sec_SconeLoop" speed="0.2" time="89.2883347131682" trackID="trk_SconeLoop_2" trainID="train53"/>
        <TrainTailLeaveTrack cycleID="179" direction="DOWN" sectionID="sec_SconeLoop" speed="54251.464192405634" time="89.31045393184485" trackID="trk_SconeLoop_2" trainID="train53"/>
        <TrainEnterTrack cycleID="177" direction="DOWN" sectionID="sec_SconeLoop" speed="0.2" time="94.70893964980645" trackID="trk_SconeLoop_2" trainID="train38"/>
        <TrainHeadLeaveTrack cycleID="177" direction="UP" sectionID="sec_SconeLoop" speed="0.2" time="94.74227298313978" trackID="trk_SconeLoop_2" trainID="train38"/>
        <TrainTailLeaveTrack cycleID="177" direction="DOWN" sectionID="sec_SconeLoop" speed="54251.464192405634" time="94.76439220181643" trackID="trk_SconeLoop_2" trainID="train38"/>
        <TrainEnterTrack cycleID="187" direction="DOWN" sectionID="sec_SconeLoop" speed="0.2" time="97.36415080330761" trackID="trk_SconeLoop_2" trainID="train45"/>
        <TrainHeadLeaveTrack cycleID="187" direction="UP" sectionID="sec_SconeLoop" speed="0.2" time="97.39748413664094" trackID="trk_SconeLoop_2" trainID="train45"/>
        <TrainTailLeaveTrack cycleID="187" direction="DOWN" sectionID="sec_SconeLoop" speed="54251.464192405634" time="97.41960335531759" trackID="trk_SconeLoop_2" trainID="train45"/>
        <TrainEnterTrack cycleID="191" direction="DOWN" sectionID="sec_SconeLoop" speed="0.2" time="101.46545202349816" trackID="trk_SconeLoop_2" trainID="train39"/>
        <TrainHeadLeaveTrack cycleID="191" direction="UP" sectionID="sec_SconeLoop" speed="0.2" time="101.49878535683149" trackID="trk_SconeLoop_2" trainID="train39"/>
        <TrainTailLeaveTrack cycleID="191" direction="DOWN" sectionID="sec_SconeLoop" speed="54251.464192405634" time="101.52090457550814" trackID="trk_SconeLoop_2" trainID="train39"/>
        <TrainEnterTrack cycleID="188" direction="DOWN" sectionID="sec_SconeLoop" speed="0.2" time="102.82833791444796" trackID="trk_SconeLoop_2" trainID="train55"/>
        <TrainHeadLeaveTrack cycleID="188" direction="UP" sectionID="sec_SconeLoop" speed="0.2" time="102.86167124778129" trackID="trk_SconeLoop_2" trainID="train55"/>
        <TrainTailLeaveTrack cycleID="188" direction="DOWN" sectionID="sec_SconeLoop" speed="54251.464192405634" time="102.88379046645794" trackID="trk_SconeLoop_2" trainID="train55"/>
        <TrainEnterTrack cycleID="192" direction="DOWN" sectionID="sec_SconeLoop" speed="0.2" time="106.42330298118512" trackID="trk_SconeLoop_2" trainID="train17"/>
        <TrainHeadLeaveTrack cycleID="192" direction="UP" sectionID="sec_SconeLoop" speed="0.2" time="106.45663631451845" trackID="trk_SconeLoop_2" trainID="train17"/>
        <TrainTailLeaveTrack cycleID="192" direction="DOWN" sectionID="sec_SconeLoop" speed="54251.464192405634" time="106.47506899674899" trackID="trk_SconeLoop_2" trainID="train17"/>
        <TrainEnterTrack cycleID="209" direction="DOWN" sectionID="sec_SconeLoop" speed="0.2" time="126.59210238708238" trackID="trk_SconeLoop_2" trainID="train14"/>
        <TrainHeadLeaveTrack cycleID="209" direction="UP" sectionID="sec_SconeLoop" speed="0.2" time="126.62543572041571" trackID="trk_SconeLoop_2" trainID="train14"/>
        <TrainTailLeaveTrack cycleID="209" direction="DOWN" sectionID="sec_SconeLoop" speed="54251.464192405634" time="126.64755493909236" trackID="trk_SconeLoop_2" trainID="train14"/>
        <TrainEnterTrack cycleID="211" direction="DOWN" sectionID="sec_SconeLoop" speed="0.2" time="126.93384024231663" trackID="trk_SconeLoop_2" trainID="train25"/>
        <TrainHeadLeaveTrack cycleID="211" direction="UP" sectionID="sec_SconeLoop" speed="0.2" time="126.96717357564997" trackID="trk_SconeLoop_2" trainID="train25"/>
        <TrainTailLeaveTrack cycleID="211" direction="DOWN" sectionID="sec_SconeLoop" speed="54251.464192405634" time="126.98929279432662" trackID="trk_SconeLoop_2" trainID="train25"/>
        <TrainEnterTrack cycleID="214" direction="DOWN" sectionID="sec_SconeLoop" speed="0.2" time="129.93629946792436" trackID="trk_SconeLoop_2" trainID="train30"/>
        <TrainHeadLeaveTrack cycleID="214" direction="UP" sectionID="sec_SconeLoop" speed="0.2" time="129.9696328012577" trackID="trk_SconeLoop_2" trainID="train30"/>
        <TrainTailLeaveTrack cycleID="214" direction="DOWN" sectionID="sec_SconeLoop" speed="54251.464192405634" time="129.99175201993432" trackID="trk_SconeLoop_2" trainID="train30"/>
        <TrainEnterTrack cycleID="219" direction="DOWN" sectionID="sec_SconeLoop" speed="0.2" time="130.58779139288237" trackID="trk_SconeLoop_2" trainID="train44"/>
        <TrainHeadLeaveTrack cycleID="219" direction="UP" sectionID="sec_SconeLoop" speed="0.2" time="130.6211247262157" trackID="trk_SconeLoop_2" trainID="train44"/>
        <TrainTailLeaveTrack cycleID="219" direction="DOWN" sectionID="sec_SconeLoop" speed="54251.464192405634" time="130.64324394489233" trackID="trk_SconeLoop_2" trainID="train44"/>
        <TrainEnterTrack cycleID="227" direction="DOWN" sectionID="sec_SconeLoop" speed="0.2" time="143.72512720582574" trackID="trk_SconeLoop_2" trainID="train48"/>
        <TrainHeadLeaveTrack cycleID="227" direction="UP" sectionID="sec_SconeLoop" speed="0.2" time="143.75846053915907" trackID="trk_SconeLoop_2" trainID="train48"/>
        <TrainTailLeaveTrack cycleID="227" direction="DOWN" sectionID="sec_SconeLoop" speed="54251.464192405634" time="143.7805797578357" trackID="trk_SconeLoop_2" trainID="train48"/>
        <TrainEnterTrack cycleID="229" direction="DOWN" sectionID="sec_SconeLoop" speed="0.2" time="149.24375881371927" trackID="trk_SconeLoop_2" trainID="train47"/>
        <TrainHeadLeaveTrack cycleID="229" direction="UP" sectionID="sec_SconeLoop" speed="0.2" time="149.2770921470526" trackID="trk_SconeLoop_2" trainID="train47"/>
        <TrainTailLeaveTrack cycleID="229" direction="DOWN" sectionID="sec_SconeLoop" speed="54251.464192405634" time="149.29921136572924" trackID="trk_SconeLoop_2" trainID="train47"/>
        <TrainEnterTrack cycleID="254" direction="DOWN" sectionID="sec_SconeLoop" speed="0.2" time="162.7967675754639" trackID="trk_SconeLoop_2" trainID="train7"/>
        <TrainHeadLeaveTrack cycleID="254" direction="UP" sectionID="sec_SconeLoop" speed="0.2" time="162.83010090879722" trackID="trk_SconeLoop_2" trainID="train7"/>
        <TrainTailLeaveTrack cycleID="254" direction="DOWN" sectionID="sec_SconeLoop" speed="54251.464192405634" time="162.85222012747386" trackID="trk_SconeLoop_2" trainID="train7"/>
        <TrainEnterTrack cycleID="262" direction="DOWN" sectionID="sec_SconeLoop" speed="0.2" time="163.189871993133" trackID="trk_SconeLoop_2" trainID="train45"/>
        <TrainHeadLeaveTrack cycleID="262" direction="UP" sectionID="sec_SconeLoop" speed="0.2" time="163.22320532646634" trackID="trk_SconeLoop_2" trainID="train45"/>
        <TrainTailLeaveTrack cycleID="262" direction="DOWN" sectionID="sec_SconeLoop" speed="54251.464192405634" time="163.24532454514298" trackID="trk_SconeLoop_2" trainID="train45"/>
        <TrainEnterTrack cycleID="242" direction="DOWN" sectionID="sec_SconeLoop" speed="0.2" time="170.6884727188987" trackID="trk_SconeLoop_2" trainID="train35"/>
        <TrainHeadLeaveTrack cycleID="242" direction="UP" sectionID="sec_SconeLoop" speed="0.2" time="170.72180605223204" trackID="trk_SconeLoop_2" trainID="train35"/>
        <TrainTailLeaveTrack cycleID="242" direction="DOWN" sectionID="sec_SconeLoop" speed="54251.464192405634" time="170.74392527090868" trackID="trk_SconeLoop_2" trainID="train35"/>
        <TrainEnterTrack cycleID="248" direction="DOWN" sectionID="sec_SconeLoop" speed="0.2" time="171.74046519035255" trackID="trk_SconeLoop_2" trainID="train18"/>
        <TrainHeadLeaveTrack cycleID="248" direction="UP" sectionID="sec_SconeLoop" speed="0.2" time="171.77379852368588" trackID="trk_SconeLoop_2" trainID="train18"/>
        <TrainTailLeaveTrack cycleID="248" direction="DOWN" sectionID="sec_SconeLoop" speed="54251.464192405634" time="171.79591774236252" trackID="trk_SconeLoop_2" trainID="train18"/>
        <TrainEnterTrack cycleID="252" direction="DOWN" sectionID="sec_SconeLoop" speed="0.2" time="175.95579517414384" trackID="trk_SconeLoop_2" trainID="train3"/>
        <TrainHeadLeaveTrack cycleID="252" direction="UP" sectionID="sec_SconeLoop" speed="0.2" time="175.98912850747718" trackID="trk_SconeLoop_2" trainID="train3"/>
        <TrainTailLeaveTrack cycleID="252" direction="DOWN" sectionID="sec_SconeLoop" speed="54251.464192405634" time="176.0112477261538" trackID="trk_SconeLoop_2" trainID="train3"/>
        <TrainEnterTrack cycleID="255" direction="DOWN" sectionID="sec_SconeLoop" speed="0.2" time="176.63047556555367" trackID="trk_SconeLoop_2" trainID="train51"/>
        <TrainHeadLeaveTrack cycleID="255" direction="UP" sectionID="sec_SconeLoop" speed="0.2" time="176.663808898887" trackID="trk_SconeLoop_2" trainID="train51"/>
        <TrainTailLeaveTrack cycleID="255" direction="DOWN" sectionID="sec_SconeLoop" speed="54251.464192405634" time="176.68592811756363" trackID="trk_SconeLoop_2" trainID="train51"/>
        <TrainEnterTrack cycleID="256" direction="DOWN" sectionID="sec_SconeLoop" speed="0.2" time="177.5179055269451" trackID="trk_SconeLoop_2" trainID="train53"/>
        <TrainHeadLeaveTrack cycleID="256" direction="UP" sectionID="sec_SconeLoop" speed="0.2" time="177.55123886027843" trackID="trk_SconeLoop_2" trainID="train53"/>
        <TrainTailLeaveTrack cycleID="256" direction="DOWN" sectionID="sec_SconeLoop" speed="54251.464192405634" time="177.57335807895507" trackID="trk_SconeLoop_2" trainID="train53"/>
        <TrainEnterTrack cycleID="265" direction="DOWN" sectionID="sec_SconeLoop" speed="0.2" time="181.88808460773055" trackID="trk_SconeLoop_2" trainID="train55"/>
        <TrainHeadLeaveTrack cycleID="265" direction="UP" sectionID="sec_SconeLoop" speed="0.2" time="181.92141794106388" trackID="trk_SconeLoop_2" trainID="train55"/>
        <TrainTailLeaveTrack cycleID="265" direction="DOWN" sectionID="sec_SconeLoop" speed="54251.464192405634" time="181.94353715974052" trackID="trk_SconeLoop_2" trainID="train55"/>
        <TrainEnterTrack cycleID="270" direction="DOWN" sectionID="sec_SconeLoop" speed="0.2" time="182.40076071259892" trackID="trk_SconeLoop_2" trainID="train14"/>
        <TrainHeadLeaveTrack cycleID="270" direction="UP" sectionID="sec_SconeLoop" speed="0.2" time="182.43409404593226" trackID="trk_SconeLoop_2" trainID="train14"/>
        <TrainTailLeaveTrack cycleID="270" direction="DOWN" sectionID="sec_SconeLoop" speed="54251.464192405634" time="182.4562132646089" trackID="trk_SconeLoop_2" trainID="train14"/>
        <TrainEnterTrack cycleID="276" direction="DOWN" sectionID="sec_SconeLoop" speed="0.2" time="183.96909541263847" trackID="trk_SconeLoop_2" trainID="train44"/>
        <TrainHeadLeaveTrack cycleID="276" direction="UP" sectionID="sec_SconeLoop" speed="0.2" time="184.0024287459718" trackID="trk_SconeLoop_2" trainID="train44"/>
        <TrainTailLeaveTrack cycleID="276" direction="DOWN" sectionID="sec_SconeLoop" speed="54251.464192405634" time="184.02454796464843" trackID="trk_SconeLoop_2" trainID="train44"/>
        <TrainEnterTrack cycleID="301" direction="DOWN" sectionID="sec_SconeLoop" speed="0.2" time="185.11257775655184" trackID="trk_SconeLoop_2" trainID="train48"/>
        <TrainHeadLeaveTrack cycleID="301" direction="UP" sectionID="sec_SconeLoop" speed="0.2" time="185.14591108988517" trackID="trk_SconeLoop_2" trainID="train48"/>
        <TrainTailLeaveTrack cycleID="301" direction="DOWN" sectionID="sec_SconeLoop" speed="54251.464192405634" time="185.1680303085618" trackID="trk_SconeLoop_2" trainID="train48"/>
        <TrainEnterTrack cycleID="283" direction="DOWN" sectionID="sec_SconeLoop" speed="0.2" time="186.5024560179745" trackID="trk_SconeLoop_2" trainID="train38"/>
        <TrainHeadLeaveTrack cycleID="283" direction="UP" sectionID="sec_SconeLoop" speed="0.2" time="186.53578935130784" trackID="trk_SconeLoop_2" trainID="train38"/>
        <TrainTailLeaveTrack cycleID="283" direction="DOWN" sectionID="sec_SconeLoop" speed="54251.464192405634" time="186.55790856998448" trackID="trk_SconeLoop_2" trainID="train38"/>
        <TrainEnterTrack cycleID="282" direction="DOWN" sectionID="sec_SconeLoop" speed="0.2" time="187.12606157658993" trackID="trk_SconeLoop_2" trainID="train50"/>
        <TrainHeadLeaveTrack cycleID="282" direction="UP" sectionID="sec_SconeLoop" speed="0.2" time="187.15939490992326" trackID="trk_SconeLoop_2" trainID="train50"/>
        <TrainTailLeaveTrack cycleID="282" direction="DOWN" sectionID="sec_SconeLoop" speed="54251.464192405634" time="187.1815141285999" trackID="trk_SconeLoop_2" trainID="train50"/>
        <TrainEnterTrack cycleID="285" direction="DOWN" sectionID="sec_SconeLoop" speed="0.2" time="188.37875011958596" trackID="trk_SconeLoop_2" trainID="train6"/>
        <TrainHeadLeaveTrack cycleID="285" direction="UP" sectionID="sec_SconeLoop" speed="0.2" time="188.4120834529193" trackID="trk_SconeLoop_2" trainID="train6"/>
        <TrainTailLeaveTrack cycleID="285" direction="DOWN" sectionID="sec_SconeLoop" speed="54251.464192405634" time="188.43051613514982" trackID="trk_SconeLoop_2" trainID="train6"/>
        <TrainEnterTrack cycleID="308" direction="DOWN" sectionID="sec_SconeLoop" speed="0.2" time="196.09094717579745" trackID="trk_SconeLoop_2" trainID="train39"/>
        <TrainHeadLeaveTrack cycleID="308" direction="UP" sectionID="sec_SconeLoop" speed="0.2" time="196.12428050913078" trackID="trk_SconeLoop_2" trainID="train39"/>
        <TrainTailLeaveTrack cycleID="308" direction="DOWN" sectionID="sec_SconeLoop" speed="54251.464192405634" time="196.14639972780742" trackID="trk_SconeLoop_2" trainID="train39"/>
        <TrainEnterTrack cycleID="317" direction="DOWN" sectionID="sec_SconeLoop" speed="0.2" time="207.04066908911895" trackID="trk_SconeLoop_2" trainID="train17"/>
        <TrainHeadLeaveTrack cycleID="317" direction="UP" sectionID="sec_SconeLoop" speed="0.2" time="207.07400242245228" trackID="trk_SconeLoop_2" trainID="train17"/>
        <TrainTailLeaveTrack cycleID="317" direction="DOWN" sectionID="sec_SconeLoop" speed="54251.464192405634" time="207.0924351046828" trackID="trk_SconeLoop_2" trainID="train17"/>
        <TrainEnterTrack cycleID="326" direction="DOWN" sectionID="sec_SconeLoop" speed="0.2" time="210.43499766305357" trackID="trk_SconeLoop_2" trainID="train3"/>
        <TrainHeadLeaveTrack cycleID="326" direction="UP" sectionID="sec_SconeLoop" speed="0.2" time="210.4683309963869" trackID="trk_SconeLoop_2" trainID="train3"/>
        <TrainTailLeaveTrack cycleID="326" direction="DOWN" sectionID="sec_SconeLoop" speed="54251.464192405634" time="210.49045021506353" trackID="trk_SconeLoop_2" trainID="train3"/>
        <TrainEnterTrack cycleID="328" direction="DOWN" sectionID="sec_SconeLoop" speed="0.2" time="211.73708962178387" trackID="trk_SconeLoop_2" trainID="train53"/>
        <TrainHeadLeaveTrack cycleID="328" direction="UP" sectionID="sec_SconeLoop" speed="0.2" time="211.7704229551172" trackID="trk_SconeLoop_2" trainID="train53"/>
        <TrainTailLeaveTrack cycleID="328" direction="DOWN" sectionID="sec_SconeLoop" speed="54251.464192405634" time="211.79254217379383" trackID="trk_SconeLoop_2" trainID="train53"/>
        <TrainEnterTrack cycleID="333" direction="DOWN" sectionID="sec_SconeLoop" speed="0.2" time="213.62260835737206" trackID="trk_SconeLoop_2" trainID="train51"/>
        <TrainHeadLeaveTrack cycleID="333" direction="UP" sectionID="sec_SconeLoop" speed="0.2" time="213.6559416907054" trackID="trk_SconeLoop_2" trainID="train51"/>
        <TrainTailLeaveTrack cycleID="333" direction="DOWN" sectionID="sec_SconeLoop" speed="54251.464192405634" time="213.67806090938203" trackID="trk_SconeLoop_2" trainID="train51"/>
        <TrainEnterTrack cycleID="336" direction="DOWN" sectionID="sec_SconeLoop" speed="0.2" time="215.7178836734418" trackID="trk_SconeLoop_2" trainID="train14"/>
        <TrainHeadLeaveTrack cycleID="336" direction="UP" sectionID="sec_SconeLoop" speed="0.2" time="215.75121700677514" trackID="trk_SconeLoop_2" trainID="train14"/>
        <TrainTailLeaveTrack cycleID="336" direction="DOWN" sectionID="sec_SconeLoop" speed="54251.464192405634" time="215.77333622545177" trackID="trk_SconeLoop_2" trainID="train14"/>
        <TrainEnterTrack cycleID="343" direction="DOWN" sectionID="sec_SconeLoop" speed="0.2" time="218.79387056986795" trackID="trk_SconeLoop_2" trainID="train50"/>
        <TrainHeadLeaveTrack cycleID="343" direction="UP" sectionID="sec_SconeLoop" speed="0.2" time="218.82720390320128" trackID="trk_SconeLoop_2" trainID="train50"/>
        <TrainTailLeaveTrack cycleID="343" direction="DOWN" sectionID="sec_SconeLoop" speed="54251.464192405634" time="218.84932312187792" trackID="trk_SconeLoop_2" trainID="train50"/>
        <TrainEnterTrack cycleID="351" direction="DOWN" sectionID="sec_SconeLoop" speed="0.2" time="242.25663631451843" trackID="trk_SconeLoop_2" trainID="train30"/>
        <TrainHeadLeaveTrack cycleID="351" direction="UP" sectionID="sec_SconeLoop" speed="0.2" time="242.28996964785176" trackID="trk_SconeLoop_2" trainID="train30"/>
        <TrainTailLeaveTrack cycleID="351" direction="DOWN" sectionID="sec_SconeLoop" speed="54251.464192405634" time="242.3120888665284" trackID="trk_SconeLoop_2" trainID="train30"/>
        <TrainEnterTrack cycleID="352" direction="DOWN" sectionID="sec_SconeLoop" speed="0.2" time="242.75663631451843" trackID="trk_SconeLoop_2" trainID="train25"/>
        <TrainHeadLeaveTrack cycleID="352" direction="UP" sectionID="sec_SconeLoop" speed="0.2" time="242.78996964785176" trackID="trk_SconeLoop_2" trainID="train25"/>
        <TrainTailLeaveTrack cycleID="352" direction="DOWN" sectionID="sec_SconeLoop" speed="54251.464192405634" time="242.8120888665284" trackID="trk_SconeLoop_2" trainID="train25"/>
        <TrainEnterTrack cycleID="353" direction="DOWN" sectionID="sec_SconeLoop" speed="0.2" time="248.05253487251858" trackID="trk_SconeLoop_2" trainID="train50"/>
        <TrainHeadLeaveTrack cycleID="353" direction="UP" sectionID="sec_SconeLoop" speed="0.2" time="248.0858682058519" trackID="trk_SconeLoop_2" trainID="train50"/>
        <TrainTailLeaveTrack cycleID="353" direction="DOWN" sectionID="sec_SconeLoop" speed="54251.464192405634" time="248.10798742452855" trackID="trk_SconeLoop_2" trainID="train50"/>
        <TrainEnterTrack cycleID="361" direction="DOWN" sectionID="sec_SconeLoop" speed="0.2" time="249.84327750580002" trackID="trk_SconeLoop_2" trainID="train48"/>
        <TrainHeadLeaveTrack cycleID="361" direction="UP" sectionID="sec_SconeLoop" speed="0.2" time="249.87661083913335" trackID="trk_SconeLoop_2" trainID="train48"/>
        <TrainTailLeaveTrack cycleID="361" direction="DOWN" sectionID="sec_SconeLoop" speed="54251.464192405634" time="249.89873005780998" trackID="trk_SconeLoop_2" trainID="train48"/>
        <TrainEnterTrack cycleID="369" direction="DOWN" sectionID="sec_SconeLoop" speed="0.2" time="255.7521771192225" trackID="trk_SconeLoop_2" trainID="train39"/>
        <TrainHeadLeaveTrack cycleID="369" direction="UP" sectionID="sec_SconeLoop" speed="0.2" time="255.78551045255583" trackID="trk_SconeLoop_2" trainID="train39"/>
        <TrainTailLeaveTrack cycleID="369" direction="DOWN" sectionID="sec_SconeLoop" speed="54251.464192405634" time="255.80762967123246" trackID="trk_SconeLoop_2" trainID="train39"/>
        <TrainEnterTrack cycleID="364" direction="DOWN" sectionID="sec_SconeLoop" speed="0.2" time="256.09391497445677" trackID="trk_SconeLoop_2" trainID="train38"/>
        <TrainHeadLeaveTrack cycleID="364" direction="UP" sectionID="sec_SconeLoop" speed="0.2" time="256.1272483077901" trackID="trk_SconeLoop_2" trainID="train38"/>
        <TrainTailLeaveTrack cycleID="364" direction="DOWN" sectionID="sec_SconeLoop" speed="54251.464192405634" time="256.1493675264668" trackID="trk_SconeLoop_2" trainID="train38"/>
        <TrainEnterTrack cycleID="366" direction="DOWN" sectionID="sec_SconeLoop" speed="0.2" time="256.61630188831185" trackID="trk_SconeLoop_2" trainID="train6"/>
        <TrainHeadLeaveTrack cycleID="366" direction="UP" sectionID="sec_SconeLoop" speed="0.2" time="256.6496352216452" trackID="trk_SconeLoop_2" trainID="train6"/>
        <TrainTailLeaveTrack cycleID="366" direction="DOWN" sectionID="sec_SconeLoop" speed="54251.464192405634" time="256.66806790387574" trackID="trk_SconeLoop_2" trainID="train6"/>
        <TrainEnterTrack cycleID="377" direction="DOWN" sectionID="sec_SconeLoop" speed="0.2" time="261.9639799215726" trackID="trk_SconeLoop_2" trainID="train51"/>
        <TrainHeadLeaveTrack cycleID="377" direction="UP" sectionID="sec_SconeLoop" speed="0.2" time="261.997313254906" trackID="trk_SconeLoop_2" trainID="train51"/>
        <TrainTailLeaveTrack cycleID="377" direction="DOWN" sectionID="sec_SconeLoop" speed="54251.464192405634" time="262.01943247358264" trackID="trk_SconeLoop_2" trainID="train51"/>
        <TrainEnterTrack cycleID="381" direction="DOWN" sectionID="sec_SconeLoop" speed="0.2" time="265.22824178722834" trackID="trk_SconeLoop_2" trainID="train47"/>
        <TrainHeadLeaveTrack cycleID="381" direction="UP" sectionID="sec_SconeLoop" speed="0.2" time="265.2615751205617" trackID="trk_SconeLoop_2" trainID="train47"/>
        <TrainTailLeaveTrack cycleID="381" direction="DOWN" sectionID="sec_SconeLoop" speed="54251.464192405634" time="265.28369433923837" trackID="trk_SconeLoop_2" trainID="train47"/>
        <TrainEnterTrack cycleID="393" direction="DOWN" sectionID="sec_SconeLoop" speed="0.2" time="267.7831382419498" trackID="trk_SconeLoop_2" trainID="train18"/>
        <TrainHeadLeaveTrack cycleID="393" direction="UP" sectionID="sec_SconeLoop" speed="0.2" time="267.8164715752832" trackID="trk_SconeLoop_2" trainID="train18"/>
        <TrainTailLeaveTrack cycleID="393" direction="DOWN" sectionID="sec_SconeLoop" speed="54251.464192405634" time="267.83859079395984" trackID="trk_SconeLoop_2" trainID="train18"/>
        <TrainEnterTrack cycleID="391" direction="DOWN" sectionID="sec_SconeLoop" speed="0.2" time="268.2874554026524" trackID="trk_SconeLoop_2" trainID="train45"/>
        <TrainHeadLeaveTrack cycleID="391" direction="UP" sectionID="sec_SconeLoop" speed="0.2" time="268.3207887359858" trackID="trk_SconeLoop_2" trainID="train45"/>
        <TrainTailLeaveTrack cycleID="391" direction="DOWN" sectionID="sec_SconeLoop" speed="54251.464192405634" time="268.34290795466245" trackID="trk_SconeLoop_2" trainID="train45"/>
        <TrainEnterTrack cycleID="390" direction="DOWN" sectionID="sec_SconeLoop" speed="0.2" time="269.5689896303033" trackID="trk_SconeLoop_2" trainID="train35"/>
        <TrainHeadLeaveTrack cycleID="390" direction="UP" sectionID="sec_SconeLoop" speed="0.2" time="269.60232296363665" trackID="trk_SconeLoop_2" trainID="train35"/>
        <TrainTailLeaveTrack cycleID="390" direction="DOWN" sectionID="sec_SconeLoop" speed="54251.464192405634" time="269.6244421823133" trackID="trk_SconeLoop_2" trainID="train35"/>
        <TrainEnterTrack cycleID="394" direction="DOWN" sectionID="sec_SconeLoop" speed="0.2" time="269.92418304506583" trackID="trk_SconeLoop_2" trainID="train55"/>
        <TrainHeadLeaveTrack cycleID="394" direction="UP" sectionID="sec_SconeLoop" speed="0.2" time="269.9575163783992" trackID="trk_SconeLoop_2" trainID="train55"/>
        <TrainTailLeaveTrack cycleID="394" direction="DOWN" sectionID="sec_SconeLoop" speed="54251.464192405634" time="269.97963559707586" trackID="trk_SconeLoop_2" trainID="train55"/>
        <TrainEnterTrack cycleID="407" direction="DOWN" sectionID="sec_SconeLoop" speed="0.2" time="279.98019301214526" trackID="trk_SconeLoop_2" trainID="train44"/>
        <TrainHeadLeaveTrack cycleID="407" direction="UP" sectionID="sec_SconeLoop" speed="0.2" time="280.0135263454786" trackID="trk_SconeLoop_2" trainID="train44"/>
        <TrainTailLeaveTrack cycleID="407" direction="DOWN" sectionID="sec_SconeLoop" speed="54251.464192405634" time="280.0356455641553" trackID="trk_SconeLoop_2" trainID="train44"/>
        <TrainEnterTrack cycleID="417" direction="DOWN" sectionID="sec_SconeLoop" speed="0.2" time="293.80263705349495" trackID="trk_SconeLoop_2" trainID="train25"/>
        <TrainHeadLeaveTrack cycleID="417" direction="UP" sectionID="sec_SconeLoop" speed="0.2" time="293.8359703868283" trackID="trk_SconeLoop_2" trainID="train25"/>
        <TrainTailLeaveTrack cycleID="417" direction="DOWN" sectionID="sec_SconeLoop" speed="54251.464192405634" time="293.858089605505" trackID="trk_SconeLoop_2" trainID="train25"/>
        <TrainEnterTrack cycleID="443" direction="DOWN" sectionID="sec_SconeLoop" speed="0.2" time="300.25739078442825" trackID="trk_SconeLoop_2" trainID="train39"/>
        <TrainHeadLeaveTrack cycleID="443" direction="UP" sectionID="sec_SconeLoop" speed="0.2" time="300.2907241177616" trackID="trk_SconeLoop_2" trainID="train39"/>
        <TrainTailLeaveTrack cycleID="443" direction="DOWN" sectionID="sec_SconeLoop" speed="54251.464192405634" time="300.3128433364383" trackID="trk_SconeLoop_2" trainID="train39"/>
        <TrainEnterTrack cycleID="438" direction="DOWN" sectionID="sec_SconeLoop" speed="0.2" time="301.61449790837463" trackID="trk_SconeLoop_2" trainID="train48"/>
        <TrainHeadLeaveTrack cycleID="438" direction="UP" sectionID="sec_SconeLoop" speed="0.2" time="301.647831241708" trackID="trk_SconeLoop_2" trainID="train48"/>
        <TrainTailLeaveTrack cycleID="438" direction="DOWN" sectionID="sec_SconeLoop" speed="54251.464192405634" time="301.66995046038465" trackID="trk_SconeLoop_2" trainID="train48"/>
        <TrainEnterTrack cycleID="426" direction="DOWN" sectionID="sec_SconeLoop" speed="0.2" time="302.5161812442019" trackID="trk_SconeLoop_2" trainID="train3"/>
        <TrainHeadLeaveTrack cycleID="426" direction="UP" sectionID="sec_SconeLoop" speed="0.2" time="302.54951457753526" trackID="trk_SconeLoop_2" trainID="train3"/>
        <TrainTailLeaveTrack cycleID="426" direction="DOWN" sectionID="sec_SconeLoop" speed="54251.464192405634" time="302.5716337962119" trackID="trk_SconeLoop_2" trainID="train3"/>
        <TrainEnterTrack cycleID="447" direction="DOWN" sectionID="sec_SconeLoop" speed="0.2" time="303.0976665107649" trackID="trk_SconeLoop_2" trainID="train45"/>
        <TrainHeadLeaveTrack cycleID="447" direction="UP" sectionID="sec_SconeLoop" speed="0.2" time="303.13099984409826" trackID="trk_SconeLoop_2" trainID="train45"/>
        <TrainTailLeaveTrack cycleID="447" direction="DOWN" sectionID="sec_SconeLoop" speed="54251.464192405634" time="303.1531190627749" trackID="trk_SconeLoop_2" trainID="train45"/>
        <TrainEnterTrack cycleID="427" direction="DOWN" sectionID="sec_SconeLoop" speed="0.2" time="303.44007042800826" trackID="trk_SconeLoop_2" trainID="train53"/>
        <TrainHeadLeaveTrack cycleID="427" direction="UP" sectionID="sec_SconeLoop" speed="0.2" time="303.4734037613416" trackID="trk_SconeLoop_2" trainID="train53"/>
        <TrainTailLeaveTrack cycleID="427" direction="DOWN" sectionID="sec_SconeLoop" speed="54251.464192405634" time="303.4955229800183" trackID="trk_SconeLoop_2" trainID="train53"/>
        <TrainEnterTrack cycleID="433" direction="DOWN" sectionID="sec_SconeLoop" speed="0.2" time="306.6268665966855" trackID="trk_SconeLoop_2" trainID="train14"/>
        <TrainHeadLeaveTrack cycleID="433" direction="UP" sectionID="sec_SconeLoop" speed="0.2" time="306.66019993001885" trackID="trk_SconeLoop_2" trainID="train14"/>
        <TrainTailLeaveTrack cycleID="433" direction="DOWN" sectionID="sec_SconeLoop" speed="54251.464192405634" time="306.6823191486955" trackID="trk_SconeLoop_2" trainID="train14"/>
        <TrainEnterTrack cycleID="441" direction="DOWN" sectionID="sec_SconeLoop" speed="0.2" time="309.28927502403883" trackID="trk_SconeLoop_2" trainID="train6"/>
        <TrainHeadLeaveTrack cycleID="441" direction="UP" sectionID="sec_SconeLoop" speed="0.2" time="309.3226083573722" trackID="trk_SconeLoop_2" trainID="train6"/>
        <TrainTailLeaveTrack cycleID="441" direction="DOWN" sectionID="sec_SconeLoop" speed="54251.464192405634" time="309.3410410396027" trackID="trk_SconeLoop_2" trainID="train6"/>
        <TrainEnterTrack cycleID="452" direction="DOWN" sectionID="sec_SconeLoop" speed="0.2" time="315.17590336515616" trackID="trk_SconeLoop_2" trainID="train47"/>
        <TrainHeadLeaveTrack cycleID="452" direction="UP" sectionID="sec_SconeLoop" speed="0.2" time="315.2092366984895" trackID="trk_SconeLoop_2" trainID="train47"/>
        <TrainTailLeaveTrack cycleID="452" direction="DOWN" sectionID="sec_SconeLoop" speed="54251.464192405634" time="315.2313559171662" trackID="trk_SconeLoop_2" trainID="train47"/>
        <TrainEnterTrack cycleID="456" direction="DOWN" sectionID="sec_SconeLoop" speed="0.2" time="316.6631141254316" trackID="trk_SconeLoop_2" trainID="train30"/>
        <TrainHeadLeaveTrack cycleID="456" direction="UP" sectionID="sec_SconeLoop" speed="0.2" time="316.69644745876496" trackID="trk_SconeLoop_2" trainID="train30"/>
        <TrainTailLeaveTrack cycleID="456" direction="DOWN" sectionID="sec_SconeLoop" speed="54251.464192405634" time="316.71856667744163" trackID="trk_SconeLoop_2" trainID="train30"/>
        <TrainEnterTrack cycleID="458" direction="DOWN" sectionID="sec_SconeLoop" speed="0.2" time="318.7611606228582" trackID="trk_SconeLoop_2" trainID="train50"/>
        <TrainHeadLeaveTrack cycleID="458" direction="UP" sectionID="sec_SconeLoop" speed="0.2" time="318.79449395619156" trackID="trk_SconeLoop_2" trainID="train50"/>
        <TrainTailLeaveTrack cycleID="458" direction="DOWN" sectionID="sec_SconeLoop" speed="54251.464192405634" time="318.8166131748682" trackID="trk_SconeLoop_2" trainID="train50"/>
        <TrainEnterTrack cycleID="462" direction="DOWN" sectionID="sec_SconeLoop" speed="0.2" time="320.56518939694894" trackID="trk_SconeLoop_2" trainID="train55"/>
        <TrainHeadLeaveTrack cycleID="462" direction="UP" sectionID="sec_SconeLoop" speed="0.2" time="320.5985227302823" trackID="trk_SconeLoop_2" trainID="train55"/>
        <TrainTailLeaveTrack cycleID="462" direction="DOWN" sectionID="sec_SconeLoop" speed="54251.464192405634" time="320.62064194895896" trackID="trk_SconeLoop_2" trainID="train55"/>
        <TrainEnterTrack cycleID="484" direction="DOWN" sectionID="sec_SconeLoop" speed="0.2" time="343.1370441365598" trackID="trk_SconeLoop_2" trainID="train39"/>
        <TrainHeadLeaveTrack cycleID="484" direction="UP" sectionID="sec_SconeLoop" speed="0.2" time="343.17037746989314" trackID="trk_SconeLoop_2" trainID="train39"/>
        <TrainTailLeaveTrack cycleID="484" direction="DOWN" sectionID="sec_SconeLoop" speed="54251.464192405634" time="343.1924966885698" trackID="trk_SconeLoop_2" trainID="train39"/>
        <TrainEnterTrack cycleID="468" direction="DOWN" sectionID="sec_SconeLoop" speed="0.2" time="347.94079551685405" trackID="trk_SconeLoop_2" trainID="train44"/>
        <TrainHeadLeaveTrack cycleID="468" direction="UP" sectionID="sec_SconeLoop" speed="0.2" time="347.9741288501874" trackID="trk_SconeLoop_2" trainID="train44"/>
        <TrainTailLeaveTrack cycleID="468" direction="DOWN" sectionID="sec_SconeLoop" speed="54251.464192405634" time="347.9962480688641" trackID="trk_SconeLoop_2" trainID="train44"/>
        <TrainEnterTrack cycleID="476" direction="DOWN" sectionID="sec_SconeLoop" speed="0.2" time="350.8276937768532" trackID="trk_SconeLoop_2" trainID="train25"/>
        <TrainHeadLeaveTrack cycleID="476" direction="UP" sectionID="sec_SconeLoop" speed="0.2" time="350.86102711018657" trackID="trk_SconeLoop_2" trainID="train25"/>
        <TrainTailLeaveTrack cycleID="476" direction="DOWN" sectionID="sec_SconeLoop" speed="54251.464192405634" time="350.88314632886323" trackID="trk_SconeLoop_2" trainID="train25"/>
        <TrainEnterTrack cycleID="488" direction="DOWN" sectionID="sec_SconeLoop" speed="0.2" time="360.40570736538933" trackID="trk_SconeLoop_2" trainID="train3"/>
        <TrainHeadLeaveTrack cycleID="488" direction="UP" sectionID="sec_SconeLoop" speed="0.2" time="360.4390406987227" trackID="trk_SconeLoop_2" trainID="train3"/>
        <TrainTailLeaveTrack cycleID="488" direction="DOWN" sectionID="sec_SconeLoop" speed="54251.464192405634" time="360.46115991739936" trackID="trk_SconeLoop_2" trainID="train3"/>
        <TrainEnterTrack cycleID="494" direction="DOWN" sectionID="sec_SconeLoop" speed="0.2" time="361.97639954303776" trackID="trk_SconeLoop_2" trainID="train47"/>
        <TrainHeadLeaveTrack cycleID="494" direction="UP" sectionID="sec_SconeLoop" speed="0.2" time="362.0097328763711" trackID="trk_SconeLoop_2" trainID="train47"/>
        <TrainTailLeaveTrack cycleID="494" direction="DOWN" sectionID="sec_SconeLoop" speed="54251.464192405634" time="362.0318520950478" trackID="trk_SconeLoop_2" trainID="train47"/>
        <TrainEnterTrack cycleID="489" direction="DOWN" sectionID="sec_SconeLoop" speed="0.2" time="362.3876185663325" trackID="trk_SconeLoop_2" trainID="train53"/>
        <TrainHeadLeaveTrack cycleID="489" direction="UP" sectionID="sec_SconeLoop" speed="0.2" time="362.42095189966585" trackID="trk_SconeLoop_2" trainID="train53"/>
        <TrainTailLeaveTrack cycleID="489" direction="DOWN" sectionID="sec_SconeLoop" speed="54251.464192405634" time="362.4430711183425" trackID="trk_SconeLoop_2" trainID="train53"/>
        <TrainEnterTrack cycleID="495" direction="DOWN" sectionID="sec_SconeLoop" speed="0.2" time="362.981242380294" trackID="trk_SconeLoop_2" trainID="train50"/>
        <TrainHeadLeaveTrack cycleID="495" direction="UP" sectionID="sec_SconeLoop" speed="0.2" time="363.0145757136274" trackID="trk_SconeLoop_2" trainID="train50"/>
        <TrainTailLeaveTrack cycleID="495" direction="DOWN" sectionID="sec_SconeLoop" speed="54251.464192405634" time="363.03669493230404" trackID="trk_SconeLoop_2" trainID="train50"/>
        <TrainEnterTrack cycleID="498" direction="DOWN" sectionID="sec_SconeLoop" speed="0.2" time="365.2406614086935" trackID="trk_SconeLoop_2" trainID="train55"/>
        <TrainHeadLeaveTrack cycleID="498" direction="UP" sectionID="sec_SconeLoop" speed="0.2" time="365.27399474202684" trackID="trk_SconeLoop_2" trainID="train55"/>
        <TrainTailLeaveTrack cycleID="498" direction="DOWN" sectionID="sec_SconeLoop" speed="54251.464192405634" time="365.2961139607035" trackID="trk_SconeLoop_2" trainID="train55"/>
        <TrainEnterTrack cycleID="501" direction="DOWN" sectionID="sec_SconeLoop" speed="0.2" time="365.744739444326" trackID="trk_SconeLoop_2" trainID="train38"/>
        <TrainHeadLeaveTrack cycleID="501" direction="UP" sectionID="sec_SconeLoop" speed="0.2" time="365.77807277765936" trackID="trk_SconeLoop_2" trainID="train38"/>
        <TrainTailLeaveTrack cycleID="501" direction="DOWN" sectionID="sec_SconeLoop" speed="54251.464192405634" time="365.800191996336" trackID="trk_SconeLoop_2" trainID="train38"/>
        <TrainEnterTrack cycleID="504" direction="DOWN" sectionID="sec_SconeLoop" speed="0.2" time="366.7022533571871" trackID="trk_SconeLoop_2" trainID="train51"/>
        <TrainHeadLeaveTrack cycleID="504" direction="UP" sectionID="sec_SconeLoop" speed="0.2" time="366.73558669052045" trackID="trk_SconeLoop_2" trainID="train51"/>
        <TrainTailLeaveTrack cycleID="504" direction="DOWN" sectionID="sec_SconeLoop" speed="54251.464192405634" time="366.7577059091971" trackID="trk_SconeLoop_2" trainID="train51"/>
        <TrainEnterTrack cycleID="506" direction="DOWN" sectionID="sec_SconeLoop" speed="0.2" time="367.2063313928196" trackID="trk_SconeLoop_2" trainID="train35"/>
        <TrainHeadLeaveTrack cycleID="506" direction="UP" sectionID="sec_SconeLoop" speed="0.2" time="367.23966472615297" trackID="trk_SconeLoop_2" trainID="train35"/>
        <TrainTailLeaveTrack cycleID="506" direction="DOWN" sectionID="sec_SconeLoop" speed="54251.464192405634" time="367.26178394482963" trackID="trk_SconeLoop_2" trainID="train35"/>
        <TrainEnterTrack cycleID="529" direction="DOWN" sectionID="sec_SconeLoop" speed="0.2" time="402.0029499725507" trackID="trk_SconeLoop_2" trainID="train17"/>
        <TrainHeadLeaveTrack cycleID="529" direction="UP" sectionID="sec_SconeLoop" speed="0.2" time="402.03628330588407" trackID="trk_SconeLoop_2" trainID="train17"/>
        <TrainTailLeaveTrack cycleID="529" direction="DOWN" sectionID="sec_SconeLoop" speed="54251.464192405634" time="402.0547159881146" trackID="trk_SconeLoop_2" trainID="train17"/>
        <TrainEnterTrack cycleID="532" direction="DOWN" sectionID="sec_SconeLoop" speed="0.2" time="402.9877181874047" trackID="trk_SconeLoop_2" trainID="train14"/>
        <TrainHeadLeaveTrack cycleID="532" direction="UP" sectionID="sec_SconeLoop" speed="0.2" time="403.02105152073807" trackID="trk_SconeLoop_2" trainID="train14"/>
        <TrainTailLeaveTrack cycleID="532" direction="DOWN" sectionID="sec_SconeLoop" speed="54251.464192405634" time="403.04317073941473" trackID="trk_SconeLoop_2" trainID="train14"/>
        <TrainEnterTrack cycleID="552" direction="DOWN" sectionID="sec_SconeLoop" speed="0.2" time="407.01827019136505" trackID="trk_SconeLoop_2" trainID="train18"/>
        <TrainHeadLeaveTrack cycleID="552" direction="UP" sectionID="sec_SconeLoop" speed="0.2" time="407.0516035246984" trackID="trk_SconeLoop_2" trainID="train18"/>
        <TrainTailLeaveTrack cycleID="552" direction="DOWN" sectionID="sec_SconeLoop" speed="54251.464192405634" time="407.0737227433751" trackID="trk_SconeLoop_2" trainID="train18"/>
        <TrainEnterTrack cycleID="541" direction="DOWN" sectionID="sec_SconeLoop" speed="0.2" time="407.74992557628906" trackID="trk_SconeLoop_2" trainID="train44"/>
        <TrainHeadLeaveTrack cycleID="541" direction="UP" sectionID="sec_SconeLoop" speed="0.2" time="407.7832589096224" trackID="trk_SconeLoop_2" trainID="train44"/>
        <TrainTailLeaveTrack cycleID="541" direction="DOWN" sectionID="sec_SconeLoop" speed="54251.464192405634" time="407.8053781282991" trackID="trk_SconeLoop_2" trainID="train44"/>
        <TrainEnterTrack cycleID="547" direction="DOWN" sectionID="sec_SconeLoop" speed="0.2" time="411.1167596027141" trackID="trk_SconeLoop_2" trainID="train3"/>
        <TrainHeadLeaveTrack cycleID="547" direction="UP" sectionID="sec_SconeLoop" speed="0.2" time="411.1500929360475" trackID="trk_SconeLoop_2" trainID="train3"/>
        <TrainTailLeaveTrack cycleID="547" direction="DOWN" sectionID="sec_SconeLoop" speed="54251.464192405634" time="411.17221215472415" trackID="trk_SconeLoop_2" trainID="train3"/>
        <TrainEnterTrack cycleID="557" direction="DOWN" sectionID="sec_SconeLoop" speed="0.2" time="416.715548360417" trackID="trk_SconeLoop_2" trainID="train51"/>
        <TrainHeadLeaveTrack cycleID="557" direction="UP" sectionID="sec_SconeLoop" speed="0.2" time="416.7488816937504" trackID="trk_SconeLoop_2" trainID="train51"/>
        <TrainTailLeaveTrack cycleID="557" direction="DOWN" sectionID="sec_SconeLoop" speed="54251.464192405634" time="416.77100091242704" trackID="trk_SconeLoop_2" trainID="train51"/>
        <TrainEnterTrack cycleID="563" direction="DOWN" sectionID="sec_SconeLoop" speed="0.2" time="419.9721359840831" trackID="trk_SconeLoop_2" trainID="train6"/>
        <TrainHeadLeaveTrack cycleID="563" direction="UP" sectionID="sec_SconeLoop" speed="0.2" time="420.00546931741644" trackID="trk_SconeLoop_2" trainID="train6"/>
        <TrainTailLeaveTrack cycleID="563" direction="DOWN" sectionID="sec_SconeLoop" speed="54251.464192405634" time="420.02390199964697" trackID="trk_SconeLoop_2" trainID="train6"/>
        <TrainEnterTrack cycleID="564" direction="DOWN" sectionID="sec_SconeLoop" speed="0.2" time="420.3100171508032" trackID="trk_SconeLoop_2" trainID="train30"/>
        <TrainHeadLeaveTrack cycleID="564" direction="UP" sectionID="sec_SconeLoop" speed="0.2" time="420.3433504841366" trackID="trk_SconeLoop_2" trainID="train30"/>
        <TrainTailLeaveTrack cycleID="564" direction="DOWN" sectionID="sec_SconeLoop" speed="54251.464192405634" time="420.36546970281324" trackID="trk_SconeLoop_2" trainID="train30"/>
        <TrainEnterTrack cycleID="576" direction="DOWN" sectionID="sec_SconeLoop" speed="0.2" time="421.7614513478349" trackID="trk_SconeLoop_2" trainID="train39"/>
        <TrainHeadLeaveTrack cycleID="576" direction="UP" sectionID="sec_SconeLoop" speed="0.2" time="421.79478468116827" trackID="trk_SconeLoop_2" trainID="train39"/>
        <TrainTailLeaveTrack cycleID="576" direction="DOWN" sectionID="sec_SconeLoop" speed="54251.464192405634" time="421.81690389984493" trackID="trk_SconeLoop_2" trainID="train39"/>
        <TrainEnterTrack cycleID="579" direction="DOWN" sectionID="sec_SconeLoop" speed="0.2" time="428.34909127790036" trackID="trk_SconeLoop_2" trainID="train50"/>
        <TrainHeadLeaveTrack cycleID="579" direction="UP" sectionID="sec_SconeLoop" speed="0.2" time="428.3824246112337" trackID="trk_SconeLoop_2" trainID="train50"/>
        <TrainTailLeaveTrack cycleID="579" direction="DOWN" sectionID="sec_SconeLoop" speed="54251.464192405634" time="428.4045438299104" trackID="trk_SconeLoop_2" trainID="train50"/>
        <TrainEnterTrack cycleID="585" direction="DOWN" sectionID="sec_SconeLoop" speed="0.2" time="440.36252193975247" trackID="trk_SconeLoop_2" trainID="train53"/>
        <TrainHeadLeaveTrack cycleID="585" direction="UP" sectionID="sec_SconeLoop" speed="0.2" time="440.39585527308583" trackID="trk_SconeLoop_2" trainID="train53"/>
        <TrainTailLeaveTrack cycleID="585" direction="DOWN" sectionID="sec_SconeLoop" speed="54251.464192405634" time="440.4179744917625" trackID="trk_SconeLoop_2" trainID="train53"/>
        <TrainEnterTrack cycleID="586" direction="DOWN" sectionID="sec_SconeLoop" speed="0.2" time="440.98821592697175" trackID="trk_SconeLoop_2" trainID="train55"/>
        <TrainHeadLeaveTrack cycleID="586" direction="UP" sectionID="sec_SconeLoop" speed="0.2" time="441.0215492603051" trackID="trk_SconeLoop_2" trainID="train55"/>
        <TrainTailLeaveTrack cycleID="586" direction="DOWN" sectionID="sec_SconeLoop" speed="54251.464192405634" time="441.0436684789818" trackID="trk_SconeLoop_2" trainID="train55"/>
        <TrainEnterTrack cycleID="591" direction="DOWN" sectionID="sec_SconeLoop" speed="0.2" time="444.6226083573722" trackID="trk_SconeLoop_2" trainID="train25"/>
        <TrainHeadLeaveTrack cycleID="591" direction="UP" sectionID="sec_SconeLoop" speed="0.2" time="444.65594169070556" trackID="trk_SconeLoop_2" trainID="train25"/>
        <TrainTailLeaveTrack cycleID="591" direction="DOWN" sectionID="sec_SconeLoop" speed="54251.464192405634" time="444.6780609093822" trackID="trk_SconeLoop_2" trainID="train25"/>
        <TrainEnterTrack cycleID="599" direction="DOWN" sectionID="sec_SconeLoop" speed="0.2" time="449.1226083573722" trackID="trk_SconeLoop_2" trainID="train14"/>
        <TrainHeadLeaveTrack cycleID="599" direction="UP" sectionID="sec_SconeLoop" speed="0.2" time="449.15594169070556" trackID="trk_SconeLoop_2" trainID="train14"/>
        <TrainTailLeaveTrack cycleID="599" direction="DOWN" sectionID="sec_SconeLoop" speed="54251.464192405634" time="449.1780609093822" trackID="trk_SconeLoop_2" trainID="train14"/>
        <TrainEnterTrack cycleID="607" direction="DOWN" sectionID="sec_SconeLoop" speed="0.2" time="455.51537269856254" trackID="trk_SconeLoop_2" trainID="train3"/>
        <TrainHeadLeaveTrack cycleID="607" direction="UP" sectionID="sec_SconeLoop" speed="0.2" time="455.5487060318959" trackID="trk_SconeLoop_2" trainID="train3"/>
        <TrainTailLeaveTrack cycleID="607" direction="DOWN" sectionID="sec_SconeLoop" speed="54251.464192405634" time="455.57082525057257" trackID="trk_SconeLoop_2" trainID="train3"/>
        <TrainEnterTrack cycleID="617" direction="DOWN" sectionID="sec_SconeLoop" speed="0.2" time="468.22031817018444" trackID="trk_SconeLoop_2" trainID="train6"/>
        <TrainHeadLeaveTrack cycleID="617" direction="UP" sectionID="sec_SconeLoop" speed="0.2" time="468.2536515035178" trackID="trk_SconeLoop_2" trainID="train6"/>
        <TrainTailLeaveTrack cycleID="617" direction="DOWN" sectionID="sec_SconeLoop" speed="54251.464192405634" time="468.2720841857483" trackID="trk_SconeLoop_2" trainID="train6"/>
        <TrainEnterTrack cycleID="619" direction="DOWN" sectionID="sec_SconeLoop" speed="0.2" time="469.5684408949237" trackID="trk_SconeLoop_2" trainID="train47"/>
        <TrainHeadLeaveTrack cycleID="619" direction="UP" sectionID="sec_SconeLoop" speed="0.2" time="469.60177422825706" trackID="trk_SconeLoop_2" trainID="train47"/>
        <TrainTailLeaveTrack cycleID="619" direction="DOWN" sectionID="sec_SconeLoop" speed="54251.464192405634" time="469.6238934469337" trackID="trk_SconeLoop_2" trainID="train47"/>
        <TrainEnterTrack cycleID="622" direction="DOWN" sectionID="sec_SconeLoop" speed="0.2" time="473.0680922049159" trackID="trk_SconeLoop_2" trainID="train50"/>
        <TrainHeadLeaveTrack cycleID="622" direction="UP" sectionID="sec_SconeLoop" speed="0.2" time="473.10142553824926" trackID="trk_SconeLoop_2" trainID="train50"/>
        <TrainTailLeaveTrack cycleID="622" direction="DOWN" sectionID="sec_SconeLoop" speed="54251.464192405634" time="473.1235447569259" trackID="trk_SconeLoop_2" trainID="train50"/>
        <TrainEnterTrack cycleID="630" direction="DOWN" sectionID="sec_SconeLoop" speed="0.2" time="480.2175463148928" trackID="trk_SconeLoop_2" trainID="train53"/>
        <TrainHeadLeaveTrack cycleID="630" direction="UP" sectionID="sec_SconeLoop" speed="0.2" time="480.25087964822615" trackID="trk_SconeLoop_2" trainID="train53"/>
        <TrainTailLeaveTrack cycleID="630" direction="DOWN" sectionID="sec_SconeLoop" speed="54251.464192405634" time="480.2729988669028" trackID="trk_SconeLoop_2" trainID="train53"/>
        <TrainEnterTrack cycleID="638" direction="DOWN" sectionID="sec_SconeLoop" speed="0.2" time="486.35166401629" trackID="trk_SconeLoop_2" trainID="train38"/>
        <TrainHeadLeaveTrack cycleID="638" direction="UP" sectionID="sec_SconeLoop" speed="0.2" time="486.38499734962335" trackID="trk_SconeLoop_2" trainID="train38"/>
        <TrainTailLeaveTrack cycleID="638" direction="DOWN" sectionID="sec_SconeLoop" speed="54251.464192405634" time="486.4071165683" trackID="trk_SconeLoop_2" trainID="train38"/>
        <TrainEnterTrack cycleID="669" direction="DOWN" sectionID="sec_SconeLoop" speed="0.2" time="513.0937902296565" trackID="trk_SconeLoop_2" trainID="train45"/>
        <TrainHeadLeaveTrack cycleID="669" direction="UP" sectionID="sec_SconeLoop" speed="0.2" time="513.1271235629898" trackID="trk_SconeLoop_2" trainID="train45"/>
        <TrainTailLeaveTrack cycleID="669" direction="DOWN" sectionID="sec_SconeLoop" speed="54251.464192405634" time="513.1492427816664" trackID="trk_SconeLoop_2" trainID="train45"/>
        <TrainEnterTrack cycleID="670" direction="DOWN" sectionID="sec_SconeLoop" speed="0.2" time="517.1911612148309" trackID="trk_SconeLoop_2" trainID="train18"/>
        <TrainHeadLeaveTrack cycleID="670" direction="UP" sectionID="sec_SconeLoop" speed="0.2" time="517.2244945481642" trackID="trk_SconeLoop_2" trainID="train18"/>
        <TrainTailLeaveTrack cycleID="670" direction="DOWN" sectionID="sec_SconeLoop" speed="54251.464192405634" time="517.2466137668408" trackID="trk_SconeLoop_2" trainID="train18"/>
        <TrainEnterTrack cycleID="671" direction="DOWN" sectionID="sec_SconeLoop" speed="0.2" time="517.5899696478518" trackID="trk_SconeLoop_2" trainID="train44"/>
        <TrainHeadLeaveTrack cycleID="671" direction="UP" sectionID="sec_SconeLoop" speed="0.2" time="517.6233029811851" trackID="trk_SconeLoop_2" trainID="train44"/>
        <TrainTailLeaveTrack cycleID="671" direction="DOWN" sectionID="sec_SconeLoop" speed="54251.464192405634" time="517.6454221998617" trackID="trk_SconeLoop_2" trainID="train44"/>
        <TrainEnterTrack cycleID="681" direction="DOWN" sectionID="sec_SconeLoop" speed="0.2" time="527.2981581242417" trackID="trk_SconeLoop_2" trainID="train30"/>
        <TrainHeadLeaveTrack cycleID="681" direction="UP" sectionID="sec_SconeLoop" speed="0.2" time="527.331491457575" trackID="trk_SconeLoop_2" trainID="train30"/>
        <TrainTailLeaveTrack cycleID="681" direction="DOWN" sectionID="sec_SconeLoop" speed="54251.464192405634" time="527.3536106762516" trackID="trk_SconeLoop_2" trainID="train30"/>
        <TrainEnterTrack cycleID="685" direction="DOWN" sectionID="sec_SconeLoop" speed="0.2" time="527.9238521114611" trackID="trk_SconeLoop_2" trainID="train7"/>
        <TrainHeadLeaveTrack cycleID="685" direction="UP" sectionID="sec_SconeLoop" speed="0.2" time="527.9571854447944" trackID="trk_SconeLoop_2" trainID="train7"/>
        <TrainTailLeaveTrack cycleID="685" direction="DOWN" sectionID="sec_SconeLoop" speed="54251.464192405634" time="527.979304663471" trackID="trk_SconeLoop_2" trainID="train7"/>
        <TrainEnterTrack cycleID="679" direction="DOWN" sectionID="sec_SconeLoop" speed="0.2" time="528.4279301470934" trackID="trk_SconeLoop_2" trainID="train25"/>
        <TrainHeadLeaveTrack cycleID="679" direction="UP" sectionID="sec_SconeLoop" speed="0.2" time="528.4612634804267" trackID="trk_SconeLoop_2" trainID="train25"/>
        <TrainTailLeaveTrack cycleID="679" direction="DOWN" sectionID="sec_SconeLoop" speed="54251.464192405634" time="528.4833826991033" trackID="trk_SconeLoop_2" trainID="train25"/>
        <TrainEnterTrack cycleID="714" direction="DOWN" sectionID="sec_SconeLoop" speed="0.2" time="544.5521569675166" trackID="trk_SconeLoop_2" trainID="train55"/>
        <TrainHeadLeaveTrack cycleID="714" direction="UP" sectionID="sec_SconeLoop" speed="0.2" time="544.5854903008499" trackID="trk_SconeLoop_2" trainID="train55"/>
        <TrainTailLeaveTrack cycleID="714" direction="DOWN" sectionID="sec_SconeLoop" speed="54251.464192405634" time="544.6076095195265" trackID="trk_SconeLoop_2" trainID="train55"/>
        <TrainEnterTrack cycleID="716" direction="DOWN" sectionID="sec_SconeLoop" speed="0.2" time="546.4233029811851" trackID="trk_SconeLoop_2" trainID="train14"/>
        <TrainHeadLeaveTrack cycleID="716" direction="UP" sectionID="sec_SconeLoop" speed="0.2" time="546.4566363145184" trackID="trk_SconeLoop_2" trainID="train14"/>
        <TrainTailLeaveTrack cycleID="716" direction="DOWN" sectionID="sec_SconeLoop" speed="54251.464192405634" time="546.478755533195" trackID="trk_SconeLoop_2" trainID="train14"/>
        <TrainEnterTrack cycleID="737" direction="DOWN" sectionID="sec_SconeLoop" speed="0.2" time="565.5096035920927" trackID="trk_SconeLoop_2" trainID="train39"/>
        <TrainHeadLeaveTrack cycleID="737" direction="UP" sectionID="sec_SconeLoop" speed="0.2" time="565.542936925426" trackID="trk_SconeLoop_2" trainID="train39"/>
        <TrainTailLeaveTrack cycleID="737" direction="DOWN" sectionID="sec_SconeLoop" speed="54251.464192405634" time="565.5650561441026" trackID="trk_SconeLoop_2" trainID="train39"/>
        <TrainEnterTrack cycleID="734" direction="DOWN" sectionID="sec_SconeLoop" speed="0.2" time="566.4022456046275" trackID="trk_SconeLoop_2" trainID="train6"/>
        <TrainHeadLeaveTrack cycleID="734" direction="UP" sectionID="sec_SconeLoop" speed="0.2" time="566.4355789379608" trackID="trk_SconeLoop_2" trainID="train6"/>
        <TrainTailLeaveTrack cycleID="734" direction="DOWN" sectionID="sec_SconeLoop" speed="54251.464192405634" time="566.4540116201914" trackID="trk_SconeLoop_2" trainID="train6"/>
        <TrainEnterTrack cycleID="740" direction="DOWN" sectionID="sec_SconeLoop" speed="0.2" time="572.4559416907053" trackID="trk_SconeLoop_2" trainID="train35"/>
        <TrainHeadLeaveTrack cycleID="740" direction="UP" sectionID="sec_SconeLoop" speed="0.2" time="572.4892750240386" trackID="trk_SconeLoop_2" trainID="train35"/>
        <TrainTailLeaveTrack cycleID="740" direction="DOWN" sectionID="sec_SconeLoop" speed="54251.464192405634" time="572.5113942427153" trackID="trk_SconeLoop_2" trainID="train35"/>
        <TrainEnterTrack cycleID="741" direction="DOWN" sectionID="sec_SconeLoop" speed="0.2" time="572.7976795459396" trackID="trk_SconeLoop_2" trainID="train3"/>
        <TrainHeadLeaveTrack cycleID="741" direction="UP" sectionID="sec_SconeLoop" speed="0.2" time="572.8310128792729" trackID="trk_SconeLoop_2" trainID="train3"/>
        <TrainTailLeaveTrack cycleID="741" direction="DOWN" sectionID="sec_SconeLoop" speed="54251.464192405634" time="572.8531320979495" trackID="trk_SconeLoop_2" trainID="train3"/>
        <TrainEnterTrack cycleID="745" direction="DOWN" sectionID="sec_SconeLoop" speed="0.2" time="575.4559416907053" trackID="trk_SconeLoop_2" trainID="train30"/>
        <TrainHeadLeaveTrack cycleID="745" direction="UP" sectionID="sec_SconeLoop" speed="0.2" time="575.4892750240386" trackID="trk_SconeLoop_2" trainID="train30"/>
        <TrainTailLeaveTrack cycleID="745" direction="DOWN" sectionID="sec_SconeLoop" speed="54251.464192405634" time="575.5113942427153" trackID="trk_SconeLoop_2" trainID="train30"/>
        <TrainEnterTrack cycleID="748" direction="DOWN" sectionID="sec_SconeLoop" speed="0.2" time="578.3301683606959" trackID="trk_SconeLoop_2" trainID="train7"/>
        <TrainHeadLeaveTrack cycleID="748" direction="UP" sectionID="sec_SconeLoop" speed="0.2" time="578.3635016940292" trackID="trk_SconeLoop_2" trainID="train7"/>
        <TrainTailLeaveTrack cycleID="748" direction="DOWN" sectionID="sec_SconeLoop" speed="54251.464192405634" time="578.3856209127058" trackID="trk_SconeLoop_2" trainID="train7"/>
        <TrainEnterTrack cycleID="758" direction="DOWN" sectionID="sec_SconeLoop" speed="0.2" time="586.2077730966915" trackID="trk_SconeLoop_2" trainID="train55"/>
        <TrainHeadLeaveTrack cycleID="758" direction="UP" sectionID="sec_SconeLoop" speed="0.2" time="586.2411064300248" trackID="trk_SconeLoop_2" trainID="train55"/>
        <TrainTailLeaveTrack cycleID="758" direction="DOWN" sectionID="sec_SconeLoop" speed="54251.464192405634" time="586.2632256487015" trackID="trk_SconeLoop_2" trainID="train55"/>
        <TrainEnterTrack cycleID="762" direction="DOWN" sectionID="sec_SconeLoop" speed="0.2" time="587.3184947928964" trackID="trk_SconeLoop_2" trainID="train14"/>
        <TrainHeadLeaveTrack cycleID="762" direction="UP" sectionID="sec_SconeLoop" speed="0.2" time="587.3518281262297" trackID="trk_SconeLoop_2" trainID="train14"/>
        <TrainTailLeaveTrack cycleID="762" direction="DOWN" sectionID="sec_SconeLoop" speed="54251.464192405634" time="587.3739473449064" trackID="trk_SconeLoop_2" trainID="train14"/>
        <TrainEnterTrack cycleID="768" direction="DOWN" sectionID="sec_SconeLoop" speed="0.2" time="590.3822007713028" trackID="trk_SconeLoop_2" trainID="train47"/>
        <TrainHeadLeaveTrack cycleID="768" direction="UP" sectionID="sec_SconeLoop" speed="0.2" time="590.4155341046361" trackID="trk_SconeLoop_2" trainID="train47"/>
        <TrainTailLeaveTrack cycleID="768" direction="DOWN" sectionID="sec_SconeLoop" speed="54251.464192405634" time="590.4376533233127" trackID="trk_SconeLoop_2" trainID="train47"/>
        <TrainEnterTrack cycleID="769" direction="DOWN" sectionID="sec_SconeLoop" speed="0.2" time="591.4982024047617" trackID="trk_SconeLoop_2" trainID="train50"/>
        <TrainHeadLeaveTrack cycleID="769" direction="UP" sectionID="sec_SconeLoop" speed="0.2" time="591.531535738095" trackID="trk_SconeLoop_2" trainID="train50"/>
        <TrainTailLeaveTrack cycleID="769" direction="DOWN" sectionID="sec_SconeLoop" speed="54251.464192405634" time="591.5536549567717" trackID="trk_SconeLoop_2" trainID="train50"/>
        <TrainEnterTrack cycleID="771" direction="DOWN" sectionID="sec_SconeLoop" speed="0.2" time="591.9378844117072" trackID="trk_SconeLoop_2" trainID="train53"/>
        <TrainHeadLeaveTrack cycleID="771" direction="UP" sectionID="sec_SconeLoop" speed="0.2" time="591.9712177450405" trackID="trk_SconeLoop_2" trainID="train53"/>
        <TrainTailLeaveTrack cycleID="771" direction="DOWN" sectionID="sec_SconeLoop" speed="54251.464192405634" time="591.9933369637171" trackID="trk_SconeLoop_2" trainID="train53"/>
        <TrainEnterTrack cycleID="772" direction="DOWN" sectionID="sec_SconeLoop" speed="0.2" time="592.2955133470545" trackID="trk_SconeLoop_2" trainID="train38"/>
        <TrainHeadLeaveTrack cycleID="772" direction="UP" sectionID="sec_SconeLoop" speed="0.2" time="592.3288466803878" trackID="trk_SconeLoop_2" trainID="train38"/>
        <TrainTailLeaveTrack cycleID="772" direction="DOWN" sectionID="sec_SconeLoop" speed="54251.464192405634" time="592.3509658990644" trackID="trk_SconeLoop_2" trainID="train38"/>
        <TrainEnterTrack cycleID="774" direction="DOWN" sectionID="sec_SconeLoop" speed="0.2" time="594.0879256728507" trackID="trk_SconeLoop_2" trainID="train51"/>
        <TrainHeadLeaveTrack cycleID="774" direction="UP" sectionID="sec_SconeLoop" speed="0.2" time="594.121259006184" trackID="trk_SconeLoop_2" trainID="train51"/>
        <TrainTailLeaveTrack cycleID="774" direction="DOWN" sectionID="sec_SconeLoop" speed="54251.464192405634" time="594.1433782248606" trackID="trk_SconeLoop_2" trainID="train51"/>
        <TrainEnterTrack cycleID="781" direction="DOWN" sectionID="sec_SconeLoop" speed="0.2" time="596.2300301049503" trackID="trk_SconeLoop_2" trainID="train6"/>
        <TrainHeadLeaveTrack cycleID="781" direction="UP" sectionID="sec_SconeLoop" speed="0.2" time="596.2633634382836" trackID="trk_SconeLoop_2" trainID="train6"/>
        <TrainTailLeaveTrack cycleID="781" direction="DOWN" sectionID="sec_SconeLoop" speed="54251.464192405634" time="596.2817961205142" trackID="trk_SconeLoop_2" trainID="train6"/>
        <TrainEnterTrack cycleID="790" direction="DOWN" sectionID="sec_SconeLoop" speed="0.2" time="613.2780493867292" trackID="trk_SconeLoop_2" trainID="train35"/>
        <TrainHeadLeaveTrack cycleID="790" direction="UP" sectionID="sec_SconeLoop" speed="0.2" time="613.3113827200625" trackID="trk_SconeLoop_2" trainID="train35"/>
        <TrainTailLeaveTrack cycleID="790" direction="DOWN" sectionID="sec_SconeLoop" speed="54251.464192405634" time="613.3335019387391" trackID="trk_SconeLoop_2" trainID="train35"/>
        <TrainEnterTrack cycleID="799" direction="DOWN" sectionID="sec_SconeLoop" speed="0.2" time="621.7545011868946" trackID="trk_SconeLoop_2" trainID="train48"/>
        <TrainHeadLeaveTrack cycleID="799" direction="UP" sectionID="sec_SconeLoop" speed="0.2" time="621.7878345202279" trackID="trk_SconeLoop_2" trainID="train48"/>
        <TrainTailLeaveTrack cycleID="799" direction="DOWN" sectionID="sec_SconeLoop" speed="54251.464192405634" time="621.8099537389045" trackID="trk_SconeLoop_2" trainID="train48"/>
        <TrainEnterTrack cycleID="801" direction="DOWN" sectionID="sec_SconeLoop" speed="0.2" time="626.2204551671806" trackID="trk_SconeLoop_2" trainID="train18"/>
        <TrainHeadLeaveTrack cycleID="801" direction="UP" sectionID="sec_SconeLoop" speed="0.2" time="626.2537885005139" trackID="trk_SconeLoop_2" trainID="train18"/>
        <TrainTailLeaveTrack cycleID="801" direction="DOWN" sectionID="sec_SconeLoop" speed="54251.464192405634" time="626.2759077191905" trackID="trk_SconeLoop_2" trainID="train18"/>
        <TrainEnterTrack cycleID="814" direction="DOWN" sectionID="sec_SconeLoop" speed="0.2" time="629.7049189921757" trackID="trk_SconeLoop_2" trainID="train7"/>
        <TrainHeadLeaveTrack cycleID="814" direction="UP" sectionID="sec_SconeLoop" speed="0.2" time="629.738252325509" trackID="trk_SconeLoop_2" trainID="train7"/>
        <TrainTailLeaveTrack cycleID="814" direction="DOWN" sectionID="sec_SconeLoop" speed="54251.464192405634" time="629.7603715441857" trackID="trk_SconeLoop_2" trainID="train7"/>
        <TrainEnterTrack cycleID="808" direction="DOWN" sectionID="sec_SconeLoop" speed="0.2" time="630.9454944889428" trackID="trk_SconeLoop_2" trainID="train30"/>
        <TrainHeadLeaveTrack cycleID="808" direction="UP" sectionID="sec_SconeLoop" speed="0.2" time="630.9788278222761" trackID="trk_SconeLoop_2" trainID="train30"/>
        <TrainTailLeaveTrack cycleID="808" direction="DOWN" sectionID="sec_SconeLoop" speed="54251.464192405634" time="631.0009470409527" trackID="trk_SconeLoop_2" trainID="train30"/>
        <TrainEnterTrack cycleID="821" direction="DOWN" sectionID="sec_SconeLoop" speed="0.2" time="642.1226083573721" trackID="trk_SconeLoop_2" trainID="train14"/>
        <TrainHeadLeaveTrack cycleID="821" direction="UP" sectionID="sec_SconeLoop" speed="0.2" time="642.1559416907054" trackID="trk_SconeLoop_2" trainID="train14"/>
        <TrainTailLeaveTrack cycleID="821" direction="DOWN" sectionID="sec_SconeLoop" speed="54251.464192405634" time="642.178060909382" trackID="trk_SconeLoop_2" trainID="train14"/>
        <TrainEnterTrack cycleID="822" direction="DOWN" sectionID="sec_SconeLoop" speed="0.2" time="642.4710139949738" trackID="trk_SconeLoop_2" trainID="train47"/>
        <TrainHeadLeaveTrack cycleID="822" direction="UP" sectionID="sec_SconeLoop" speed="0.2" time="642.5043473283071" trackID="trk_SconeLoop_2" trainID="train47"/>
        <TrainTailLeaveTrack cycleID="822" direction="DOWN" sectionID="sec_SconeLoop" speed="54251.464192405634" time="642.5264665469837" trackID="trk_SconeLoop_2" trainID="train47"/>
        <TrainEnterTrack cycleID="830" direction="DOWN" sectionID="sec_SconeLoop" speed="0.2" time="656.1226083573721" trackID="trk_SconeLoop_2" trainID="train35"/>
        <TrainHeadLeaveTrack cycleID="830" direction="UP" sectionID="sec_SconeLoop" speed="0.2" time="656.1559416907054" trackID="trk_SconeLoop_2" trainID="train35"/>
        <TrainTailLeaveTrack cycleID="830" direction="DOWN" sectionID="sec_SconeLoop" speed="54251.464192405634" time="656.178060909382" trackID="trk_SconeLoop_2" trainID="train35"/>
        <TrainEnterTrack cycleID="832" direction="DOWN" sectionID="sec_SconeLoop" speed="0.2" time="658.6921173160274" trackID="trk_SconeLoop_2" trainID="train44"/>
        <TrainHeadLeaveTrack cycleID="832" direction="UP" sectionID="sec_SconeLoop" speed="0.2" time="658.7254506493607" trackID="trk_SconeLoop_2" trainID="train44"/>
        <TrainTailLeaveTrack cycleID="832" direction="DOWN" sectionID="sec_SconeLoop" speed="54251.464192405634" time="658.7475698680373" trackID="trk_SconeLoop_2" trainID="train44"/>
        <TrainEnterTrack cycleID="835" direction="DOWN" sectionID="sec_SconeLoop" speed="0.2" time="662.3324340642179" trackID="trk_SconeLoop_2" trainID="train48"/>
        <TrainHeadLeaveTrack cycleID="835" direction="UP" sectionID="sec_SconeLoop" speed="0.2" time="662.3657673975512" trackID="trk_SconeLoop_2" trainID="train48"/>
        <TrainTailLeaveTrack cycleID="835" direction="DOWN" sectionID="sec_SconeLoop" speed="54251.464192405634" time="662.3878866162278" trackID="trk_SconeLoop_2" trainID="train48"/>
        <TrainEnterTrack cycleID="904" direction="DOWN" sectionID="sec_SconeLoop" speed="0.2" time="736.7333858504538" trackID="trk_SconeLoop_2" trainID="train51"/>
        <TrainHeadLeaveTrack cycleID="904" direction="UP" sectionID="sec_SconeLoop" speed="0.2" time="736.7667191837871" trackID="trk_SconeLoop_2" trainID="train51"/>
        <TrainTailLeaveTrack cycleID="904" direction="DOWN" sectionID="sec_SconeLoop" speed="54251.464192405634" time="736.7888384024637" trackID="trk_SconeLoop_2" trainID="train51"/>
        <TrainEnterTrack cycleID="907" direction="DOWN" sectionID="sec_SconeLoop" speed="0.2" time="738.1226083573721" trackID="trk_SconeLoop_2" trainID="train50"/>
        <TrainHeadLeaveTrack cycleID="907" direction="UP" sectionID="sec_SconeLoop" speed="0.2" time="738.1559416907054" trackID="trk_SconeLoop_2" trainID="train50"/>
        <TrainTailLeaveTrack cycleID="907" direction="DOWN" sectionID="sec_SconeLoop" speed="54251.464192405634" time="738.178060909382" trackID="trk_SconeLoop_2" trainID="train50"/>
        <TrainEnterTrack cycleID="912" direction="DOWN" sectionID="sec_SconeLoop" speed="0.2" time="741.2566363145185" trackID="trk_SconeLoop_2" trainID="train35"/>
        <TrainHeadLeaveTrack cycleID="912" direction="UP" sectionID="sec_SconeLoop" speed="0.2" time="741.2899696478518" trackID="trk_SconeLoop_2" trainID="train35"/>
        <TrainTailLeaveTrack cycleID="912" direction="DOWN" sectionID="sec_SconeLoop" speed="54251.464192405634" time="741.3120888665284" trackID="trk_SconeLoop_2" trainID="train35"/>
        <TrainEnterTrack cycleID="921" direction="DOWN" sectionID="sec_SconeLoop" speed="0.2" time="744.4164960195823" trackID="trk_SconeLoop_2" trainID="train18"/>
        <TrainHeadLeaveTrack cycleID="921" direction="UP" sectionID="sec_SconeLoop" speed="0.2" time="744.4498293529156" trackID="trk_SconeLoop_2" trainID="train18"/>
        <TrainTailLeaveTrack cycleID="921" direction="DOWN" sectionID="sec_SconeLoop" speed="54251.464192405634" time="744.4719485715922" trackID="trk_SconeLoop_2" trainID="train18"/>
        <TrainEnterTrack cycleID="916" direction="DOWN" sectionID="sec_SconeLoop" speed="0.2" time="745.0017428198347" trackID="trk_SconeLoop_2" trainID="train44"/>
        <TrainHeadLeaveTrack cycleID="916" direction="UP" sectionID="sec_SconeLoop" speed="0.2" time="745.035076153168" trackID="trk_SconeLoop_2" trainID="train44"/>
        <TrainTailLeaveTrack cycleID="916" direction="DOWN" sectionID="sec_SconeLoop" speed="54251.464192405634" time="745.0571953718446" trackID="trk_SconeLoop_2" trainID="train44"/>
        <TrainEnterTrack cycleID="918" direction="DOWN" sectionID="sec_SconeLoop" speed="0.2" time="745.3434806750689" trackID="trk_SconeLoop_2" trainID="train30"/>
        <TrainHeadLeaveTrack cycleID="918" direction="UP" sectionID="sec_SconeLoop" speed="0.2" time="745.3768140084022" trackID="trk_SconeLoop_2" trainID="train30"/>
        <TrainTailLeaveTrack cycleID="918" direction="DOWN" sectionID="sec_SconeLoop" speed="54251.464192405634" time="745.3989332270788" trackID="trk_SconeLoop_2" trainID="train30"/>
        <TrainEnterTrack cycleID="926" direction="DOWN" sectionID="sec_SconeLoop" speed="0.2" time="752.1226083573721" trackID="trk_SconeLoop_2" trainID="train17"/>
        <TrainHeadLeaveTrack cycleID="926" direction="UP" sectionID="sec_SconeLoop" speed="0.2" time="752.1559416907054" trackID="trk_SconeLoop_2" trainID="train17"/>
        <TrainTailLeaveTrack cycleID="926" direction="DOWN" sectionID="sec_SconeLoop" speed="54251.464192405634" time="752.174374372936" trackID="trk_SconeLoop_2" trainID="train17"/>
        <TrainEnterTrack cycleID="937" direction="DOWN" sectionID="sec_SconeLoop" speed="0.2" time="764.3516868611928" trackID="trk_SconeLoop_2" trainID="train6"/>
        <TrainHeadLeaveTrack cycleID="937" direction="UP" sectionID="sec_SconeLoop" speed="0.2" time="764.3850201945261" trackID="trk_SconeLoop_2" trainID="train6"/>
        <TrainTailLeaveTrack cycleID="937" direction="DOWN" sectionID="sec_SconeLoop" speed="54251.464192405634" time="764.4034528767567" trackID="trk_SconeLoop_2" trainID="train6"/>
        <TrainEnterTrack cycleID="951" direction="DOWN" sectionID="sec_SconeLoop" speed="0.2" time="786.9559416907053" trackID="trk_SconeLoop_2" trainID="train25"/>
        <TrainHeadLeaveTrack cycleID="951" direction="UP" sectionID="sec_SconeLoop" speed="0.2" time="786.9892750240386" trackID="trk_SconeLoop_2" trainID="train25"/>
        <TrainTailLeaveTrack cycleID="951" direction="DOWN" sectionID="sec_SconeLoop" speed="54251.464192405634" time="787.0113942427153" trackID="trk_SconeLoop_2" trainID="train25"/>
        <TrainEnterTrack cycleID="958" direction="DOWN" sectionID="sec_SconeLoop" speed="0.2" time="795.2518058431161" trackID="trk_SconeLoop_2" trainID="train55"/>
        <TrainHeadLeaveTrack cycleID="958" direction="UP" sectionID="sec_SconeLoop" speed="0.2" time="795.2851391764494" trackID="trk_SconeLoop_2" trainID="train55"/>
        <TrainTailLeaveTrack cycleID="958" direction="DOWN" sectionID="sec_SconeLoop" speed="54251.464192405634" time="795.307258395126" trackID="trk_SconeLoop_2" trainID="train55"/>
        <TrainEnterTrack cycleID="971" direction="DOWN" sectionID="sec_SconeLoop" speed="0.2" time="804.2434799413348" trackID="trk_SconeLoop_2" trainID="train38"/>
        <TrainHeadLeaveTrack cycleID="971" direction="UP" sectionID="sec_SconeLoop" speed="0.2" time="804.2768132746681" trackID="trk_SconeLoop_2" trainID="train38"/>
        <TrainTailLeaveTrack cycleID="971" direction="DOWN" sectionID="sec_SconeLoop" speed="54251.464192405634" time="804.2989324933448" trackID="trk_SconeLoop_2" trainID="train38"/>
        <TrainEnterTrack cycleID="980" direction="DOWN" sectionID="sec_SconeLoop" speed="0.2" time="815.6160839452083" trackID="trk_SconeLoop_2" trainID="train51"/>
        <TrainHeadLeaveTrack cycleID="980" direction="UP" sectionID="sec_SconeLoop" speed="0.2" time="815.6494172785416" trackID="trk_SconeLoop_2" trainID="train51"/>
        <TrainTailLeaveTrack cycleID="980" direction="DOWN" sectionID="sec_SconeLoop" speed="54251.464192405634" time="815.6715364972182" trackID="trk_SconeLoop_2" trainID="train51"/>
        <TrainEnterTrack cycleID="984" direction="DOWN" sectionID="sec_SconeLoop" speed="0.2" time="820.7304968426829" trackID="trk_SconeLoop_2" trainID="train53"/>
        <TrainHeadLeaveTrack cycleID="984" direction="UP" sectionID="sec_SconeLoop" speed="0.2" time="820.7638301760162" trackID="trk_SconeLoop_2" trainID="train53"/>
        <TrainTailLeaveTrack cycleID="984" direction="DOWN" sectionID="sec_SconeLoop" speed="54251.464192405634" time="820.7859493946928" trackID="trk_SconeLoop_2" trainID="train53"/>
        <TrainEnterTrack cycleID="992" direction="DOWN" sectionID="sec_SconeLoop" speed="0.2" time="824.320024748783" trackID="trk_SconeLoop_2" trainID="train30"/>
        <TrainHeadLeaveTrack cycleID="992" direction="UP" sectionID="sec_SconeLoop" speed="0.2" time="824.3533580821163" trackID="trk_SconeLoop_2" trainID="train30"/>
        <TrainTailLeaveTrack cycleID="992" direction="DOWN" sectionID="sec_SconeLoop" speed="54251.464192405634" time="824.3754773007929" trackID="trk_SconeLoop_2" trainID="train30"/>
        <TrainEnterTrack cycleID="994" direction="DOWN" sectionID="sec_SconeLoop" speed="0.2" time="827.9161735860741" trackID="trk_SconeLoop_2" trainID="train44"/>
        <TrainHeadLeaveTrack cycleID="994" direction="UP" sectionID="sec_SconeLoop" speed="0.2" time="827.9495069194074" trackID="trk_SconeLoop_2" trainID="train44"/>
        <TrainTailLeaveTrack cycleID="994" direction="DOWN" sectionID="sec_SconeLoop" speed="54251.464192405634" time="827.971626138084" trackID="trk_SconeLoop_2" trainID="train44"/>
	</railEvents>
</railLog>